Workbook

Sheet Dashboard
A1: SOR/SCIP Static Dataset Update
A2: Updated on | B2: 2026-06-09 16:45
A3: Change made | B3: Deleted Alexianer GmbH; inserted Hochschule für Musik Mainz and Hochschule für Gesellschaftsgestaltung (HfGG).
A4: Members in universe M | B4: 102
A5: Concrete clusters K | B5: 24
A6: Candidate cards P | B6: 694
A7: SCIP model | B7: Binary weighted set-packing over Excel-defined candidate universe P.
A8: Objective | B8: maximize SUM(final_support_score_p * selected_x_p)
A9: Candidate generation | B9: For each cluster, pair members with relevance >=3; score and rank; keep top 30 per cluster.
A10: Scoring | B10: Static score = positive support components minus penalties. Live crawler/feedback can later add dynamic boosts.
A12: Update | B12: Static ZIRP info-box keyword radar added
A13: New sheet | B13: InfoBox_Keyword_Radar
A14: Members covered | B14: 103
A15: Dictionary | B15: Keyword_Dictionary
A16: Summary | B16: Keyword_Summary
A18: Update | B18: Role-weighted SCIP constraint layer added
A19: New sheets | B19: Role_Weights; Member_Role_Weights; Candidate_Role_Balance; SCIP_Role_Constraint_Readme
A20: Logic | B20: Each role gets total mass 1 via 1 / count(role). Candidate pair mass = weight(role_a)+weight(role_b).
A21: Use | B21: Use role_balanced_score as objective input and role exposure as SCIP audit/constraint.
A22: Created | B22: 2026-06-13

Sheet All_ZIRP_Members
A1: member_id | B1: member_name | C1: homepage | D1: actor_role | E1: actor_subrole | F1: cluster_count | G1: max_cluster_relevance | H1: broad_zirp_fields | I1: top_static_clusters
A2: 1 | B2: 1. FSV Mainz 05 e.V. | C2: https://www.mainz05.de | D2: context_actor | E2: sports_regional_identity_anchor | F2: 4 | G2: 5 | H2: gesellschaft, kultur | I2: Sport, Region und gesellschaftliche Identifikation (5); Kultur, Standortidentität und regionale Attraktivität (4); Demokratie, Medien und gesellschaftlicher Zusammenhalt (3); Kreativwirtschaft, Medien und digitale Öffentlichkeit (3)
A3: 2 | B3: AOK Rheinland-Pfalz/Saarland | C3: https://www.aok.de/rheinland-pfalz | D3: context_actor | E3: health_social_anchor | F3: 3 | G3: 5 | H3: gesellschaft | I3: Gesundheitsversorgung und Prävention (5); Pflege, Fachkräfte und Sozialwirtschaft (4); Sport, Region und gesellschaftliche Identifikation (4)
A4: 3 | B4: Architektenkammer Rheinland-Pfalz | C4: https://www.diearchitekten.org | D4: implementation_anchor | E4: construction_planning_anchor | F4: 3 | G4: 5 | H4: nachhaltigkeit, technologie | I4: Digitale Bau-, Planungs- und Genehmigungsprozesse (5); Klimaanpassung in Stadt und Land (4); Kreislaufwirtschaft, Bau und Ersatzbaustoffverordnung (4)
A5: 4 | B5: Aturas GmbH | C5: https://aturas.com | D5: profit_anchor | E5: technology_digital_anchor | F5: 4 | G5: 4 | H5: technologie, wirtschaft, wissen | I5: Digitale Bau-, Planungs- und Genehmigungsprozesse (4); KI, Daten und Verwaltungs-/Wirtschaftsanwendungen (4); Mittelstand, Digitalisierung und Produktivität (4); Verwaltungswissen und digitale Umsetzung (4)
A6: 5 | B6: Barmherzige Brüder Trier gGmbH | C6: https://www.bbtgruppe.de | D6: context_actor | E6: health_social_anchor | F6: 5 | G6: 5 | H6: gesellschaft, wirtschaft, wissen | I6: Pflege, Fachkräfte und Sozialwirtschaft (5); Arbeitsmarkt, Fachkräfte und Qualifizierung (4); Gesundheitsversorgung und Prävention (4); Teilhabe, Inklusion und Arbeitsmarkt (4); Weiterbildung und lebenslanges Lernen (4)
A7: 6 | B7: BASF SE | C7: https://www.basf.com | D7: profit_anchor | E7: industry_anchor | F7: 5 | G7: 5 | H7: nachhaltigkeit, technologie, wirtschaft, wissen | I7: Standort, Investition und industrielle Transformation (5); Energie, Netze und Versorgungssicherheit (4); Hochschule-Wirtschaft-Transfer (4); Industrie 4.0, Automatisierung und Produktion (4); Arbeitsmarkt, Fachkräfte und Qualifizierung (3)
A8: 7 | B8: Bauern- und Winzerverband Rheinland-Pfalz Süd e.V. | C8: https://www.bwv-rlp.de | D8: implementation_anchor | E8: agriculture_wine_anchor | F8: 1 | G8: 5 | H8: nachhaltigkeit | I8: Klimaanpassung in Stadt und Land (5)
A9: 8 | B9: Bauwirtschaft Rheinland-Pfalz e.V. | C9: https://www.bauwirtschaft-rlp.de | D9: context_actor | E9: construction_planning_anchor | F9: 3 | G9: 5 | H9: nachhaltigkeit, technologie | I9: Digitale Bau-, Planungs- und Genehmigungsprozesse (5); Kreislaufwirtschaft, Bau und Ersatzbaustoffverordnung (5); Klimaanpassung in Stadt und Land (4)
A10: 9 | B10: Bernd Hummel Holding GmbH | C10: https://www.bernd-hummel.de | D10: profit_anchor | E10: industry_anchor | F10: 0 | G10: 0
A11: 10 | B11: Bitburger Braugruppe GmbH | C11: https://www.bitburger-braugruppe.de | D11: profit_anchor | E11: food_beverage_consumer_anchor | F11: 1 | G11: 4 | H11: wirtschaft | I11: Standort, Investition und industrielle Transformation (4)
A12: 11 | B12: Boehringer Ingelheim Pharma GmbH & Co. KG | C12: https://www.boehringer-ingelheim.com/de | D12: profit_anchor | E12: health_social_anchor | F12: 5 | G12: 5 | H12: gesellschaft, wirtschaft, wissen | I12: Standort, Investition und industrielle Transformation (5); Gesundheitsversorgung und Prävention (4); Hochschule-Wirtschaft-Transfer (4); Arbeitsmarkt, Fachkräfte und Qualifizierung (3); Finanzierung und Förderung von Transformation (3)
A13: 12 | B13: BRICKMAKERS AG | C13: http://www.brickmakers.de | D13: profit_anchor | E13: technology_digital_anchor | F13: 5 | G13: 5 | H13: technologie, wirtschaft, wissen | I13: KI, Daten und Verwaltungs-/Wirtschaftsanwendungen (5); Mittelstand, Digitalisierung und Produktivität (5); Cyberresilienz und kritische Infrastruktur (4); Digitale Bau-, Planungs- und Genehmigungsprozesse (4); Hochschule-Wirtschaft-Transfer (4)
A14: 13 | B14: Bundesagentur für Arbeit, Regionaldirektion Rheinland-Pfalz-Saarland | C14: https://www.arbeitsagentur.de | D14: implementation_anchor | E14: public_policy_anchor | F14: 4 | G14: 5 | H14: gesellschaft, wirtschaft, wissen | I14: Arbeitsmarkt, Fachkräfte und Qualifizierung (5); Pflege, Fachkräfte und Sozialwirtschaft (5); Teilhabe, Inklusion und Arbeitsmarkt (5); Weiterbildung und lebenslanges Lernen (5)
A15: 14 | B15: Caritasverband für die Diözese Speyer e.V. | C15: https://www.caritas-speyer.de | D15: implementation_anchor | E15: health_social_anchor | F15: 5 | G15: 5 | H15: gesellschaft, wirtschaft | I15: Pflege, Fachkräfte und Sozialwirtschaft (5); Teilhabe, Inklusion und Arbeitsmarkt (5); Arbeitsmarkt, Fachkräfte und Qualifizierung (4); Demokratie, Medien und gesellschaftlicher Zusammenhalt (4); Gesundheitsversorgung und Prävention (4)
A16: 15 | B16: Continental Automotive Technologies GmbH, Safety and Motion (SAM), Standort Rheinböllen | C16: https://www.continental-corporation.de | D16: profit_anchor | E16: industry_anchor | F16: 2 | G16: 5 | H16: technologie, wirtschaft | I16: Industrie 4.0, Automatisierung und Produktion (5); Standort, Investition und industrielle Transformation (4)
A17: 16 | B17: Debeka Versicherungsgruppe | C17: https://www.debeka.de | D17: profit_anchor | E17: bank_finance_anchor | F17: 3 | G17: 4 | H17: technologie, wirtschaft | I17: Cyberresilienz und kritische Infrastruktur (4); Finanzierung und Förderung von Transformation (4); Standort, Investition und industrielle Transformation (4)
A18: 17 | B18: Deutsche Bundesbank, Hauptverwaltung in Rheinland-Pfalz und dem Saarland | C18: https://www.bundesbank.de | D18: context_actor | E18: bank_finance_anchor | F18: 1 | G18: 4 | H18: technologie | I18: Cyberresilienz und kritische Infrastruktur (4)
A19: 18 | B19: Deutsche Telekom AG | C19: https://www.telekom.de | D19: profit_anchor | E19: technology_digital_anchor | F19: 5 | G19: 5 | H19: kultur, technologie, wirtschaft | I19: Cyberresilienz und kritische Infrastruktur (5); KI, Daten und Verwaltungs-/Wirtschaftsanwendungen (5); Mittelstand, Digitalisierung und Produktivität (5); Industrie 4.0, Automatisierung und Produktion (4); Kreativwirtschaft, Medien und digitale Öffentlichkeit (4)
A20: 19 | B20: Deutsche Universität für Verwaltungswissenschaften Speyer | C20: https://www.uni-speyer.de | D20: academic_support | E20: university_research | F20: 5 | G20: 5 | H20: gesellschaft, technologie, wissen | I20: Demokratie, Medien und gesellschaftlicher Zusammenhalt (5); KI, Daten und Verwaltungs-/Wirtschaftsanwendungen (5); Verwaltungswissen und digitale Umsetzung (5); Wissenschaft, Demokratie und gesellschaftlicher Zusammenhalt (5); Digitale Bau-, Planungs- und Genehmigungsprozesse (4)
A21: 20 | B21: Deutscher Gewerkschaftsbund (DGB) Rheinland-Pfalz/Saarland | C21: https://rlp-saarland.dgb.de | D21: context_actor | E21: chamber_association_anchor | F21: 4 | G21: 5 | H21: gesellschaft, wirtschaft, wissen | I21: Arbeitsmarkt, Fachkräfte und Qualifizierung (5); Pflege, Fachkräfte und Sozialwirtschaft (4); Teilhabe, Inklusion und Arbeitsmarkt (4); Weiterbildung und lebenslanges Lernen (4)
A22: 21 | B22: Duale Hochschule Rheinland-Pfalz | C22: https://www.dh-rlp.de | D22: academic_support | E22: university_applied_sciences | F22: 4 | G22: 5 | H22: gesellschaft, wirtschaft, wissen | I22: Arbeitsmarkt, Fachkräfte und Qualifizierung (5); Weiterbildung und lebenslanges Lernen (5); Hochschule-Wirtschaft-Transfer (4); Pflege, Fachkräfte und Sozialwirtschaft (4)
... A29: 28 | B29: Evangelische Kirche der Pfalz | C29: https://www.evkirchepfalz.de | D29: context_actor | E29: culture_foundation_anchor | F29: 5 | G29: 5 | H29: gesellschaft, kultur, wissen | I29: Demokratie, Medien und gesellschaftlicher Zusammenhalt (5); Wissenschaft, Demokratie und gesellschaftlicher Zusammenhalt (5); Kultur, Standortidentität und regionale Attraktivität (4); Teilhabe, Inklusion und Arbeitsmarkt (4); Talentförderung, Musik und Nachwuchs (3)
A30: 29 | B30: Fachingen Heil- und Mineralbrunnen GmbH | C30: https://www.fachingen.de | D30: profit_anchor | E30: food_beverage_consumer_anchor | F30: 0 | G30: 0
A31: 30 | B31: Gerolsteiner Brunnen GmbH & Co. KG | C31: https://www.gerolsteiner.de | D31: profit_anchor | E31: food_beverage_consumer_anchor | F31: 0 | G31: 0
A32: 31 | B32: GLOBUS Markthallen Holding GmbH & Co. KG | C32: https://www.globus.de | D32: profit_anchor | E32: food_beverage_consumer_anchor | F32: 5 | G32: 4 | H32: gesellschaft, wirtschaft, wissen | I32: Standort, Investition und industrielle Transformation (4); Arbeitsmarkt, Fachkräfte und Qualifizierung (3); Sport, Region und gesellschaftliche Identifikation (3); Teilhabe, Inklusion und Arbeitsmarkt (3); Weiterbildung und lebenslanges Lernen (3)
A33: 32 | B33: Handwerkskammern Rheinland-Pfalz | C33: https://handwerk-rlp.de | D33: implementation_anchor | E33: chamber_association_anchor | F33: 5 | G33: 5 | H33: wirtschaft, wissen | I33: Arbeitsmarkt, Fachkräfte und Qualifizierung (5); Weiterbildung und lebenslanges Lernen (5); Hochschule-Wirtschaft-Transfer (4); Mittelstand, Digitalisierung und Produktivität (4); Finanzierung und Förderung von Transformation (3)
A34: 33 | B34: Heberger Gruppe | C34: https://www.heberger.de | D34: context_actor | E34: construction_planning_anchor | F34: 2 | G34: 4 | H34: nachhaltigkeit, technologie | I34: Kreislaufwirtschaft, Bau und Ersatzbaustoffverordnung (4); Digitale Bau-, Planungs- und Genehmigungsprozesse (3)
A35: 34 | B35: Hochschule für Gesellschaftsgestaltung (HfGG) | C35: https://www.hfgg.de/ | D35: academic_support | E35: university_applied_sciences | F35: 6 | G35: 5 | H35: gesellschaft, nachhaltigkeit, wissen | I35: Wissenschaft, Demokratie und gesellschaftlicher Zusammenhalt (5); Demokratie, Medien und gesellschaftlicher Zusammenhalt (4); Teilhabe, Inklusion und Arbeitsmarkt (4); Klimaanpassung in Stadt und Land (4); Hochschule-Wirtschaft-Transfer (3); Weiterbildung und lebenslanges Lernen (3)
A36: 35 | B36: Hochschule für Musik Mainz | C36: https://www.musik.uni-mainz.de/ | D36: academic_support | E36: university_applied_sciences | F36: 5 | G36: 5 | H36: kultur, wissen | I36: Talentförderung, Musik und Nachwuchs (5); Kultur, Standortidentität und regionale Attraktivität (4); Kreativwirtschaft, Medien und digitale Öffentlichkeit (3); Wissenschaft, Demokratie und gesellschaftlicher Zusammenhalt (3); Weiterbildung und lebenslanges Lernen (3)
A37: 36 | B37: Hochschule für Wirtschaft und Gesellschaft Ludwigshafen | C37: https://www.hwg-lu.de | D37: academic_support | E37: university_applied_sciences | F37: 4 | G37: 4 | H37: gesellschaft, wirtschaft, wissen | I37: Arbeitsmarkt, Fachkräfte und Qualifizierung (4); Hochschule-Wirtschaft-Transfer (4); Weiterbildung und lebenslanges Lernen (4); Gesundheitsversorgung und Prävention (3)
A38: 37 | B38: Hochschule Kaiserslautern | C38: https://www.hs-kl.de | D38: academic_support | E38: university_applied_sciences | F38: 5 | G38: 4 | H38: technologie, wirtschaft, wissen | I38: Arbeitsmarkt, Fachkräfte und Qualifizierung (4); Hochschule-Wirtschaft-Transfer (4); Industrie 4.0, Automatisierung und Produktion (4); KI, Daten und Verwaltungs-/Wirtschaftsanwendungen (4); Mittelstand, Digitalisierung und Produktivität (4)
A39: 38 | B39: Hochschule Koblenz | C39: https://www.hs-koblenz.de | D39: academic_support | E39: university_applied_sciences | F39: 5 | G39: 4 | H39: technologie, wirtschaft, wissen | I39: Arbeitsmarkt, Fachkräfte und Qualifizierung (4); Hochschule-Wirtschaft-Transfer (4); Weiterbildung und lebenslanges Lernen (4); KI, Daten und Verwaltungs-/Wirtschaftsanwendungen (3); Mittelstand, Digitalisierung und Produktivität (3)
A40: 39 | B40: Hochschule Mainz | C40: https://www.hs-mainz.de | D40: academic_support | E40: university_applied_sciences | F40: 5 | G40: 5 | H40: kultur, technologie, wirtschaft, wissen | I40: Digitale Bau-, Planungs- und Genehmigungsprozesse (5); Kreativwirtschaft, Medien und digitale Öffentlichkeit (5); Arbeitsmarkt, Fachkräfte und Qualifizierung (4); Hochschule-Wirtschaft-Transfer (4); KI, Daten und Verwaltungs-/Wirtschaftsanwendungen (4)
A41: 40 | B41: Hochschule Trier | C41: https://www.hochschule-trier.de | D41: academic_support | E41: university_applied_sciences | F41: 5 | G41: 4 | H41: nachhaltigkeit, technologie, wirtschaft, wissen | I41: Arbeitsmarkt, Fachkräfte und Qualifizierung (4); Hochschule-Wirtschaft-Transfer (4); Wasser, Umwelttechnik und kommunale Resilienz (4); Weiterbildung und lebenslanges Lernen (4); Industrie 4.0, Automatisierung und Produktion (3)
A42: 41 | B42: Hochschule Worms | C42: https://www.hs-worms.de | D42: academic_support | E42: university_applied_sciences | F42: 3 | G42: 4 | H42: wirtschaft, wissen | I42: Arbeitsmarkt, Fachkräfte und Qualifizierung (4); Hochschule-Wirtschaft-Transfer (4); Weiterbildung und lebenslanges Lernen (4)
A43: 42 | B43: IKK Südwest | C43: https://www.ikk-suedwest.de | D43: context_actor | E43: health_social_anchor | F43: 3 | G43: 5 | H43: gesellschaft | I43: Gesundheitsversorgung und Prävention (5); Pflege, Fachkräfte und Sozialwirtschaft (4); Sport, Region und gesellschaftliche Identifikation (4)
... A59: 58 | B59: KÜBLER GmbH | C59: https://www.kuebler-hallenheizungen.de | D59: profit_anchor | E59: energy_infrastructure_anchor | F59: 3 | G59: 4 | H59: nachhaltigkeit, technologie, wirtschaft | I59: Energie, Netze und Versorgungssicherheit (4); Industrie 4.0, Automatisierung und Produktion (3); Mittelstand, Digitalisierung und Produktivität (3)
A60: 59 | B60: L Q M Marktforschung GmbH | D60: profit_anchor | E60: professional_services_anchor | F60: 0 | G60: 0
A61: 60 | B61: Landesbank Baden-Württemberg (LBBW) | C61: https://www.lbbw.de | D61: profit_anchor | E61: bank_finance_anchor | F61: 4 | G61: 5 | H61: nachhaltigkeit, technologie, wirtschaft | I61: Finanzierung und Förderung von Transformation (5); Standort, Investition und industrielle Transformation (5); Cyberresilienz und kritische Infrastruktur (4); Energie, Netze und Versorgungssicherheit (3)
A62: 61 | B62: LandesPsychotherapeutenKammer Rheinland-Pfalz | C62: https://www.lpk-rlp.de | D62: implementation_anchor | E62: health_social_anchor | F62: 2 | G62: 4 | H62: gesellschaft | I62: Gesundheitsversorgung und Prävention (4); Pflege, Fachkräfte und Sozialwirtschaft (4)
A63: 62 | B63: Landesärztekammer Rheinland-Pfalz | C63: https://www.laek-rlp.de | D63: implementation_anchor | E63: health_social_anchor | F63: 2 | G63: 5 | H63: gesellschaft | I63: Gesundheitsversorgung und Prävention (5); Pflege, Fachkräfte und Sozialwirtschaft (4)
A64: 63 | B64: Landkreistag Rheinland-Pfalz | C64: https://www.landkreistag.rlp.de | D64: context_actor | E64: public_policy_anchor | F64: 5 | G64: 5 | H64: nachhaltigkeit, technologie, wissen | I64: Digitale Bau-, Planungs- und Genehmigungsprozesse (5); Klimaanpassung in Stadt und Land (5); Kreislaufwirtschaft, Bau und Ersatzbaustoffverordnung (5); Verwaltungswissen und digitale Umsetzung (5); Cyberresilienz und kritische Infrastruktur (4)
A65: 64 | B65: Leonardo PersonalKonzept GmbH | C65: https://www.leonardo-personal.de | D65: profit_anchor | E65: professional_services_anchor | F65: 4 | G65: 4 | H65: gesellschaft, wirtschaft, wissen | I65: Arbeitsmarkt, Fachkräfte und Qualifizierung (4); Teilhabe, Inklusion und Arbeitsmarkt (4); Pflege, Fachkräfte und Sozialwirtschaft (3); Weiterbildung und lebenslanges Lernen (3)
A66: 65 | B66: Licharz GmbH | C66: https://www.licharz.com | D66: profit_anchor | E66: industry_anchor | F66: 2 | G66: 3 | H66: technologie, wirtschaft | I66: Industrie 4.0, Automatisierung und Produktion (3); Mittelstand, Digitalisierung und Produktivität (3)
A67: 66 | B67: LOTTO Rheinland-Pfalz GmbH | C67: https://www.lotto-rlp.de | D67: profit_anchor | E67: culture_foundation_anchor | F67: 3 | G67: 4 | H67: gesellschaft, kultur | I67: Sport, Region und gesellschaftliche Identifikation (4); Kultur, Standortidentität und regionale Attraktivität (3); Talentförderung, Musik und Nachwuchs (3)
A68: 67 | B68: LÖWEN ENTERTAINMENT GmbH | C68: https://www.loewen.de | D68: profit_anchor | E68: technology_digital_anchor | F68: 0 | G68: 0
A69: 68 | B69: Mainzer Stadtwerke AG | C69: https://www.mainzer-stadtwerke.de | D69: profit_anchor | E69: energy_infrastructure_anchor | F69: 4 | G69: 5 | H69: nachhaltigkeit, technologie | I69: Cyberresilienz und kritische Infrastruktur (5); Energie, Netze und Versorgungssicherheit (5); Klimaanpassung in Stadt und Land (4); Wasser, Umwelttechnik und kommunale Resilienz (4)
A70: 69 | B70: Michelin Reifenwerke AG & Co. KGaA | C70: https://www.michelin.de | D70: profit_anchor | E70: industry_anchor | F70: 3 | G70: 4 | H70: nachhaltigkeit, technologie, wirtschaft | I70: Industrie 4.0, Automatisierung und Produktion (4); Standort, Investition und industrielle Transformation (4); Energie, Netze und Versorgungssicherheit (3)
A71: 70 | B71: Ministerium für Wirtschaft, Verkehr, Landwirtschaft und Weinbau | C71: https://mwvlw.rlp.de | D71: profit_anchor | E71: public_policy_anchor | F71: 5 | G71: 5 | H71: technologie, wirtschaft, wissen | I71: Finanzierung und Förderung von Transformation (5); Standort, Investition und industrielle Transformation (5); Verwaltungswissen und digitale Umsetzung (5); Arbeitsmarkt, Fachkräfte und Qualifizierung (4); Digitale Bau-, Planungs- und Genehmigungsprozesse (4)
A72: 71 | B72: PFAFF Industriesysteme und Maschinen GmbH | C72: https://www.pfaff-industrial.com | D72: profit_anchor | E72: industry_anchor | F72: 2 | G72: 5 | H72: technologie, wirtschaft | I72: Industrie 4.0, Automatisierung und Produktion (5); Mittelstand, Digitalisierung und Produktivität (4)
A73: 72 | B73: Pfalzwerke AG | C73: https://www.pfalzwerke.de | D73: profit_anchor | E73: energy_infrastructure_anchor | F73: 5 | G73: 5 | H73: nachhaltigkeit, technologie, wirtschaft | I73: Cyberresilienz und kritische Infrastruktur (5); Energie, Netze und Versorgungssicherheit (5); Finanzierung und Förderung von Transformation (3); Klimaanpassung in Stadt und Land (3); Wasser, Umwelttechnik und kommunale Resilienz (3)
A74: 73 | B74: Provinzial Versicherung AG | C74: http://www.provinzial.de | D74: profit_anchor | E74: bank_finance_anchor | F74: 2 | G74: 4 | H74: technologie, wirtschaft | I74: Cyberresilienz und kritische Infrastruktur (4); Finanzierung und Förderung von Transformation (4)
A75: 74 | B75: Rheinland-Pfälzische Technische Universität Kaiserslautern-Landau (RPTU) | C75: https://regionalentwicklung-raumordnung.de | D75: academic_support | E75: university_research | F75: 5 | G75: 5 | H75: technologie, wirtschaft, wissen | I75: Cyberresilienz und kritische Infrastruktur (5); Hochschule-Wirtschaft-Transfer (5); Industrie 4.0, Automatisierung und Produktion (5); KI, Daten und Verwaltungs-/Wirtschaftsanwendungen (5); Mittelstand, Digitalisierung und Produktivität (5)
A76: 75 | B76: robotspaceship | C76: https://www.robotspaceship.ai | D76: context_actor | E76: technology_digital_anchor | F76: 3 | G76: 5 | H76: kultur, technologie, wirtschaft | I76: KI, Daten und Verwaltungs-/Wirtschaftsanwendungen (5); Mittelstand, Digitalisierung und Produktivität (5); Kreativwirtschaft, Medien und digitale Öffentlichkeit (4)
A77: 76 | B77: RPR1. | C77: https://www.rpr1.de | D77: context_actor | E77: media_publicity_anchor | F77: 5 | G77: 5 | H77: gesellschaft, kultur, wissen | I77: Demokratie, Medien und gesellschaftlicher Zusammenhalt (5); Kreativwirtschaft, Medien und digitale Öffentlichkeit (5); Kultur, Standortidentität und regionale Attraktivität (4); Sport, Region und gesellschaftliche Identifikation (4); Wissenschaft, Demokratie und gesellschaftlicher Zusammenhalt (4)
A78: 77 | B78: Schoenergie GmbH | C78: http://www.schoenergie.de | D78: profit_anchor | E78: energy_infrastructure_anchor | F78: 1 | G78: 4 | H78: nachhaltigkeit | I78: Energie, Netze und Versorgungssicherheit (4)
A79: 78 | B79: SCHOTT AG | C79: https://www.schott.com | D79: profit_anchor | E79: industry_anchor | F79: 5 | G79: 5 | H79: nachhaltigkeit, technologie, wirtschaft, wissen | I79: Standort, Investition und industrielle Transformation (5); Energie, Netze und Versorgungssicherheit (4); Hochschule-Wirtschaft-Transfer (4); Industrie 4.0, Automatisierung und Produktion (4); Finanzierung und Förderung von Transformation (3)
A80: 79 | B80: Schuler Service GmbH & Co. KG | C80: https://www.schuler-service.com | D80: profit_anchor | E80: industry_anchor | F80: 0 | G80: 0
A81: 80 | B81: SIMONA AG | C81: https://www.simona.de | D81: profit_anchor | E81: industry_anchor | F81: 3 | G81: 4 | H81: nachhaltigkeit, technologie, wirtschaft | I81: Standort, Investition und industrielle Transformation (4); Energie, Netze und Versorgungssicherheit (3); Industrie 4.0, Automatisierung und Produktion (3)
A82: 81 | B82: SmartFactory KL e.V. | C82: https://smartfactory.de | D82: context_actor | E82: technology_digital_anchor | F82: 4 | G82: 5 | H82: technologie, wirtschaft, wissen | I82: Hochschule-Wirtschaft-Transfer (5); Industrie 4.0, Automatisierung und Produktion (5); Mittelstand, Digitalisierung und Produktivität (5); KI, Daten und Verwaltungs-/Wirtschaftsanwendungen (4)
A83: 82 | B83: Sparkassenverband Rheinland-Pfalz | C83: https://www.sv-rlp.de | D83: profit_anchor | E83: bank_finance_anchor | F83: 5 | G83: 5 | H83: technologie, wirtschaft, wissen | I83: Finanzierung und Förderung von Transformation (5); Cyberresilienz und kritische Infrastruktur (4); Standort, Investition und industrielle Transformation (4); Mittelstand, Digitalisierung und Produktivität (3); Verwaltungswissen und digitale Umsetzung (3)
A84: 83 | B84: Staatskanzlei des Landes Rheinland-Pfalz | C84: https://www.rlp.de/regierung/staatskanzlei | D84: context_actor | E84: public_policy_anchor | F84: 5 | G84: 5 | H84: gesellschaft, technologie, wissen | I84: Cyberresilienz und kritische Infrastruktur (5); Demokratie, Medien und gesellschaftlicher Zusammenhalt (5); Verwaltungswissen und digitale Umsetzung (5); Wissenschaft, Demokratie und gesellschaftlicher Zusammenhalt (5); Digitale Bau-, Planungs- und Genehmigungsprozesse (4)
A85: 84 | B85: Steuerberaterkammer Rheinland-Pfalz | C85: https://www.sbk-rlp.de | D85: implementation_anchor | E85: chamber_association_anchor | F85: 0 | G85: 0
A86: 85 | B86: Städtetag Rheinland-Pfalz | C86: https://www.staedtetag-rlp.de | D86: context_actor | E86: public_policy_anchor | F86: 5 | G86: 5 | H86: kultur, nachhaltigkeit, technologie, wissen | I86: Digitale Bau-, Planungs- und Genehmigungsprozesse (5); Klimaanpassung in Stadt und Land (5); Kreislaufwirtschaft, Bau und Ersatzbaustoffverordnung (5); Kultur, Standortidentität und regionale Attraktivität (5); Verwaltungswissen und digitale Umsetzung (5)
A87: 86 | B87: SWR – Südwestrundfunk | C87: https://www.swr.de | D87: context_actor | E87: media_publicity_anchor | F87: 5 | G87: 5 | H87: gesellschaft, kultur, wissen | I87: Demokratie, Medien und gesellschaftlicher Zusammenhalt (5); Kreativwirtschaft, Medien und digitale Öffentlichkeit (5); Kultur, Standortidentität und regionale Attraktivität (5); Wissenschaft, Demokratie und gesellschaftlicher Zusammenhalt (5); Talentförderung, Musik und Nachwuchs (4)
A88: 87 | B88: Techniker Krankenkasse | C88: https://www.tk.de/rp | D88: context_actor | E88: health_social_anchor | F88: 3 | G88: 5 | H88: gesellschaft | I88: Gesundheitsversorgung und Prävention (5); Pflege, Fachkräfte und Sozialwirtschaft (4); Sport, Region und gesellschaftliche Identifikation (4)
A89: 88 | B89: Technische Hochschule Bingen | C89: https://www.th-bingen.de | D89: academic_support | E89: university_applied_sciences | F89: 5 | G89: 4 | H89: nachhaltigkeit, technologie, wirtschaft, wissen | I89: Arbeitsmarkt, Fachkräfte und Qualifizierung (4); Digitale Bau-, Planungs- und Genehmigungsprozesse (4); Hochschule-Wirtschaft-Transfer (4); Industrie 4.0, Automatisierung und Produktion (4); Klimaanpassung in Stadt und Land (4)
A90: 89 | B90: thyssenkrupp Rasselstein GmbH | C90: https://www.thyssenkrupp-steel.com/de/unternehmen/business-units/packaging-steel/ | D90: profit_anchor | E90: industry_anchor | F90: 3 | G90: 5 | H90: nachhaltigkeit, technologie, wirtschaft | I90: Standort, Investition und industrielle Transformation (5); Energie, Netze und Versorgungssicherheit (4); Industrie 4.0, Automatisierung und Produktion (4)
A91: 90 | B91: Transdev GmbH | C91: https://www.transdev.de | D91: profit_anchor | E91: energy_infrastructure_anchor | F91: 1 | G91: 3 | H91: nachhaltigkeit | I91: Klimaanpassung in Stadt und Land (3)
A92: 91 | B92: TÜV Rheinland Berlin Brandenburg Pfalz e.V. | C92: https://www.tuv.com/germany/de/ | D92: context_actor | E92: chamber_association_anchor | F92: 5 | G92: 5 | H92: nachhaltigkeit, technologie | I92: Cyberresilienz und kritische Infrastruktur (5); Digitale Bau-, Planungs- und Genehmigungsprozesse (4); Industrie 4.0, Automatisierung und Produktion (4); KI, Daten und Verwaltungs-/Wirtschaftsanwendungen (4); Kreislaufwirtschaft, Bau und Ersatzbaustoffverordnung (4)
A93: 92 | B93: Universität Koblenz | C93: http://www.uni-koblenz.de | D93: academic_support | E93: university_research | F93: 5 | G93: 4 | H93: gesellschaft, technologie, wissen | I93: Demokratie, Medien und gesellschaftlicher Zusammenhalt (4); Hochschule-Wirtschaft-Transfer (4); KI, Daten und Verwaltungs-/Wirtschaftsanwendungen (4); Verwaltungswissen und digitale Umsetzung (4); Wissenschaft, Demokratie und gesellschaftlicher Zusammenhalt (4)
A94: 93 | B94: Universität Trier | C94: https://www.uni-trier.de | D94: academic_support | E94: university_research | F94: 5 | G94: 5 | H94: gesellschaft, technologie, wissen | I94: Wissenschaft, Demokratie und gesellschaftlicher Zusammenhalt (5); Cyberresilienz und kritische Infrastruktur (4); Demokratie, Medien und gesellschaftlicher Zusammenhalt (4); Hochschule-Wirtschaft-Transfer (4); KI, Daten und Verwaltungs-/Wirtschaftsanwendungen (4)
A95: 94 | B95: Vereinigte VR Bank Kur- und Rheinpfalz eG | C95: https://www.vvrbank-krp.de | D95: profit_anchor | E95: bank_finance_anchor | F95: 2 | G95: 4 | H95: wirtschaft | I95: Finanzierung und Förderung von Transformation (4); Standort, Investition und industrielle Transformation (3)
A96: 95 | B96: vero – Verband der Bau- und Rohstoffindustrie | C96: http://www.vero-baustoffe.de | D96: profit_anchor | E96: construction_planning_anchor | F96: 2 | G96: 5 | H96: nachhaltigkeit, technologie | I96: Digitale Bau-, Planungs- und Genehmigungsprozesse (5); Kreislaufwirtschaft, Bau und Ersatzbaustoffverordnung (5)
A97: 96 | B97: Villa Musica Rheinland-Pfalz | C97: https://www.villamusica.de | D97: context_actor | E97: culture_foundation_anchor | F97: 5 | G97: 5 | H97: gesellschaft, kultur, wissen | I97: Kultur, Standortidentität und regionale Attraktivität (5); Talentförderung, Musik und Nachwuchs (5); Kreativwirtschaft, Medien und digitale Öffentlichkeit (4); Demokratie, Medien und gesellschaftlicher Zusammenhalt (3); Wissenschaft, Demokratie und gesellschaftlicher Zusammenhalt (3)
... A104: 103 | B104: Alexianer GmbH | C104: https://www.alexianer.de/ | D104: context_actor | E104: health_social_anchor | F104: 4 | G104: 5 | H104: gesellschaft, wirtschaft, wissen | I104: Gesundheitsversorgung und Prävention (5); Pflege, Fachkräfte und Sozialwirtschaft (5); Teilhabe, Inklusion und Arbeitsmarkt (4); Dialog, Vernetzung und gesellschaftliche Verantwortung (4)

Sheet Candidate_Patterns
A1: candidate_id | B1: scip_variable | C1: selected_x | D1: member_a | E1: member_b | F1: member_a_id | G1: member_b_id | H1: role_a | I1: subrole_a | J1: role_b | K1: subrole_b | L1: themenfeld | M1: concrete_cluster | N1: cluster_label | O1: relevance_a | P1: relevance_b | Q1: shared_concrete_clusters | R1: complementary_topic_pairs | S1: momentum_from_event_count | T1: avg_decision_quality | U1: section_diversity | V1: role_complementarity | W1: application_capability_bridge | X1: broad_media_penalty | Y1: weak_profile_penalty | Z1: academic_only_penalty | AA1: abstract_overlap_penalty | AB1: final_support_score | AC1: static_cluster_problem | AD1: reasoning | AE1: member_pair_key | AF1: opportunity_key
A2: C0001 | B2: x_0001 | C2: 0 | D2: Architektenkammer Rheinland-Pfalz | E2: vero – Verband der Bau- und Rohstoffindustrie | F2: 3 | G2: 95 | H2: implementation_anchor | I2: construction_planning_anchor | J2: profit_anchor | K2: construction_planning_anchor | L2: technologie | M2: digitale_bau_verwaltung_planung | N2: Digitale Bau-, Planungs- und Genehmigungsprozesse | O2: 5 | P2: 5 | Q2: 14 | R2: 4 | S2: 0 | T2: 0 | U2: 2 | V2: 8 | W2: 8 | X2: 0 | Y2: 0 | Z2: 0 | AA2: 0 | AB2: 40.208485 | AC2: Wie können Bau, Planung, Genehmigung und Verwaltung durch digitale Werkzeuge schneller und rechtssicherer werden? | AD2: Digitale Bau-, Planungs- und Genehmigungsprozesse: Architektenkammer Rheinland-Pfalz (implementation_anchor, 5) + vero – Verband der Bau- und Rohstoffindustrie (profit_anchor, 5). | AE2: Architektenkammer Rheinland-Pfalz | vero – Verband der Bau- und Rohstoffindustrie | AF2: digitale-bau-verwaltung-planung-architektenkammer-rheinland-pfalz-vero-verband-der-bau-und-rohs
A3: C0002 | B3: x_0002 | C3: 0 | D3: Ingenieurkammer Rheinland-Pfalz | E3: vero – Verband der Bau- und Rohstoffindustrie | F3: 44 | G3: 95 | H3: implementation_anchor | I3: construction_planning_anchor | J3: profit_anchor | K3: construction_planning_anchor | L3: technologie | M3: digitale_bau_verwaltung_planung | N3: Digitale Bau-, Planungs- und Genehmigungsprozesse | O3: 5 | P3: 5 | Q3: 14 | R3: 4 | S3: 0 | T3: 0 | U3: 2 | V3: 8 | W3: 8 | X3: 0 | Y3: 0 | Z3: 0 | AA3: 0 | AB3: 40.208485 | AC3: Wie können Bau, Planung, Genehmigung und Verwaltung durch digitale Werkzeuge schneller und rechtssicherer werden? | AD3: Digitale Bau-, Planungs- und Genehmigungsprozesse: Ingenieurkammer Rheinland-Pfalz (implementation_anchor, 5) + vero – Verband der Bau- und Rohstoffindustrie (profit_anchor, 5). | AE3: Ingenieurkammer Rheinland-Pfalz | vero – Verband der Bau- und Rohstoffindustrie | AF3: digitale-bau-verwaltung-planung-ingenieurkammer-rheinland-pfalz-vero-verband-der-bau-und-rohsto
A4: C0003 | B4: x_0003 | C4: 0 | D4: Bundesagentur für Arbeit, Regionaldirektion Rheinland-Pfalz-Saarland | E4: Leonardo PersonalKonzept GmbH | F4: 13 | G4: 64 | H4: implementation_anchor | I4: public_policy_anchor | J4: profit_anchor | K4: professional_services_anchor | L4: wirtschaft | M4: arbeitsmarkt_fachkraefte | N4: Arbeitsmarkt, Fachkräfte und Qualifizierung | O4: 5 | P4: 4 | Q4: 13 | R4: 4 | S4: 0 | T4: 0 | U4: 2 | V4: 8 | W4: 8 | X4: 0 | Y4: 0 | Z4: 0 | AA4: 0 | AB4: 47.342258 | AC4: Wie sichern Unternehmen, Hochschulen, Kammern und Arbeitsverwaltung Fachkräfte für Transformation, Pflege, Technik und Verwaltung? | AD4: Arbeitsmarkt, Fachkräfte und Qualifizierung: Bundesagentur für Arbeit, Regionaldirektion Rheinland-Pfalz-Saarland (implementation_anchor, 5) + Leonardo PersonalKonzept GmbH (profit_anchor, 4). | AE4: Bundesagentur für Arbeit, Regionaldirektion Rheinland-Pfalz-Saarland | Leonardo PersonalKonzept GmbH | AF4: arbeitsmarkt-fachkraefte-bundesagentur-für-arbeit-regionaldirektion-rheinland-pfalz-saarland-le
A5: C0004 | B5: x_0004 | C5: 0 | D5: Bundesagentur für Arbeit, Regionaldirektion Rheinland-Pfalz-Saarland | E5: Ministerium für Wirtschaft, Verkehr, Landwirtschaft und Weinbau | F5: 13 | G5: 70 | H5: implementation_anchor | I5: public_policy_anchor | J5: profit_anchor | K5: public_policy_anchor | L5: wirtschaft | M5: arbeitsmarkt_fachkraefte | N5: Arbeitsmarkt, Fachkräfte und Qualifizierung | O5: 5 | P5: 4 | Q5: 13 | R5: 4 | S5: 0 | T5: 0 | U5: 2 | V5: 8 | W5: 8 | X5: 0 | Y5: 0 | Z5: 0 | AA5: 0 | AB5: 45.139072 | AC5: Wie sichern Unternehmen, Hochschulen, Kammern und Arbeitsverwaltung Fachkräfte für Transformation, Pflege, Technik und Verwaltung? | AD5: Arbeitsmarkt, Fachkräfte und Qualifizierung: Bundesagentur für Arbeit, Regionaldirektion Rheinland-Pfalz-Saarland (implementation_anchor, 5) + Ministerium für Wirtschaft, Verkehr, Landwirtschaft und Weinbau (profit_anchor, 4). | AE5: Bundesagentur für Arbeit, Regionaldirektion Rheinland-Pfalz-Saarland | Ministerium für Wirtschaft, Verkehr, Landwirtschaft und Weinbau | AF5: arbeitsmarkt-fachkraefte-bundesagentur-für-arbeit-regionaldirektion-rheinland-pfalz-saarland-mi
A6: C0005 | B6: x_0005 | C6: 0 | D6: Handwerkskammern Rheinland-Pfalz | E6: Leonardo PersonalKonzept GmbH | F6: 32 | G6: 64 | H6: implementation_anchor | I6: chamber_association_anchor | J6: profit_anchor | K6: professional_services_anchor | L6: wirtschaft | M6: arbeitsmarkt_fachkraefte | N6: Arbeitsmarkt, Fachkräfte und Qualifizierung | O6: 5 | P6: 4 | Q6: 13 | R6: 4 | S6: 0 | T6: 0 | U6: 2 | V6: 8 | W6: 8 | X6: 0 | Y6: 0 | Z6: 0 | AA6: 0 | AB6: 52.446862 | AC6: Wie sichern Unternehmen, Hochschulen, Kammern und Arbeitsverwaltung Fachkräfte für Transformation, Pflege, Technik und Verwaltung? | AD6: Arbeitsmarkt, Fachkräfte und Qualifizierung: Handwerkskammern Rheinland-Pfalz (implementation_anchor, 5) + Leonardo PersonalKonzept GmbH (profit_anchor, 4). | AE6: Handwerkskammern Rheinland-Pfalz | Leonardo PersonalKonzept GmbH | AF6: arbeitsmarkt-fachkraefte-handwerkskammern-rheinland-pfalz-leonardo-personalkonzept-gmbh
A7: C0006 | B7: x_0006 | C7: 0 | D7: Handwerkskammern Rheinland-Pfalz | E7: Ministerium für Wirtschaft, Verkehr, Landwirtschaft und Weinbau | F7: 32 | G7: 70 | H7: implementation_anchor | I7: chamber_association_anchor | J7: profit_anchor | K7: public_policy_anchor | L7: wirtschaft | M7: arbeitsmarkt_fachkraefte | N7: Arbeitsmarkt, Fachkräfte und Qualifizierung | O7: 5 | P7: 4 | Q7: 13 | R7: 4 | S7: 0 | T7: 0 | U7: 2 | V7: 8 | W7: 8 | X7: 0 | Y7: 0 | Z7: 0 | AA7: 0 | AB7: 50.467017 | AC7: Wie sichern Unternehmen, Hochschulen, Kammern und Arbeitsverwaltung Fachkräfte für Transformation, Pflege, Technik und Verwaltung? | AD7: Arbeitsmarkt, Fachkräfte und Qualifizierung: Handwerkskammern Rheinland-Pfalz (implementation_anchor, 5) + Ministerium für Wirtschaft, Verkehr, Landwirtschaft und Weinbau (profit_anchor, 4). | AE7: Handwerkskammern Rheinland-Pfalz | Ministerium für Wirtschaft, Verkehr, Landwirtschaft und Weinbau | AF7: arbeitsmarkt-fachkraefte-handwerkskammern-rheinland-pfalz-ministerium-für-wirtschaft-verkehr-la
A8: C0007 | B8: x_0007 | C8: 0 | D8: Architektenkammer Rheinland-Pfalz | E8: Aturas GmbH | F8: 3 | G8: 4 | H8: implementation_anchor | I8: construction_planning_anchor | J8: profit_anchor | K8: technology_digital_anchor | L8: technologie | M8: digitale_bau_verwaltung_planung | N8: Digitale Bau-, Planungs- und Genehmigungsprozesse | O8: 5 | P8: 4 | Q8: 13 | R8: 4 | S8: 0 | T8: 0 | U8: 2 | V8: 8 | W8: 8 | X8: 0 | Y8: 0 | Z8: 0 | AA8: 0 | AB8: 37.99019 | AC8: Wie können Bau, Planung, Genehmigung und Verwaltung durch digitale Werkzeuge schneller und rechtssicherer werden? | AD8: Digitale Bau-, Planungs- und Genehmigungsprozesse: Architektenkammer Rheinland-Pfalz (implementation_anchor, 5) + Aturas GmbH (profit_anchor, 4). | AE8: Architektenkammer Rheinland-Pfalz | Aturas GmbH | AF8: digitale-bau-verwaltung-planung-architektenkammer-rheinland-pfalz-aturas-gmbh
A9: C0008 | B9: x_0008 | C9: 0 | D9: Architektenkammer Rheinland-Pfalz | E9: BRICKMAKERS AG | F9: 3 | G9: 12 | H9: implementation_anchor | I9: construction_planning_anchor | J9: profit_anchor | K9: technology_digital_anchor | L9: technologie | M9: digitale_bau_verwaltung_planung | N9: Digitale Bau-, Planungs- und Genehmigungsprozesse | O9: 5 | P9: 4 | Q9: 13 | R9: 4 | S9: 0 | T9: 0 | U9: 2 | V9: 8 | W9: 8 | X9: 0 | Y9: 0 | Z9: 0 | AA9: 0 | AB9: 37.99019 | AC9: Wie können Bau, Planung, Genehmigung und Verwaltung durch digitale Werkzeuge schneller und rechtssicherer werden? | AD9: Digitale Bau-, Planungs- und Genehmigungsprozesse: Architektenkammer Rheinland-Pfalz (implementation_anchor, 5) + BRICKMAKERS AG (profit_anchor, 4). | AE9: Architektenkammer Rheinland-Pfalz | BRICKMAKERS AG | AF9: digitale-bau-verwaltung-planung-architektenkammer-rheinland-pfalz-brickmakers-ag
A10: C0009 | B10: x_0009 | C10: 0 | D10: Architektenkammer Rheinland-Pfalz | E10: Empolis Information Management GmbH | F10: 3 | G10: 23 | H10: implementation_anchor | I10: construction_planning_anchor | J10: profit_anchor | K10: technology_digital_anchor | L10: technologie | M10: digitale_bau_verwaltung_planung | N10: Digitale Bau-, Planungs- und Genehmigungsprozesse | O10: 5 | P10: 4 | Q10: 13 | R10: 4 | S10: 0 | T10: 0 | U10: 2 | V10: 8 | W10: 8 | X10: 0 | Y10: 0 | Z10: 0 | AA10: 0 | AB10: 37.99019 | AC10: Wie können Bau, Planung, Genehmigung und Verwaltung durch digitale Werkzeuge schneller und rechtssicherer werden? | AD10: Digitale Bau-, Planungs- und Genehmigungsprozesse: Architektenkammer Rheinland-Pfalz (implementation_anchor, 5) + Empolis Information Management GmbH (profit_anchor, 4). | AE10: Architektenkammer Rheinland-Pfalz | Empolis Information Management GmbH | AF10: digitale-bau-verwaltung-planung-architektenkammer-rheinland-pfalz-empolis-information-managemen
A11: C0010 | B11: x_0010 | C11: 0 | D11: Architektenkammer Rheinland-Pfalz | E11: Ministerium für Wirtschaft, Verkehr, Landwirtschaft und Weinbau | F11: 3 | G11: 70 | H11: implementation_anchor | I11: construction_planning_anchor | J11: profit_anchor | K11: public_policy_anchor | L11: technologie | M11: digitale_bau_verwaltung_planung | N11: Digitale Bau-, Planungs- und Genehmigungsprozesse | O11: 5 | P11: 4 | Q11: 13 | R11: 4 | S11: 0 | T11: 0 | U11: 2 | V11: 8 | W11: 8 | X11: 0 | Y11: 0 | Z11: 0 | AA11: 0 | AB11: 42.223735 | AC11: Wie können Bau, Planung, Genehmigung und Verwaltung durch digitale Werkzeuge schneller und rechtssicherer werden? | AD11: Digitale Bau-, Planungs- und Genehmigungsprozesse: Architektenkammer Rheinland-Pfalz (implementation_anchor, 5) + Ministerium für Wirtschaft, Verkehr, Landwirtschaft und Weinbau (profit_anchor, 4). | AE11: Architektenkammer Rheinland-Pfalz | Ministerium für Wirtschaft, Verkehr, Landwirtschaft und Weinbau | AF11: digitale-bau-verwaltung-planung-architektenkammer-rheinland-pfalz-ministerium-für-wirtschaft-ve
A12: C0011 | B12: x_0011 | C12: 0 | D12: Aturas GmbH | E12: Ingenieurkammer Rheinland-Pfalz | F12: 4 | G12: 44 | H12: profit_anchor | I12: technology_digital_anchor | J12: implementation_anchor | K12: construction_planning_anchor | L12: technologie | M12: digitale_bau_verwaltung_planung | N12: Digitale Bau-, Planungs- und Genehmigungsprozesse | O12: 4 | P12: 5 | Q12: 13 | R12: 4 | S12: 0 | T12: 0 | U12: 2 | V12: 8 | W12: 8 | X12: 0 | Y12: 0 | Z12: 0 | AA12: 0 | AB12: 37.99019 | AC12: Wie können Bau, Planung, Genehmigung und Verwaltung durch digitale Werkzeuge schneller und rechtssicherer werden? | AD12: Digitale Bau-, Planungs- und Genehmigungsprozesse: Aturas GmbH (profit_anchor, 4) + Ingenieurkammer Rheinland-Pfalz (implementation_anchor, 5). | AE12: Aturas GmbH | Ingenieurkammer Rheinland-Pfalz | AF12: digitale-bau-verwaltung-planung-aturas-gmbh-ingenieurkammer-rheinland-pfalz
A13: C0012 | B13: x_0012 | C13: 0 | D13: BRICKMAKERS AG | E13: Ingenieurkammer Rheinland-Pfalz | F13: 12 | G13: 44 | H13: profit_anchor | I13: technology_digital_anchor | J13: implementation_anchor | K13: construction_planning_anchor | L13: technologie | M13: digitale_bau_verwaltung_planung | N13: Digitale Bau-, Planungs- und Genehmigungsprozesse | O13: 4 | P13: 5 | Q13: 13 | R13: 4 | S13: 0 | T13: 0 | U13: 2 | V13: 8 | W13: 8 | X13: 0 | Y13: 0 | Z13: 0 | AA13: 0 | AB13: 37.99019 | AC13: Wie können Bau, Planung, Genehmigung und Verwaltung durch digitale Werkzeuge schneller und rechtssicherer werden? | AD13: Digitale Bau-, Planungs- und Genehmigungsprozesse: BRICKMAKERS AG (profit_anchor, 4) + Ingenieurkammer Rheinland-Pfalz (implementation_anchor, 5). | AE13: BRICKMAKERS AG | Ingenieurkammer Rheinland-Pfalz | AF13: digitale-bau-verwaltung-planung-brickmakers-ag-ingenieurkammer-rheinland-pfalz
... A695: C0694 | B695: x_0694 | C695: 0 | D695: Evangelische Kirche der Pfalz | E695: ZDF – Zweites Deutsches Fernsehen | F695: 28 | G695: 102 | H695: context_actor | I695: culture_foundation_anchor | J695: context_actor | K695: media_publicity_anchor | L695: kultur | M695: musikstipendium_talentfoerderung | N695: Talentförderung, Musik und Nachwuchs | O695: 3 | P695: 4 | Q695: 11 | R695: 2 | S695: 0 | T695: 0 | U695: 1 | V695: 3 | W695: 4 | X695: 0 | Y695: 0 | Z695: 0 | AA695: 4 | AB695: 24.782714 | AC695: Wie lassen sich kulturelle Talentförderung, Bildung und regionale Sichtbarkeit verbinden? | AD695: Talentförderung, Musik und Nachwuchs: Evangelische Kirche der Pfalz (context_actor, 3) + ZDF – Zweites Deutsches Fernsehen (context_actor, 4). | AE695: Evangelische Kirche der Pfalz | ZDF – Zweites Deutsches Fernsehen | AF695: musikstipendium-talentfoerderung-evangelische-kirche-der-pfalz-zdf-zweites-deutsches-fernsehen

Sheet Member_Constraints
A1: member_id | B1: member_name | C1: actor_role | D1: selected_count | E1: limit | F1: slack | G1: constraint_status
A2: 1 | B2: 1. FSV Mainz 05 e.V. | C2: context_actor | D2: =SUMIFS(Candidate_Patterns!$C:$C,Candidate_Patterns!$F:$F,A2)+SUMIFS(Candidate_Patterns!$C:$C,Candidate_Patterns!$G:$G,A2) | E2: 1 | F2: =E2-D2 | G2: =IF(F2>=0,"OK","VIOLATION")
A3: 2 | B3: AOK Rheinland-Pfalz/Saarland | C3: context_actor | D3: =SUMIFS(Candidate_Patterns!$C:$C,Candidate_Patterns!$F:$F,A3)+SUMIFS(Candidate_Patterns!$C:$C,Candidate_Patterns!$G:$G,A3) | E3: 1 | F3: =E3-D3 | G3: =IF(F3>=0,"OK","VIOLATION")
A4: 3 | B4: Architektenkammer Rheinland-Pfalz | C4: implementation_anchor | D4: =SUMIFS(Candidate_Patterns!$C:$C,Candidate_Patterns!$F:$F,A4)+SUMIFS(Candidate_Patterns!$C:$C,Candidate_Patterns!$G:$G,A4) | E4: 1 | F4: =E4-D4 | G4: =IF(F4>=0,"OK","VIOLATION")
A5: 4 | B5: Aturas GmbH | C5: profit_anchor | D5: =SUMIFS(Candidate_Patterns!$C:$C,Candidate_Patterns!$F:$F,A5)+SUMIFS(Candidate_Patterns!$C:$C,Candidate_Patterns!$G:$G,A5) | E5: 1 | F5: =E5-D5 | G5: =IF(F5>=0,"OK","VIOLATION")
A6: 5 | B6: Barmherzige Brüder Trier gGmbH | C6: context_actor | D6: =SUMIFS(Candidate_Patterns!$C:$C,Candidate_Patterns!$F:$F,A6)+SUMIFS(Candidate_Patterns!$C:$C,Candidate_Patterns!$G:$G,A6) | E6: 1 | F6: =E6-D6 | G6: =IF(F6>=0,"OK","VIOLATION")
A7: 6 | B7: BASF SE | C7: profit_anchor | D7: =SUMIFS(Candidate_Patterns!$C:$C,Candidate_Patterns!$F:$F,A7)+SUMIFS(Candidate_Patterns!$C:$C,Candidate_Patterns!$G:$G,A7) | E7: 1 | F7: =E7-D7 | G7: =IF(F7>=0,"OK","VIOLATION")
A8: 7 | B8: Bauern- und Winzerverband Rheinland-Pfalz Süd e.V. | C8: implementation_anchor | D8: =SUMIFS(Candidate_Patterns!$C:$C,Candidate_Patterns!$F:$F,A8)+SUMIFS(Candidate_Patterns!$C:$C,Candidate_Patterns!$G:$G,A8) | E8: 1 | F8: =E8-D8 | G8: =IF(F8>=0,"OK","VIOLATION")
A9: 8 | B9: Bauwirtschaft Rheinland-Pfalz e.V. | C9: context_actor | D9: =SUMIFS(Candidate_Patterns!$C:$C,Candidate_Patterns!$F:$F,A9)+SUMIFS(Candidate_Patterns!$C:$C,Candidate_Patterns!$G:$G,A9) | E9: 1 | F9: =E9-D9 | G9: =IF(F9>=0,"OK","VIOLATION")
A10: 9 | B10: Bernd Hummel Holding GmbH | C10: profit_anchor | D10: =SUMIFS(Candidate_Patterns!$C:$C,Candidate_Patterns!$F:$F,A10)+SUMIFS(Candidate_Patterns!$C:$C,Candidate_Patterns!$G:$G,A10) | E10: 1 | F10: =E10-D10 | G10: =IF(F10>=0,"OK","VIOLATION")
A11: 10 | B11: Bitburger Braugruppe GmbH | C11: profit_anchor | D11: =SUMIFS(Candidate_Patterns!$C:$C,Candidate_Patterns!$F:$F,A11)+SUMIFS(Candidate_Patterns!$C:$C,Candidate_Patterns!$G:$G,A11) | E11: 1 | F11: =E11-D11 | G11: =IF(F11>=0,"OK","VIOLATION")
A12: 11 | B12: Boehringer Ingelheim Pharma GmbH & Co. KG | C12: profit_anchor | D12: =SUMIFS(Candidate_Patterns!$C:$C,Candidate_Patterns!$F:$F,A12)+SUMIFS(Candidate_Patterns!$C:$C,Candidate_Patterns!$G:$G,A12) | E12: 1 | F12: =E12-D12 | G12: =IF(F12>=0,"OK","VIOLATION")
A13: 12 | B13: BRICKMAKERS AG | C13: profit_anchor | D13: =SUMIFS(Candidate_Patterns!$C:$C,Candidate_Patterns!$F:$F,A13)+SUMIFS(Candidate_Patterns!$C:$C,Candidate_Patterns!$G:$G,A13) | E13: 1 | F13: =E13-D13 | G13: =IF(F13>=0,"OK","VIOLATION")
... A103: 102 | B103: ZDF – Zweites Deutsches Fernsehen | C103: context_actor | D103: =SUMIFS(Candidate_Patterns!$C:$C,Candidate_Patterns!$F:$F,A103)+SUMIFS(Candidate_Patterns!$C:$C,Candidate_Patterns!$G:$G,A103) | E103: 1 | F103: =E103-D103 | G103: =IF(F103>=0,"OK","VIOLATION")

Sheet Cluster_Constraints
A1: concrete_cluster | B1: themenfeld | C1: cluster_label | D1: selected_count | E1: limit | F1: slack | G1: constraint_status
A2: energie_versorgungssicherheit | B2: nachhaltigkeit | C2: Energie, Netze und Versorgungssicherheit | D2: =SUMIFS(Candidate_Patterns!$C:$C,Candidate_Patterns!$K:$K,A2) | E2: 2 | F2: =E2-D2 | G2: =IF(F2>=0,"OK","VIOLATION")
A3: kreislaufwirtschaft_bau_ebv | B3: nachhaltigkeit | C3: Kreislaufwirtschaft, Bau und Ersatzbaustoffverordnung | D3: =SUMIFS(Candidate_Patterns!$C:$C,Candidate_Patterns!$K:$K,A3) | E3: 2 | F3: =E3-D3 | G3: =IF(F3>=0,"OK","VIOLATION")
A4: wasser_umwelttechnik_resilienz | B4: nachhaltigkeit | C4: Wasser, Umwelttechnik und kommunale Resilienz | D4: =SUMIFS(Candidate_Patterns!$C:$C,Candidate_Patterns!$K:$K,A4) | E4: 2 | F4: =E4-D4 | G4: =IF(F4>=0,"OK","VIOLATION")
A5: klima_anpassung_stadt_land | B5: nachhaltigkeit | C5: Klimaanpassung in Stadt und Land | D5: =SUMIFS(Candidate_Patterns!$C:$C,Candidate_Patterns!$K:$K,A5) | E5: 2 | F5: =E5-D5 | G5: =IF(F5>=0,"OK","VIOLATION")
A6: standort_investition_transformation | B6: wirtschaft | C6: Standort, Investition und industrielle Transformation | D6: =SUMIFS(Candidate_Patterns!$C:$C,Candidate_Patterns!$K:$K,A6) | E6: 2 | F6: =E6-D6 | G6: =IF(F6>=0,"OK","VIOLATION")
A7: mittelstand_digitalisierung_produktivitaet | B7: wirtschaft | C7: Mittelstand, Digitalisierung und Produktivität | D7: =SUMIFS(Candidate_Patterns!$C:$C,Candidate_Patterns!$K:$K,A7) | E7: 2 | F7: =E7-D7 | G7: =IF(F7>=0,"OK","VIOLATION")
A8: arbeitsmarkt_fachkraefte | B8: wirtschaft | C8: Arbeitsmarkt, Fachkräfte und Qualifizierung | D8: =SUMIFS(Candidate_Patterns!$C:$C,Candidate_Patterns!$K:$K,A8) | E8: 2 | F8: =E8-D8 | G8: =IF(F8>=0,"OK","VIOLATION")
A9: finanzierung_foerderung_transformation | B9: wirtschaft | C9: Finanzierung und Förderung von Transformation | D9: =SUMIFS(Candidate_Patterns!$C:$C,Candidate_Patterns!$K:$K,A9) | E9: 2 | F9: =E9-D9 | G9: =IF(F9>=0,"OK","VIOLATION")
A10: ki_daten_verwaltung_wirtschaft | B10: technologie | C10: KI, Daten und Verwaltungs-/Wirtschaftsanwendungen | D10: =SUMIFS(Candidate_Patterns!$C:$C,Candidate_Patterns!$K:$K,A10) | E10: 2 | F10: =E10-D10 | G10: =IF(F10>=0,"OK","VIOLATION")
A11: industrie_40_automation | B11: technologie | C11: Industrie 4.0, Automatisierung und Produktion | D11: =SUMIFS(Candidate_Patterns!$C:$C,Candidate_Patterns!$K:$K,A11) | E11: 2 | F11: =E11-D11 | G11: =IF(F11>=0,"OK","VIOLATION")
A12: cyber_resilienz_kritische_infrastruktur | B12: technologie | C12: Cyberresilienz und kritische Infrastruktur | D12: =SUMIFS(Candidate_Patterns!$C:$C,Candidate_Patterns!$K:$K,A12) | E12: 2 | F12: =E12-D12 | G12: =IF(F12>=0,"OK","VIOLATION")
A13: digitale_bau_verwaltung_planung | B13: technologie | C13: Digitale Bau-, Planungs- und Genehmigungsprozesse | D13: =SUMIFS(Candidate_Patterns!$C:$C,Candidate_Patterns!$K:$K,A13) | E13: 2 | F13: =E13-D13 | G13: =IF(F13>=0,"OK","VIOLATION")
... A25: sport_region_identifikation | B25: gesellschaft | C25: Sport, Region und gesellschaftliche Identifikation | D25: =SUMIFS(Candidate_Patterns!$C:$C,Candidate_Patterns!$K:$K,A25) | E25: 2 | F25: =E25-D25 | G25: =IF(F25>=0,"OK","VIOLATION")

Sheet Static_Clusters
A1: concrete_cluster | B1: themenfeld | C1: cluster_label | D1: static_problem_question | E1: signal_keywords | F1: priority_weight
A2: energie_versorgungssicherheit | B2: nachhaltigkeit | C2: Energie, Netze und Versorgungssicherheit | D2: Wie bleiben Unternehmen, Kommunen und Infrastrukturträger in Rheinland-Pfalz investitions- und versorgungssicher? | E2: energiepreise, strompreise, wärme, waerme, netzausbau, versorgungssicherheit, erneuerbare energien, speicher, photovoltaik, wasserstoff, standortkosten, energieintensive industrie | F2: 8.8
A3: kreislaufwirtschaft_bau_ebv | B3: nachhaltigkeit | C3: Kreislaufwirtschaft, Bau und Ersatzbaustoffverordnung | D3: Wie können Bauwirtschaft, Rohstoffindustrie, Kommunen und Verwaltung Kreislaufwirtschaft praktisch und rechtssicher umsetzen? | E3: ersatzbaustoffverordnung, ebv, einbaukarte, recyclingbaustoffe, rohstoffindustrie, bauwirtschaft, kommunen, verwaltung, planungssicherheit, regulierung, genehmigung | F3: 9
A4: wasser_umwelttechnik_resilienz | B4: nachhaltigkeit | C4: Wasser, Umwelttechnik und kommunale Resilienz | D4: Wie können Kommunen und Infrastrukturträger Wasser-, Abwasser- und Umwelttechnik digitaler und resilienter steuern? | E4: wasser, abwasser, umwelttechnik, prozesssteuerung, sensorik, cloud, kommunale infrastruktur, klimafolgen, resilienz, versorgung, entsorgung | F4: 7.7
A5: klima_anpassung_stadt_land | B5: nachhaltigkeit | C5: Klimaanpassung in Stadt und Land | D5: Wie reagieren Kommunen, Bauwirtschaft, Landwirtschaft und Infrastruktur auf Hitze, Starkregen und Flächendruck? | E5: starkregen, hitze, klimaanpassung, flächenverbrauch, flaechenverbrauch, innenstadt, mobilität, mobilitaet, stadtentwicklung, biodiversität, biodiversitaet, landwirtschaft, kommunen | F5: 5
A6: standort_investition_transformation | B6: wirtschaft | C6: Standort, Investition und industrielle Transformation | D6: Welche Standortbedingungen entscheiden darüber, ob Unternehmen in Rheinland-Pfalz investieren, modernisieren oder verlagern? | E6: investition, standort, produktion, werk, kapazität, kapazitaet, arbeitsplätze, arbeitsplaetze, modernisierung, transformation, wettbewerbsfähigkeit, wettbewerbsfaehigkeit, industrie, export, lieferketten | F6: 7.5
A7: mittelstand_digitalisierung_produktivitaet | B7: wirtschaft | C7: Mittelstand, Digitalisierung und Produktivität | D7: Wie können mittelständische Unternehmen digitale Werkzeuge praktisch einsetzen, ohne dass daraus nur Pilotprojekte entstehen? | E7: digitalisierung, mittelstand, produktivität, produktivitaet, automatisierung, ki, software, plattform, prozessoptimierung, industrie 4.0, cloud, erp | F7: 5
A8: arbeitsmarkt_fachkraefte | B8: wirtschaft | C8: Arbeitsmarkt, Fachkräfte und Qualifizierung | D8: Wie sichern Unternehmen, Hochschulen, Kammern und Arbeitsverwaltung Fachkräfte für Transformation, Pflege, Technik und Verwaltung? | E8: fachkräfte, fachkraefte, ausbildung, weiterbildung, qualifizierung, duale ausbildung, arbeitsmarkt, personal, recruiting, integration, zuwanderung, nachwuchs | F8: 8.6
A9: finanzierung_foerderung_transformation | B9: wirtschaft | C9: Finanzierung und Förderung von Transformation | D9: Wie kommen Investitionen, Fördermittel, Banken und Unternehmensstrategien schneller zusammen? | E9: förderung, foerderung, finanzierung, kredit, investition, kapital, transformation, mittelstand, nachfolge, innovation, risiko, bank | F9: 5
A10: ki_daten_verwaltung_wirtschaft | B10: technologie | C10: KI, Daten und Verwaltungs-/Wirtschaftsanwendungen | D10: Wo können KI und Datenplattformen in Unternehmen, Verwaltung und öffentlicher Infrastruktur konkret Nutzen stiften? | E10: ki, künstliche intelligenz, kuenstliche intelligenz, daten, plattform, automatisierung, verwaltung, e-government, prozessdigitalisierung, chatbot, wissensmanagement | F10: 7.9
A11: industrie_40_automation | B11: technologie | C11: Industrie 4.0, Automatisierung und Produktion | D11: Wie wird industrielle Produktion in Rheinland-Pfalz digitaler, robuster und wettbewerbsfähiger? | E11: industrie 4.0, automatisierung, produktion, sensorik, maschinenbau, digitaler zwilling, robotik, prozesssteuerung, fertigung, smart factory | F11: 5
A12: cyber_resilienz_kritische_infrastruktur | B12: technologie | C12: Cyberresilienz und kritische Infrastruktur | D12: Wie schützen Unternehmen, Kommunen und Versorger digitale Systeme, Daten und kritische Infrastruktur? | E12: cybersicherheit, it-sicherheit, resilienz, kritische infrastruktur, krisenmanagement, datenschutz, cloud, netzwerke, kommunen, versorgung | F12: 5
A13: digitale_bau_verwaltung_planung | B13: technologie | C13: Digitale Bau-, Planungs- und Genehmigungsprozesse | D13: Wie können Bau, Planung, Genehmigung und Verwaltung durch digitale Werkzeuge schneller und rechtssicherer werden? | E13: bim, planung, genehmigung, bauverwaltung, einbaukarte, ersatzbaustoffverordnung, kommunen, verwaltung, digitales tool, plattform | F13: 7.4
... A25: sport_region_identifikation | B25: gesellschaft | C25: Sport, Region und gesellschaftliche Identifikation | D25: Wie können Sportvereine als regionale Plattformen für Bildung, Teilhabe, Gesundheit oder Standortbindung wirken? | E25: sport, verein, nachwuchs, bildung, gesundheit, integration, fans, region, identifikation, gesellschaftliches engagement | F25: 5

Sheet Member_Cluster_Matrix
A1: member_id | B1: member_name | C1: actor_role | D1: energie_versorgungssicherheit | E1: kreislaufwirtschaft_bau_ebv | F1: wasser_umwelttechnik_resilienz | G1: klima_anpassung_stadt_land | H1: standort_investition_transformation | I1: mittelstand_digitalisierung_produktivitaet | J1: arbeitsmarkt_fachkraefte | K1: finanzierung_foerderung_transformation | L1: ki_daten_verwaltung_wirtschaft | M1: industrie_40_automation | N1: cyber_resilienz_kritische_infrastruktur | O1: digitale_bau_verwaltung_planung | P1: kultur_standort_identitaet | Q1: kreativwirtschaft_digitale_medien | R1: musikstipendium_talentfoerderung | S1: hochschule_wirtschaft_transfer | T1: weiterbildung_lebenslanges_lernen | U1: wissenschaft_demokratie_gesellschaft | V1: verwaltungswissen_digitalisierung | W1: gesundheit_versorgung_praevention | X1: pflege_fachkraefte_sozialwirtschaft | Y1: teilhabe_inklusion_arbeitsmarkt | Z1: demokratie_medien_zusammenhalt | AA1: sport_region_identifikation
A2: 1 | B2: 1. FSV Mainz 05 e.V. | C2: context_actor | D2: 0 | E2: 0 | F2: 0 | G2: 0 | H2: 0 | I2: 0 | J2: 0 | K2: 0 | L2: 0 | M2: 0 | N2: 0 | O2: 0 | P2: 4 | Q2: 3 | R2: 0 | S2: 0 | T2: 0 | U2: 0 | V2: 0 | W2: 0 | X2: 0 | Y2: 0 | Z2: 3 | AA2: 5
A3: 2 | B3: AOK Rheinland-Pfalz/Saarland | C3: context_actor | D3: 0 | E3: 0 | F3: 0 | G3: 0 | H3: 0 | I3: 0 | J3: 0 | K3: 0 | L3: 0 | M3: 0 | N3: 0 | O3: 0 | P3: 0 | Q3: 0 | R3: 0 | S3: 0 | T3: 0 | U3: 0 | V3: 0 | W3: 5 | X3: 4 | Y3: 0 | Z3: 0 | AA3: 4
A4: 3 | B4: Architektenkammer Rheinland-Pfalz | C4: implementation_anchor | D4: 0 | E4: 4 | F4: 0 | G4: 4 | H4: 0 | I4: 0 | J4: 0 | K4: 0 | L4: 0 | M4: 0 | N4: 0 | O4: 5 | P4: 0 | Q4: 0 | R4: 0 | S4: 0 | T4: 0 | U4: 0 | V4: 0 | W4: 0 | X4: 0 | Y4: 0 | Z4: 0 | AA4: 0
A5: 4 | B5: Aturas GmbH | C5: profit_anchor | D5: 0 | E5: 0 | F5: 0 | G5: 0 | H5: 0 | I5: 4 | J5: 0 | K5: 0 | L5: 4 | M5: 0 | N5: 0 | O5: 4 | P5: 0 | Q5: 0 | R5: 0 | S5: 0 | T5: 0 | U5: 0 | V5: 4 | W5: 0 | X5: 0 | Y5: 0 | Z5: 0 | AA5: 0
A6: 5 | B6: Barmherzige Brüder Trier gGmbH | C6: context_actor | D6: 0 | E6: 0 | F6: 0 | G6: 0 | H6: 0 | I6: 0 | J6: 4 | K6: 0 | L6: 0 | M6: 0 | N6: 0 | O6: 0 | P6: 0 | Q6: 0 | R6: 0 | S6: 0 | T6: 4 | U6: 0 | V6: 0 | W6: 4 | X6: 5 | Y6: 4 | Z6: 0 | AA6: 0
A7: 6 | B7: BASF SE | C7: profit_anchor | D7: 4 | E7: 0 | F7: 0 | G7: 0 | H7: 5 | I7: 0 | J7: 3 | K7: 0 | L7: 0 | M7: 4 | N7: 0 | O7: 0 | P7: 0 | Q7: 0 | R7: 0 | S7: 4 | T7: 0 | U7: 0 | V7: 0 | W7: 0 | X7: 0 | Y7: 0 | Z7: 0 | AA7: 0
A8: 7 | B8: Bauern- und Winzerverband Rheinland-Pfalz Süd e.V. | C8: implementation_anchor | D8: 0 | E8: 0 | F8: 0 | G8: 5 | H8: 0 | I8: 0 | J8: 0 | K8: 0 | L8: 0 | M8: 0 | N8: 0 | O8: 0 | P8: 0 | Q8: 0 | R8: 0 | S8: 0 | T8: 0 | U8: 0 | V8: 0 | W8: 0 | X8: 0 | Y8: 0 | Z8: 0 | AA8: 0
A9: 8 | B9: Bauwirtschaft Rheinland-Pfalz e.V. | C9: context_actor | D9: 0 | E9: 5 | F9: 0 | G9: 4 | H9: 0 | I9: 0 | J9: 0 | K9: 0 | L9: 0 | M9: 0 | N9: 0 | O9: 5 | P9: 0 | Q9: 0 | R9: 0 | S9: 0 | T9: 0 | U9: 0 | V9: 0 | W9: 0 | X9: 0 | Y9: 0 | Z9: 0 | AA9: 0
A10: 9 | B10: Bernd Hummel Holding GmbH | C10: profit_anchor | D10: 0 | E10: 0 | F10: 0 | G10: 0 | H10: 0 | I10: 0 | J10: 0 | K10: 0 | L10: 0 | M10: 0 | N10: 0 | O10: 0 | P10: 0 | Q10: 0 | R10: 0 | S10: 0 | T10: 0 | U10: 0 | V10: 0 | W10: 0 | X10: 0 | Y10: 0 | Z10: 0 | AA10: 0
A11: 10 | B11: Bitburger Braugruppe GmbH | C11: profit_anchor | D11: 0 | E11: 0 | F11: 0 | G11: 0 | H11: 4 | I11: 0 | J11: 0 | K11: 0 | L11: 0 | M11: 0 | N11: 0 | O11: 0 | P11: 0 | Q11: 0 | R11: 0 | S11: 0 | T11: 0 | U11: 0 | V11: 0 | W11: 0 | X11: 0 | Y11: 0 | Z11: 0 | AA11: 0
A12: 11 | B12: Boehringer Ingelheim Pharma GmbH & Co. KG | C12: profit_anchor | D12: 0 | E12: 0 | F12: 0 | G12: 0 | H12: 5 | I12: 0 | J12: 3 | K12: 3 | L12: 0 | M12: 0 | N12: 0 | O12: 0 | P12: 0 | Q12: 0 | R12: 0 | S12: 4 | T12: 0 | U12: 0 | V12: 0 | W12: 4 | X12: 0 | Y12: 0 | Z12: 0 | AA12: 0
A13: 12 | B13: BRICKMAKERS AG | C13: profit_anchor | D13: 0 | E13: 0 | F13: 0 | G13: 0 | H13: 0 | I13: 5 | J13: 0 | K13: 0 | L13: 5 | M13: 0 | N13: 4 | O13: 4 | P13: 0 | Q13: 0 | R13: 0 | S13: 4 | T13: 0 | U13: 0 | V13: 0 | W13: 0 | X13: 0 | Y13: 0 | Z13: 0 | AA13: 0
... A103: 102 | B103: ZDF – Zweites Deutsches Fernsehen | C103: context_actor | D103: 0 | E103: 0 | F103: 0 | G103: 0 | H103: 0 | I103: 0 | J103: 0 | K103: 0 | L103: 0 | M103: 0 | N103: 0 | O103: 0 | P103: 5 | Q103: 5 | R103: 4 | S103: 0 | T103: 0 | U103: 5 | V103: 0 | W103: 0 | X103: 0 | Y103: 0 | Z103: 5 | AA103: 0

Sheet Scoring_Rules
A1: Component | B1: Meaning | C1: Default logic used here | D1: Constraint or objective?
A2: candidate universe P | B2: Rows in Candidate_Patterns; generated from updated member table and 24 static clusters. | C2: For each cluster, include member pairs where both relevance scores are >= 3; rank by score; keep top 30 per cluster. | D2: Candidate generation before SCIP
A3: shared_concrete_clusters | B3: Both actors are relevant to the same concrete cluster. | C3: MIN(14, 4 + relevance_a + relevance_b). | D3: Objective coefficient
A4: complementary_topic_pairs | B4: Useful bridge between actor types/themes. | C4: 4 if roles differ; 1 if both academic_support; 2 if same non-academic role. | D4: Objective coefficient
A5: momentum_from_event_count | B5: Optional live signal momentum from crawler. | C5: Static default 0; later enriched by crawler events. | D5: Objective coefficient
A6: avg_decision_quality | B6: Optional live quality from crawler. | C6: Static default 0; later enriched by signal judge / evidence quality. | D6: Objective coefficient
A7: section_diversity | B7: Different evidence/role logic in one card. | C7: 2 if roles differ; else 1. | D7: Objective coefficient
A8: role_complementarity | B8: Quality of actor bridge. | C8: profit+implementation=8; academic+implementation=7; academic+profit=6; context+profit/implementation=6; context+academic=5; academic+academic=2. | D8: Objective coefficient
A9: application_capability_bridge | B9: Can this pair move from topic to action? | C9: Same role bridge logic: implementation/resource + knowledge/problem owner scores higher. | D9: Objective coefficient
A10: broad_media_penalty | B10: Prevents media over-selection outside public-role lanes. | C10: 0 in this static file; reserved for later media-role refinements. | D10: Objective penalty
A11: weak_profile_penalty | B11: Penalizes weak cluster relevance. | C11: 4 if either actor has relevance < 3; normally 0 because candidates require >= 3. | D11: Objective penalty
A12: academic_only_penalty | B12: Penalizes all-academic cards. | C12: 12 if both actors are academic_support. This keeps universities as support unless the pair is very strong. | D12: Objective penalty
... A14: final_support_score | B14: Support score attached to x_p. | C14: SUM positive components O:U minus penalties V:Y. | D14: Objective coefficient

Sheet Model_Readme
A1: Topic | B1: Explanation
A2: Update performed | B2: Removed Alexianer GmbH from the member universe and all candidate/constraint/matrix sheets. Added Hochschule für Musik Mainz and Hochschule für Gesellschaftsgestaltung (HfGG) with static cluster profiles.
A3: Hochschule für Musik Mainz mapping | B3: academic_support; culture/knowledge profile. Main cluster: Talentförderung, Musik und Nachwuchs (5), plus Kultur/Standortidentität, Kreativwirtschaft, Wissenschaft/Demokratie, Weiterbildung.
A4: HfGG mapping | B4: academic_support; society/sustainability/knowledge profile. Main cluster: Wissenschaft, Demokratie und gesellschaftlicher Zusammenhalt (5), plus Demokratie/Medien/Zusammenhalt, Teilhabe/Inklusion, Klimaanpassung, Hochschule-Wirtschaft-Transfer, Weiterbildung.
A5: Plausible candidate patterns | B5: For every concrete cluster, members with relevance >=3 are eligible. The script creates all pair combinations inside that cluster, scores them, ranks them, and keeps the top 30 cards per cluster. This yields an auditable static candidate universe P.
A6: Scoring decisions | B6: Positive components: shared cluster relevance, role difference/complementarity, section diversity, action bridge, future live signal fields. Negative components: weak profile, academic-only, abstract overlap, media penalty placeholder.
A7: SCIP formulation | B7: Binary weighted set-packing: choose x_p in {0,1} to maximize SUM(final_support_score_p*x_p), subject to max selected cards, member limits, cluster limits, and opportunity duplicate limits.
A8: Dynamic update note | B8: Crawler and feedback should later enrich scores, not rewrite the static member universe or constraints automatically.

Sheet InfoBox_Keyword_Radar
A1: member_id | B1: member_name | C1: homepage | D1: actor_role | E1: actor_subrole | F1: searchable_profile_text | G1: keyword_families_hit | H1: keywords_hit | I1: keyword_hit_count | J1: strongest_static_signal | K1: SOR_interpretation | L1: suggested_use | M1: source_url | N1: extraction_note
A2: 1 | B2: 1. FSV Mainz 05 e.V. | C2: https://www.mainz05.de | D2: context_actor | E2: sports_regional_identity_anchor | F2: 1. FSV Mainz 05 e.V. | context_actor | gesellschaft, kultur | Sport, Region und gesellschaftliche Identifikation (5); Kultur, Standortidentität und regionale Attraktivität (4); Demokratie, Medien und gesellschaftlicher Zusammenhalt (3); Kreativwirtschaft, Medien und digitale Öffentlichkeit (3) | G2: KI / Digital; Wirtschaft / Mittelstand / Standort; Dialog / Netzwerk / Verantwortung; Kultur / Medien / Öffentlichkeit | H2: digital; IT; Wirtschaft; Standort; gesellschaftlich; Zusammenhalt; Kultur; Medien; Öffentlichkeit; Kreativwirtschaft; Standortidentität; Region; gesellschaftliche Identifikation; Demokratie | I2: 14 | J2: Sport, Region und gesellschaftliche Identifikation (5) | K2: Static profile activates 4 keyword family/families: KI / Digital, Wirtschaft / Mittelstand / Standort, Dialog / Netzwerk / Verantwortung, Kultur / Medien / Öffentlichkeit. | L2: Use as convening/context partner for digitalization / data / technology opportunity anchor. | M2: https://www.zirp.de/die-zirp/mitglieder/ | N2: Keyword search over existing static ZIRP member fields in this workbook, designed to mirror/search official ZIRP profile info boxes.
A3: 2 | B3: AOK Rheinland-Pfalz/Saarland | C3: https://www.aok.de/rheinland-pfalz | D3: context_actor | E3: health_social_anchor | F3: AOK Rheinland-Pfalz/Saarland | context_actor | gesellschaft | Gesundheitsversorgung und Prävention (5); Pflege, Fachkräfte und Sozialwirtschaft (4); Sport, Region und gesellschaftliche Identifikation (4) | G3: KI / Digital; Nachhaltigkeit / Klima / Energie; Gesundheit / Pflege / Sozialwirtschaft; Fachkräfte / Arbeit / Qualifizierung; Wirtschaft / Mittelstand / Standort; Dialog / Netzwerk / Verantwortung; Kultur / Medien / Öffentlichkeit | H3: IT; Land; Gesundheit; Gesundheitsversorgung; Pflege; Sozialwirtschaft; Prävention; Versorgung; Fachkräfte; Wirtschaft; gesellschaftlich; Region; gesellschaftliche Identifikation | I3: 13 | J3: Gesundheitsversorgung und Prävention (5) | K3: Static profile activates 7 keyword family/families: KI / Digital, Nachhaltigkeit / Klima / Energie, Gesundheit / Pflege / Sozialwirtschaft, Fachkräfte / Arbeit / Qualifizierung, Wirtschaft / Mittelstand / Standort, Dialog / Netzwerk / Verantwortung, Kultur / Medien / Öffentlichkeit. | L3: Use as convening/context partner for health/social-sector opportunity anchor. | M3: https://www.zirp.de/die-zirp/mitglieder/ | N3: Keyword search over existing static ZIRP member fields in this workbook, designed to mirror/search official ZIRP profile info boxes.
A4: 3 | B4: Architektenkammer Rheinland-Pfalz | C4: https://www.diearchitekten.org | D4: implementation_anchor | E4: construction_planning_anchor | F4: Architektenkammer Rheinland-Pfalz | implementation_anchor | nachhaltigkeit, technologie | Digitale Bau-, Planungs- und Genehmigungsprozesse (5); Klimaanpassung in Stadt und Land (4); Kreislaufwirtschaft, Bau und Ersatzbaustoffverordnung (4) | G4: KI / Digital; Nachhaltigkeit / Klima / Energie; Bau / Raum / Infrastruktur; Wirtschaft / Mittelstand / Standort | H4: digital; IT; Technologie; Nachhaltigkeit; nachhaltig; Klima; Klimaanpassung; Kreislauf; Ersatzbaustoff; Land; Stadt; Bau; Planung; Genehmigung; Wirtschaft | I4: 15 | J4: Digitale Bau-, Planungs- und Genehmigungsprozesse (5) | K4: Static profile activates 4 keyword family/families: KI / Digital, Nachhaltigkeit / Klima / Energie, Bau / Raum / Infrastruktur, Wirtschaft / Mittelstand / Standort. | L4: Use as institutional implementation partner for digitalization / data / technology opportunity anchor. | M4: https://www.zirp.de/die-zirp/mitglieder/ | N4: Keyword search over existing static ZIRP member fields in this workbook, designed to mirror/search official ZIRP profile info boxes.
A5: 4 | B5: Aturas GmbH | C5: https://aturas.com | D5: profit_anchor | E5: technology_digital_anchor | F5: Aturas GmbH | profit_anchor | technologie, wirtschaft, wissen | Digitale Bau-, Planungs- und Genehmigungsprozesse (4); KI, Daten und Verwaltungs-/Wirtschaftsanwendungen (4); Mittelstand, Digitalisierung und Produktivität (4); Verwaltungswissen und digitale Umsetzung (4) | G5: KI / Digital; Innovation / Transfer; Fachkräfte / Arbeit / Qualifizierung; Bau / Raum / Infrastruktur; Wirtschaft / Mittelstand / Standort; Wissenschaft / Bildung / Hochschule | H5: KI; Digitalisierung; digital; Daten; IT; Technologie; Verwaltung; Wissen; Produktivität; Bau; Planung; Genehmigung; Wirtschaft; Mittelstand | I5: 14 | J5: Digitale Bau-, Planungs- und Genehmigungsprozesse (4) | K5: Static profile activates 6 keyword family/families: KI / Digital, Innovation / Transfer, Fachkräfte / Arbeit / Qualifizierung, Bau / Raum / Infrastruktur, Wirtschaft / Mittelstand / Standort, Wissenschaft / Bildung / Hochschule. | L5: Use as implementation/commercial partner for digitalization / data / technology opportunity anchor. | M5: https://www.zirp.de/die-zirp/mitglieder/ | N5: Keyword search over existing static ZIRP member fields in this workbook, designed to mirror/search official ZIRP profile info boxes.
A6: 5 | B6: Barmherzige Brüder Trier gGmbH | C6: https://www.bbtgruppe.de | D6: context_actor | E6: health_social_anchor | F6: Barmherzige Brüder Trier gGmbH | context_actor | gesellschaft, wirtschaft, wissen | Pflege, Fachkräfte und Sozialwirtschaft (5); Arbeitsmarkt, Fachkräfte und Qualifizierung (4); Gesundheitsversorgung und Prävention (4); Teilhabe, Inklusion und Arbeitsmarkt (4); Weiterbildung und lebenslanges Lernen (4) | G6: KI / Digital; Innovation / Transfer; Gesundheit / Pflege / Sozialwirtschaft; Fachkräfte / Arbeit / Qualifizierung; Wirtschaft / Mittelstand / Standort; Wissenschaft / Bildung / Hochschule | H6: IT; Wissen; Gesundheit; Gesundheitsversorgung; Pflege; Sozialwirtschaft; Prävention; Versorgung; Teilhabe; Fachkräfte; Qualifizierung; Weiterbildung; Arbeitsmarkt; lebenslanges Lernen; Wirtschaft; Bildung | I6: 16 | J6: Pflege, Fachkräfte und Sozialwirtschaft (5) | K6: Static profile activates 6 keyword family/families: KI / Digital, Innovation / Transfer, Gesundheit / Pflege / Sozialwirtschaft, Fachkräfte / Arbeit / Qualifizierung, Wirtschaft / Mittelstand / Standort, Wissenschaft / Bildung / Hochschule. | L6: Use as convening/context partner for health/social-sector opportunity anchor. | M6: https://www.zirp.de/die-zirp/mitglieder/ | N6: Keyword search over existing static ZIRP member fields in this workbook, designed to mirror/search official ZIRP profile info boxes.
A7: 6 | B7: BASF SE | C7: https://www.basf.com | D7: profit_anchor | E7: industry_anchor | F7: BASF SE | profit_anchor | nachhaltigkeit, technologie, wirtschaft, wissen | Standort, Investition und industrielle Transformation (5); Energie, Netze und Versorgungssicherheit (4); Hochschule-Wirtschaft-Transfer (4); Industrie 4.0, Automatisierung und Produktion (4); Arbeitsmarkt, Fachkräfte und Qualifizierung (3) | G7: KI / Digital; Innovation / Transfer; Nachhaltigkeit / Klima / Energie; Gesundheit / Pflege / Sozialwirtschaft; Fachkräfte / Arbeit / Qualifizierung; Wirtschaft / Mittelstand / Standort; Wissenschaft / Bildung / Hochschule | H7: IT; Technologie; Automatisierung; Industrie 4.0; Transfer; Wissen; Nachhaltigkeit; nachhaltig; Energie; Netze; Versorgungssicherheit; Versorgung; Fachkräfte; Qualifizierung; Arbeitsmarkt; Wirtschaft; Standort; Industrie; Investition; Transformation; Hochschule | I7: 21 | J7: Standort, Investition und industrielle Transformation (5) | K7: Static profile activates 7 keyword family/families: KI / Digital, Innovation / Transfer, Nachhaltigkeit / Klima / Energie, Gesundheit / Pflege / Sozialwirtschaft, Fachkräfte / Arbeit / Qualifizierung, Wirtschaft / Mittelstand / Standort, Wissenschaft / Bildung / Hochschule. | L7: Use as implementation/commercial partner for health/social-sector opportunity anchor. | M7: https://www.zirp.de/die-zirp/mitglieder/ | N7: Keyword search over existing static ZIRP member fields in this workbook, designed to mirror/search official ZIRP profile info boxes.
A8: 7 | B8: Bauern- und Winzerverband Rheinland-Pfalz Süd e.V. | C8: https://www.bwv-rlp.de | D8: implementation_anchor | E8: agriculture_wine_anchor | F8: Bauern- und Winzerverband Rheinland-Pfalz Süd e.V. | implementation_anchor | nachhaltigkeit | Klimaanpassung in Stadt und Land (5) | G8: KI / Digital; Nachhaltigkeit / Klima / Energie; Bau / Raum / Infrastruktur | H8: IT; Nachhaltigkeit; nachhaltig; Klima; Klimaanpassung; Land; Stadt; Bau | I8: 8 | J8: Klimaanpassung in Stadt und Land (5) | K8: Static profile activates 3 keyword family/families: KI / Digital, Nachhaltigkeit / Klima / Energie, Bau / Raum / Infrastruktur. | L8: Use as institutional implementation partner for digitalization / data / technology opportunity anchor. | M8: https://www.zirp.de/die-zirp/mitglieder/ | N8: Keyword search over existing static ZIRP member fields in this workbook, designed to mirror/search official ZIRP profile info boxes.
A9: 8 | B9: Bauwirtschaft Rheinland-Pfalz e.V. | C9: https://www.bauwirtschaft-rlp.de | D9: context_actor | E9: construction_planning_anchor | F9: Bauwirtschaft Rheinland-Pfalz e.V. | context_actor | nachhaltigkeit, technologie | Digitale Bau-, Planungs- und Genehmigungsprozesse (5); Kreislaufwirtschaft, Bau und Ersatzbaustoffverordnung (5); Klimaanpassung in Stadt und Land (4) | G9: KI / Digital; Nachhaltigkeit / Klima / Energie; Bau / Raum / Infrastruktur; Wirtschaft / Mittelstand / Standort | H9: digital; IT; Technologie; Nachhaltigkeit; nachhaltig; Klima; Klimaanpassung; Kreislauf; Ersatzbaustoff; Land; Stadt; Bau; Planung; Genehmigung; Wirtschaft | I9: 15 | J9: Digitale Bau-, Planungs- und Genehmigungsprozesse (5) | K9: Static profile activates 4 keyword family/families: KI / Digital, Nachhaltigkeit / Klima / Energie, Bau / Raum / Infrastruktur, Wirtschaft / Mittelstand / Standort. | L9: Use as convening/context partner for digitalization / data / technology opportunity anchor. | M9: https://www.zirp.de/die-zirp/mitglieder/ | N9: Keyword search over existing static ZIRP member fields in this workbook, designed to mirror/search official ZIRP profile info boxes.
A10: 9 | B10: Bernd Hummel Holding GmbH | C10: https://www.bernd-hummel.de | D10: profit_anchor | E10: industry_anchor | F10: Bernd Hummel Holding GmbH | profit_anchor | | | G10: KI / Digital | H10: IT | I10: 1 | K10: Static profile activates 1 keyword family/families: KI / Digital. | L10: Use as implementation/commercial partner for digitalization / data / technology opportunity anchor. | M10: https://www.zirp.de/die-zirp/mitglieder/ | N10: Keyword search over existing static ZIRP member fields in this workbook, designed to mirror/search official ZIRP profile info boxes.
A11: 10 | B11: Bitburger Braugruppe GmbH | C11: https://www.bitburger-braugruppe.de | D11: profit_anchor | E11: food_beverage_consumer_anchor | F11: Bitburger Braugruppe GmbH | profit_anchor | wirtschaft | Standort, Investition und industrielle Transformation (4) | G11: KI / Digital; Wirtschaft / Mittelstand / Standort | H11: IT; Wirtschaft; Standort; Industrie; Investition; Transformation | I11: 6 | J11: Standort, Investition und industrielle Transformation (4) | K11: Static profile activates 2 keyword family/families: KI / Digital, Wirtschaft / Mittelstand / Standort. | L11: Use as implementation/commercial partner for digitalization / data / technology opportunity anchor. | M11: https://www.zirp.de/die-zirp/mitglieder/ | N11: Keyword search over existing static ZIRP member fields in this workbook, designed to mirror/search official ZIRP profile info boxes.
A12: 11 | B12: Boehringer Ingelheim Pharma GmbH & Co. KG | C12: https://www.boehringer-ingelheim.com/de | D12: profit_anchor | E12: health_social_anchor | F12: Boehringer Ingelheim Pharma GmbH & Co. KG | profit_anchor | gesellschaft, wirtschaft, wissen | Standort, Investition und industrielle Transformation (5); Gesundheitsversorgung und Prävention (4); Hochschule-Wirtschaft-Transfer (4); Arbeitsmarkt, Fachkräfte und Qualifizierung (3); Finanzierung und Förderung von Transformation (3) | G12: KI / Digital; Innovation / Transfer; Gesundheit / Pflege / Sozialwirtschaft; Fachkräfte / Arbeit / Qualifizierung; Wirtschaft / Mittelstand / Standort; Wissenschaft / Bildung / Hochschule | H12: IT; Transfer; Wissen; Gesundheit; Gesundheitsversorgung; Prävention; Versorgung; Fachkräfte; Qualifizierung; Arbeitsmarkt; Wirtschaft; Standort; Industrie; Investition; Transformation; Förderung; Finanzierung; Hochschule | I12: 18 | J12: Standort, Investition und industrielle Transformation (5) | K12: Static profile activates 6 keyword family/families: KI / Digital, Innovation / Transfer, Gesundheit / Pflege / Sozialwirtschaft, Fachkräfte / Arbeit / Qualifizierung, Wirtschaft / Mittelstand / Standort, Wissenschaft / Bildung / Hochschule. | L12: Use as implementation/commercial partner for health/social-sector opportunity anchor. | M12: https://www.zirp.de/die-zirp/mitglieder/ | N12: Keyword search over existing static ZIRP member fields in this workbook, designed to mirror/search official ZIRP profile info boxes.
A13: 12 | B13: BRICKMAKERS AG | C13: http://www.brickmakers.de | D13: profit_anchor | E13: technology_digital_anchor | F13: BRICKMAKERS AG | profit_anchor | technologie, wirtschaft, wissen | KI, Daten und Verwaltungs-/Wirtschaftsanwendungen (5); Mittelstand, Digitalisierung und Produktivität (5); Cyberresilienz und kritische Infrastruktur (4); Digitale Bau-, Planungs- und Genehmigungsprozesse (4); Hochschule-Wirtschaft-Transfer (4) | G13: KI / Digital; Innovation / Transfer; Fachkräfte / Arbeit / Qualifizierung; Bau / Raum / Infrastruktur; Wirtschaft / Mittelstand / Standort; Wissenschaft / Bildung / Hochschule | H13: KI; Digitalisierung; digital; Daten; IT; Technologie; Cyber; Verwaltung; Transfer; Wissen; Produktivität; Bau; Infrastruktur; Planung; Genehmigung; Wirtschaft; Mittelstand; Hochschule | I13: 18 | J13: KI, Daten und Verwaltungs-/Wirtschaftsanwendungen (5) | K13: Static profile activates 6 keyword family/families: KI / Digital, Innovation / Transfer, Fachkräfte / Arbeit / Qualifizierung, Bau / Raum / Infrastruktur, Wirtschaft / Mittelstand / Standort, Wissenschaft / Bildung / Hochschule. | L13: Use as implementation/commercial partner for digitalization / data / technology opportunity anchor. | M13: https://www.zirp.de/die-zirp/mitglieder/ | N13: Keyword search over existing static ZIRP member fields in this workbook, designed to mirror/search official ZIRP profile info boxes.
A14: 13 | B14: Bundesagentur für Arbeit, Regionaldirektion Rheinland-Pfalz-Saarland | C14: https://www.arbeitsagentur.de | D14: implementation_anchor | E14: public_policy_anchor | F14: Bundesagentur für Arbeit, Regionaldirektion Rheinland-Pfalz-Saarland | implementation_anchor | gesellschaft, wirtschaft, wissen | Arbeitsmarkt, Fachkräfte und Qualifizierung (5); Pflege, Fachkräfte und Sozialwirtschaft (5); Teilhabe, Inklusion und Arbeitsmarkt (5); Weiterbildung und lebenslanges Lernen (5) | G14: KI / Digital; Innovation / Transfer; Nachhaltigkeit / Klima / Energie; Gesundheit / Pflege / Sozialwirtschaft; Fachkräfte / Arbeit / Qualifizierung; Wirtschaft / Mittelstand / Standort; Wissenschaft / Bildung / Hochschule; Kultur / Medien / Öffentlichkeit | H14: IT; Wissen; Land; Pflege; Sozialwirtschaft; Teilhabe; Fachkräfte; Qualifizierung; Weiterbildung; Arbeitsmarkt; lebenslanges Lernen; Wirtschaft; Bildung; Region | I14: 14 | J14: Arbeitsmarkt, Fachkräfte und Qualifizierung (5) | K14: Static profile activates 8 keyword family/families: KI / Digital, Innovation / Transfer, Nachhaltigkeit / Klima / Energie, Gesundheit / Pflege / Sozialwirtschaft, Fachkräfte / Arbeit / Qualifizierung, Wirtschaft / Mittelstand / Standort, Wissenschaft / Bildung / Hochschule, Kultur / Medien / Öffentlichkeit. | L14: Use as institutional implementation partner for health/social-sector opportunity anchor. | M14: https://www.zirp.de/die-zirp/mitglieder/ | N14: Keyword search over existing static ZIRP member fields in this workbook, designed to mirror/search official ZIRP profile info boxes.
A15: 14 | B15: Caritasverband für die Diözese Speyer e.V. | C15: https://www.caritas-speyer.de | D15: implementation_anchor | E15: health_social_anchor | F15: Caritasverband für die Diözese Speyer e.V. | implementation_anchor | gesellschaft, wirtschaft | Pflege, Fachkräfte und Sozialwirtschaft (5); Teilhabe, Inklusion und Arbeitsmarkt (5); Arbeitsmarkt, Fachkräfte und Qualifizierung (4); Demokratie, Medien und gesellschaftlicher Zusammenhalt (4); Gesundheitsversorgung und Prävention (4) | G15: KI / Digital; Gesundheit / Pflege / Sozialwirtschaft; Fachkräfte / Arbeit / Qualifizierung; Wirtschaft / Mittelstand / Standort; Wissenschaft / Bildung / Hochschule; Dialog / Netzwerk / Verantwortung; Kultur / Medien / Öffentlichkeit | H15: IT; Gesundheit; Gesundheitsversorgung; Pflege; Sozialwirtschaft; Prävention; Versorgung; Teilhabe; Fachkräfte; Qualifizierung; Arbeitsmarkt; Wirtschaft; gesellschaftlich; Zusammenhalt; Medien; Demokratie | I15: 16 | J15: Pflege, Fachkräfte und Sozialwirtschaft (5) | K15: Static profile activates 7 keyword family/families: KI / Digital, Gesundheit / Pflege / Sozialwirtschaft, Fachkräfte / Arbeit / Qualifizierung, Wirtschaft / Mittelstand / Standort, Wissenschaft / Bildung / Hochschule, Dialog / Netzwerk / Verantwortung, Kultur / Medien / Öffentlichkeit. | L15: Use as institutional implementation partner for health/social-sector opportunity anchor. | M15: https://www.zirp.de/die-zirp/mitglieder/ | N15: Keyword search over existing static ZIRP member fields in this workbook, designed to mirror/search official ZIRP profile info boxes.
A16: 15 | B16: Continental Automotive Technologies GmbH, Safety and Motion (SAM), Standort Rheinböllen | C16: https://www.continental-corporation.de | D16: profit_anchor | E16: industry_anchor | F16: Continental Automotive Technologies GmbH, Safety and Motion (SAM), Standort Rheinböllen | profit_anchor | technologie, wirtschaft | Industrie 4.0, Automatisierung und Produktion (5); Standort, Investition und industrielle Transformation (4) | G16: KI / Digital; Wirtschaft / Mittelstand / Standort | H16: IT; Technologie; Automatisierung; Industrie 4.0; Wirtschaft; Standort; Industrie; Investition; Transformation | I16: 9 | J16: Industrie 4.0, Automatisierung und Produktion (5) | K16: Static profile activates 2 keyword family/families: KI / Digital, Wirtschaft / Mittelstand / Standort. | L16: Use as implementation/commercial partner for digitalization / data / technology opportunity anchor. | M16: https://www.zirp.de/die-zirp/mitglieder/ | N16: Keyword search over existing static ZIRP member fields in this workbook, designed to mirror/search official ZIRP profile info boxes.
A17: 16 | B17: Debeka Versicherungsgruppe | C17: https://www.debeka.de | D17: profit_anchor | E17: bank_finance_anchor | F17: Debeka Versicherungsgruppe | profit_anchor | technologie, wirtschaft | Cyberresilienz und kritische Infrastruktur (4); Finanzierung und Förderung von Transformation (4); Standort, Investition und industrielle Transformation (4) | G17: KI / Digital; Bau / Raum / Infrastruktur; Wirtschaft / Mittelstand / Standort | H17: IT; Technologie; Cyber; Infrastruktur; Wirtschaft; Standort; Industrie; Investition; Transformation; Förderung; Finanzierung | I17: 11 | J17: Cyberresilienz und kritische Infrastruktur (4) | K17: Static profile activates 3 keyword family/families: KI / Digital, Bau / Raum / Infrastruktur, Wirtschaft / Mittelstand / Standort. | L17: Use as implementation/commercial partner for digitalization / data / technology opportunity anchor. | M17: https://www.zirp.de/die-zirp/mitglieder/ | N17: Keyword search over existing static ZIRP member fields in this workbook, designed to mirror/search official ZIRP profile info boxes.
A18: 17 | B18: Deutsche Bundesbank, Hauptverwaltung in Rheinland-Pfalz und dem Saarland | C18: https://www.bundesbank.de | D18: context_actor | E18: bank_finance_anchor | F18: Deutsche Bundesbank, Hauptverwaltung in Rheinland-Pfalz und dem Saarland | context_actor | technologie | Cyberresilienz und kritische Infrastruktur (4) | G18: KI / Digital; Nachhaltigkeit / Klima / Energie; Bau / Raum / Infrastruktur | H18: IT; Technologie; Cyber; Verwaltung; Land; Infrastruktur | I18: 6 | J18: Cyberresilienz und kritische Infrastruktur (4) | K18: Static profile activates 3 keyword family/families: KI / Digital, Nachhaltigkeit / Klima / Energie, Bau / Raum / Infrastruktur. | L18: Use as convening/context partner for digitalization / data / technology opportunity anchor. | M18: https://www.zirp.de/die-zirp/mitglieder/ | N18: Keyword search over existing static ZIRP member fields in this workbook, designed to mirror/search official ZIRP profile info boxes.
A19: 18 | B19: Deutsche Telekom AG | C19: https://www.telekom.de | D19: profit_anchor | E19: technology_digital_anchor | F19: Deutsche Telekom AG | profit_anchor | kultur, technologie, wirtschaft | Cyberresilienz und kritische Infrastruktur (5); KI, Daten und Verwaltungs-/Wirtschaftsanwendungen (5); Mittelstand, Digitalisierung und Produktivität (5); Industrie 4.0, Automatisierung und Produktion (4); Kreativwirtschaft, Medien und digitale Öffentlichkeit (4) | G19: KI / Digital; Fachkräfte / Arbeit / Qualifizierung; Bau / Raum / Infrastruktur; Wirtschaft / Mittelstand / Standort; Kultur / Medien / Öffentlichkeit | H19: KI; Digitalisierung; digital; Daten; IT; Technologie; Cyber; Automatisierung; Industrie 4.0; Verwaltung; Produktivität; Infrastruktur; Wirtschaft; Mittelstand; Industrie; Kultur; Medien; Öffentlichkeit; Kreativwirtschaft | I19: 19 | J19: Cyberresilienz und kritische Infrastruktur (5) | K19: Static profile activates 5 keyword family/families: KI / Digital, Fachkräfte / Arbeit / Qualifizierung, Bau / Raum / Infrastruktur, Wirtschaft / Mittelstand / Standort, Kultur / Medien / Öffentlichkeit. | L19: Use as implementation/commercial partner for digitalization / data / technology opportunity anchor. | M19: https://www.zirp.de/die-zirp/mitglieder/ | N19: Keyword search over existing static ZIRP member fields in this workbook, designed to mirror/search official ZIRP profile info boxes.
A20: 19 | B20: Deutsche Universität für Verwaltungswissenschaften Speyer | C20: https://www.uni-speyer.de | D20: academic_support | E20: university_research | F20: Deutsche Universität für Verwaltungswissenschaften Speyer | academic_support | gesellschaft, technologie, wissen | Demokratie, Medien und gesellschaftlicher Zusammenhalt (5); KI, Daten und Verwaltungs-/Wirtschaftsanwendungen (5); Verwaltungswissen und digitale Umsetzung (5); Wissenschaft, Demokratie und gesellschaftlicher Zusammenhalt (5); Digitale Bau-, Planungs- und Genehmigungsprozesse (4) | G20: KI / Digital; Innovation / Transfer; Bau / Raum / Infrastruktur; Wirtschaft / Mittelstand / Standort; Wissenschaft / Bildung / Hochschule; Dialog / Netzwerk / Verantwortung; Kultur / Medien / Öffentlichkeit | H20: KI; digital; Daten; IT; Technologie; Verwaltung; Wissen; Bau; Planung; Genehmigung; Wirtschaft; Wissenschaft; Universität; gesellschaftlich; Zusammenhalt; Medien; Demokratie | I20: 17 | J20: Demokratie, Medien und gesellschaftlicher Zusammenhalt (5) | K20: Static profile activates 7 keyword family/families: KI / Digital, Innovation / Transfer, Bau / Raum / Infrastruktur, Wirtschaft / Mittelstand / Standort, Wissenschaft / Bildung / Hochschule, Dialog / Netzwerk / Verantwortung, Kultur / Medien / Öffentlichkeit. | L20: Use as evidence, research or transfer partner for digitalization / data / technology opportunity anchor. | M20: https://www.zirp.de/die-zirp/mitglieder/ | N20: Keyword search over existing static ZIRP member fields in this workbook, designed to mirror/search official ZIRP profile info boxes.
A21: 20 | B21: Deutscher Gewerkschaftsbund (DGB) Rheinland-Pfalz/Saarland | C21: https://rlp-saarland.dgb.de | D21: context_actor | E21: chamber_association_anchor | F21: Deutscher Gewerkschaftsbund (DGB) Rheinland-Pfalz/Saarland | context_actor | gesellschaft, wirtschaft, wissen | Arbeitsmarkt, Fachkräfte und Qualifizierung (5); Pflege, Fachkräfte und Sozialwirtschaft (4); Teilhabe, Inklusion und Arbeitsmarkt (4); Weiterbildung und lebenslanges Lernen (4) | G21: KI / Digital; Innovation / Transfer; Nachhaltigkeit / Klima / Energie; Gesundheit / Pflege / Sozialwirtschaft; Fachkräfte / Arbeit / Qualifizierung; Wirtschaft / Mittelstand / Standort; Wissenschaft / Bildung / Hochschule | H21: IT; Wissen; Land; Pflege; Sozialwirtschaft; Teilhabe; Fachkräfte; Qualifizierung; Weiterbildung; Arbeitsmarkt; lebenslanges Lernen; Wirtschaft; Bildung | I21: 13 | J21: Arbeitsmarkt, Fachkräfte und Qualifizierung (5) | K21: Static profile activates 7 keyword family/families: KI / Digital, Innovation / Transfer, Nachhaltigkeit / Klima / Energie, Gesundheit / Pflege / Sozialwirtschaft, Fachkräfte / Arbeit / Qualifizierung, Wirtschaft / Mittelstand / Standort, Wissenschaft / Bildung / Hochschule. | L21: Use as convening/context partner for health/social-sector opportunity anchor. | M21: https://www.zirp.de/die-zirp/mitglieder/ | N21: Keyword search over existing static ZIRP member fields in this workbook, designed to mirror/search official ZIRP profile info boxes.
A22: 21 | B22: Duale Hochschule Rheinland-Pfalz | C22: https://www.dh-rlp.de | D22: academic_support | E22: university_applied_sciences | F22: Duale Hochschule Rheinland-Pfalz | academic_support | gesellschaft, wirtschaft, wissen | Arbeitsmarkt, Fachkräfte und Qualifizierung (5); Weiterbildung und lebenslanges Lernen (5); Hochschule-Wirtschaft-Transfer (4); Pflege, Fachkräfte und Sozialwirtschaft (4) | G22: KI / Digital; Innovation / Transfer; Nachhaltigkeit / Klima / Energie; Gesundheit / Pflege / Sozialwirtschaft; Fachkräfte / Arbeit / Qualifizierung; Wirtschaft / Mittelstand / Standort; Wissenschaft / Bildung / Hochschule | H22: IT; Transfer; Wissen; Land; Pflege; Sozialwirtschaft; Fachkräfte; Qualifizierung; Weiterbildung; Arbeitsmarkt; lebenslanges Lernen; Wirtschaft; Hochschule; Bildung | I22: 14 | J22: Arbeitsmarkt, Fachkräfte und Qualifizierung (5) | K22: Static profile activates 7 keyword family/families: KI / Digital, Innovation / Transfer, Nachhaltigkeit / Klima / Energie, Gesundheit / Pflege / Sozialwirtschaft, Fachkräfte / Arbeit / Qualifizierung, Wirtschaft / Mittelstand / Standort, Wissenschaft / Bildung / Hochschule. | L22: Use as evidence, research or transfer partner for health/social-sector opportunity anchor. | M22: https://www.zirp.de/die-zirp/mitglieder/ | N22: Keyword search over existing static ZIRP member fields in this workbook, designed to mirror/search official ZIRP profile info boxes.
... A29: 28 | B29: Evangelische Kirche der Pfalz | C29: https://www.evkirchepfalz.de | D29: context_actor | E29: culture_foundation_anchor | F29: Evangelische Kirche der Pfalz | context_actor | gesellschaft, kultur, wissen | Demokratie, Medien und gesellschaftlicher Zusammenhalt (5); Wissenschaft, Demokratie und gesellschaftlicher Zusammenhalt (5); Kultur, Standortidentität und regionale Attraktivität (4); Teilhabe, Inklusion und Arbeitsmarkt (4); Talentförderung, Musik und Nachwuchs (3) | G29: KI / Digital; Innovation / Transfer; Gesundheit / Pflege / Sozialwirtschaft; Fachkräfte / Arbeit / Qualifizierung; Wirtschaft / Mittelstand / Standort; Wissenschaft / Bildung / Hochschule; Dialog / Netzwerk / Verantwortung; Kultur / Medien / Öffentlichkeit | H29: KI; IT; Wissen; Teilhabe; Arbeitsmarkt; Standort; Förderung; Wissenschaft; gesellschaftlich; Zusammenhalt; Kultur; Medien; Musik; Standortidentität; Region; Demokratie | I29: 16 | J29: Demokratie, Medien und gesellschaftlicher Zusammenhalt (5) | K29: Static profile activates 8 keyword family/families: KI / Digital, Innovation / Transfer, Gesundheit / Pflege / Sozialwirtschaft, Fachkräfte / Arbeit / Qualifizierung, Wirtschaft / Mittelstand / Standort, Wissenschaft / Bildung / Hochschule, Dialog / Netzwerk / Verantwortung, Kultur / Medien / Öffentlichkeit. | L29: Use as convening/context partner for health/social-sector opportunity anchor. | M29: https://www.zirp.de/die-zirp/mitglieder/ | N29: Keyword search over existing static ZIRP member fields in this workbook, designed to mirror/search official ZIRP profile info boxes.
A30: 29 | B30: Fachingen Heil- und Mineralbrunnen GmbH | C30: https://www.fachingen.de | D30: profit_anchor | E30: food_beverage_consumer_anchor | F30: Fachingen Heil- und Mineralbrunnen GmbH | profit_anchor | | | G30: KI / Digital | H30: IT | I30: 1 | K30: Static profile activates 1 keyword family/families: KI / Digital. | L30: Use as implementation/commercial partner for digitalization / data / technology opportunity anchor. | M30: https://www.zirp.de/die-zirp/mitglieder/ | N30: Keyword search over existing static ZIRP member fields in this workbook, designed to mirror/search official ZIRP profile info boxes.
A31: 30 | B31: Gerolsteiner Brunnen GmbH & Co. KG | C31: https://www.gerolsteiner.de | D31: profit_anchor | E31: food_beverage_consumer_anchor | F31: Gerolsteiner Brunnen GmbH & Co. KG | profit_anchor | | | G31: KI / Digital | H31: IT | I31: 1 | K31: Static profile activates 1 keyword family/families: KI / Digital. | L31: Use as implementation/commercial partner for digitalization / data / technology opportunity anchor. | M31: https://www.zirp.de/die-zirp/mitglieder/ | N31: Keyword search over existing static ZIRP member fields in this workbook, designed to mirror/search official ZIRP profile info boxes.
A32: 31 | B32: GLOBUS Markthallen Holding GmbH & Co. KG | C32: https://www.globus.de | D32: profit_anchor | E32: food_beverage_consumer_anchor | F32: GLOBUS Markthallen Holding GmbH & Co. KG | profit_anchor | gesellschaft, wirtschaft, wissen | Standort, Investition und industrielle Transformation (4); Arbeitsmarkt, Fachkräfte und Qualifizierung (3); Sport, Region und gesellschaftliche Identifikation (3); Teilhabe, Inklusion und Arbeitsmarkt (3); Weiterbildung und lebenslanges Lernen (3) | G32: KI / Digital; Innovation / Transfer; Gesundheit / Pflege / Sozialwirtschaft; Fachkräfte / Arbeit / Qualifizierung; Wirtschaft / Mittelstand / Standort; Wissenschaft / Bildung / Hochschule; Dialog / Netzwerk / Verantwortung; Kultur / Medien / Öffentlichkeit | H32: IT; Wissen; Teilhabe; Fachkräfte; Qualifizierung; Weiterbildung; Arbeitsmarkt; lebenslanges Lernen; Wirtschaft; Standort; Industrie; Investition; Transformation; Bildung; gesellschaftlich; Region; gesellschaftliche Identifikation | I32: 17 | J32: Standort, Investition und industrielle Transformation (4) | K32: Static profile activates 8 keyword family/families: KI / Digital, Innovation / Transfer, Gesundheit / Pflege / Sozialwirtschaft, Fachkräfte / Arbeit / Qualifizierung, Wirtschaft / Mittelstand / Standort, Wissenschaft / Bildung / Hochschule, Dialog / Netzwerk / Verantwortung, Kultur / Medien / Öffentlichkeit. | L32: Use as implementation/commercial partner for health/social-sector opportunity anchor. | M32: https://www.zirp.de/die-zirp/mitglieder/ | N32: Keyword search over existing static ZIRP member fields in this workbook, designed to mirror/search official ZIRP profile info boxes.
A33: 32 | B33: Handwerkskammern Rheinland-Pfalz | C33: https://handwerk-rlp.de | D33: implementation_anchor | E33: chamber_association_anchor | F33: Handwerkskammern Rheinland-Pfalz | implementation_anchor | wirtschaft, wissen | Arbeitsmarkt, Fachkräfte und Qualifizierung (5); Weiterbildung und lebenslanges Lernen (5); Hochschule-Wirtschaft-Transfer (4); Mittelstand, Digitalisierung und Produktivität (4); Finanzierung und Förderung von Transformation (3) | G33: KI / Digital; Innovation / Transfer; Nachhaltigkeit / Klima / Energie; Fachkräfte / Arbeit / Qualifizierung; Wirtschaft / Mittelstand / Standort; Wissenschaft / Bildung / Hochschule | H33: Digitalisierung; digital; IT; Transfer; Wissen; Land; Fachkräfte; Qualifizierung; Weiterbildung; Arbeitsmarkt; Produktivität; lebenslanges Lernen; Wirtschaft; Mittelstand; Transformation; Förderung; Finanzierung; Hochschule; Bildung | I33: 19 | J33: Arbeitsmarkt, Fachkräfte und Qualifizierung (5) | K33: Static profile activates 6 keyword family/families: KI / Digital, Innovation / Transfer, Nachhaltigkeit / Klima / Energie, Fachkräfte / Arbeit / Qualifizierung, Wirtschaft / Mittelstand / Standort, Wissenschaft / Bildung / Hochschule. | L33: Use as institutional implementation partner for digitalization / data / technology opportunity anchor. | M33: https://www.zirp.de/die-zirp/mitglieder/ | N33: Keyword search over existing static ZIRP member fields in this workbook, designed to mirror/search official ZIRP profile info boxes.
A34: 33 | B34: Heberger Gruppe | C34: https://www.heberger.de | D34: context_actor | E34: construction_planning_anchor | F34: Heberger Gruppe | context_actor | nachhaltigkeit, technologie | Kreislaufwirtschaft, Bau und Ersatzbaustoffverordnung (4); Digitale Bau-, Planungs- und Genehmigungsprozesse (3) | G34: KI / Digital; Nachhaltigkeit / Klima / Energie; Bau / Raum / Infrastruktur; Wirtschaft / Mittelstand / Standort | H34: digital; IT; Technologie; Nachhaltigkeit; nachhaltig; Kreislauf; Ersatzbaustoff; Bau; Planung; Genehmigung; Wirtschaft | I34: 11 | J34: Kreislaufwirtschaft, Bau und Ersatzbaustoffverordnung (4) | K34: Static profile activates 4 keyword family/families: KI / Digital, Nachhaltigkeit / Klima / Energie, Bau / Raum / Infrastruktur, Wirtschaft / Mittelstand / Standort. | L34: Use as convening/context partner for digitalization / data / technology opportunity anchor. | M34: https://www.zirp.de/die-zirp/mitglieder/ | N34: Keyword search over existing static ZIRP member fields in this workbook, designed to mirror/search official ZIRP profile info boxes.
A35: 34 | B35: Hochschule für Gesellschaftsgestaltung (HfGG) | C35: https://www.hfgg.de/ | D35: academic_support | E35: university_applied_sciences | F35: Hochschule für Gesellschaftsgestaltung (HfGG) | academic_support | gesellschaft, nachhaltigkeit, wissen | Wissenschaft, Demokratie und gesellschaftlicher Zusammenhalt (5); Demokratie, Medien und gesellschaftlicher Zusammenhalt (4); Teilhabe, Inklusion und Arbeitsmarkt (4); Klimaanpassung in Stadt und Land (4); Hochschule-Wirtschaft-Transfer (3); Weiterbildung und lebenslanges Lernen (3) | G35: KI / Digital; Innovation / Transfer; Nachhaltigkeit / Klima / Energie; Gesundheit / Pflege / Sozialwirtschaft; Fachkräfte / Arbeit / Qualifizierung; Bau / Raum / Infrastruktur; Wirtschaft / Mittelstand / Standort; Wissenschaft / Bildung / Hochschule; Dialog / Netzwerk / Verantwortung; Kultur / Medien / Öffentlichkeit | H35: IT; Transfer; Wissen; Nachhaltigkeit; nachhaltig; Klima; Klimaanpassung; Land; Stadt; Teilhabe; Weiterbildung; Arbeitsmarkt; lebenslanges Lernen; Wirtschaft; Wissenschaft; Hochschule; Bildung; gesellschaftlich; Zusammenhalt; Medien; Demokratie | I35: 21 | J35: Wissenschaft, Demokratie und gesellschaftlicher Zusammenhalt (5) | K35: Static profile activates 10 keyword family/families: KI / Digital, Innovation / Transfer, Nachhaltigkeit / Klima / Energie, Gesundheit / Pflege / Sozialwirtschaft, Fachkräfte / Arbeit / Qualifizierung, Bau / Raum / Infrastruktur, Wirtschaft / Mittelstand / Standort, Wissenschaft / Bildung / Hochschule, Dialog / Netzwerk / Verantwortung, Kultur / Medien / Öffentlichkeit. | L35: Use as evidence, research or transfer partner for health/social-sector opportunity anchor. | M35: https://www.zirp.de/die-zirp/mitglieder/ | N35: Keyword search over existing static ZIRP member fields in this workbook, designed to mirror/search official ZIRP profile info boxes.
A36: 35 | B36: Hochschule für Musik Mainz | C36: https://www.musik.uni-mainz.de/ | D36: academic_support | E36: university_applied_sciences | F36: Hochschule für Musik Mainz | academic_support | kultur, wissen | Talentförderung, Musik und Nachwuchs (5); Kultur, Standortidentität und regionale Attraktivität (4); Kreativwirtschaft, Medien und digitale Öffentlichkeit (3); Wissenschaft, Demokratie und gesellschaftlicher Zusammenhalt (3); Weiterbildung und lebenslanges Lernen (3) | G36: KI / Digital; Innovation / Transfer; Fachkräfte / Arbeit / Qualifizierung; Wirtschaft / Mittelstand / Standort; Wissenschaft / Bildung / Hochschule; Dialog / Netzwerk / Verantwortung; Kultur / Medien / Öffentlichkeit | H36: digital; IT; Wissen; Weiterbildung; lebenslanges Lernen; Wirtschaft; Standort; Förderung; Wissenschaft; Hochschule; Bildung; gesellschaftlich; Zusammenhalt; Kultur; Medien; Öffentlichkeit; Kreativwirtschaft; Musik; Standortidentität; Region; Demokratie | I36: 21 | J36: Talentförderung, Musik und Nachwuchs (5) | K36: Static profile activates 7 keyword family/families: KI / Digital, Innovation / Transfer, Fachkräfte / Arbeit / Qualifizierung, Wirtschaft / Mittelstand / Standort, Wissenschaft / Bildung / Hochschule, Dialog / Netzwerk / Verantwortung, Kultur / Medien / Öffentlichkeit. | L36: Use as evidence, research or transfer partner for digitalization / data / technology opportunity anchor. | M36: https://www.zirp.de/die-zirp/mitglieder/ | N36: Keyword search over existing static ZIRP member fields in this workbook, designed to mirror/search official ZIRP profile info boxes.
A37: 36 | B37: Hochschule für Wirtschaft und Gesellschaft Ludwigshafen | C37: https://www.hwg-lu.de | D37: academic_support | E37: university_applied_sciences | F37: Hochschule für Wirtschaft und Gesellschaft Ludwigshafen | academic_support | gesellschaft, wirtschaft, wissen | Arbeitsmarkt, Fachkräfte und Qualifizierung (4); Hochschule-Wirtschaft-Transfer (4); Weiterbildung und lebenslanges Lernen (4); Gesundheitsversorgung und Prävention (3) | G37: KI / Digital; Innovation / Transfer; Gesundheit / Pflege / Sozialwirtschaft; Fachkräfte / Arbeit / Qualifizierung; Wirtschaft / Mittelstand / Standort; Wissenschaft / Bildung / Hochschule | H37: IT; Transfer; Wissen; Gesundheit; Gesundheitsversorgung; Prävention; Versorgung; Fachkräfte; Qualifizierung; Weiterbildung; Arbeitsmarkt; lebenslanges Lernen; Wirtschaft; Hochschule; Bildung | I37: 15 | J37: Arbeitsmarkt, Fachkräfte und Qualifizierung (4) | K37: Static profile activates 6 keyword family/families: KI / Digital, Innovation / Transfer, Gesundheit / Pflege / Sozialwirtschaft, Fachkräfte / Arbeit / Qualifizierung, Wirtschaft / Mittelstand / Standort, Wissenschaft / Bildung / Hochschule. | L37: Use as evidence, research or transfer partner for health/social-sector opportunity anchor. | M37: https://www.zirp.de/die-zirp/mitglieder/ | N37: Keyword search over existing static ZIRP member fields in this workbook, designed to mirror/search official ZIRP profile info boxes.
A38: 37 | B38: Hochschule Kaiserslautern | C38: https://www.hs-kl.de | D38: academic_support | E38: university_applied_sciences | F38: Hochschule Kaiserslautern | academic_support | technologie, wirtschaft, wissen | Arbeitsmarkt, Fachkräfte und Qualifizierung (4); Hochschule-Wirtschaft-Transfer (4); Industrie 4.0, Automatisierung und Produktion (4); KI, Daten und Verwaltungs-/Wirtschaftsanwendungen (4); Mittelstand, Digitalisierung und Produktivität (4) | G38: KI / Digital; Innovation / Transfer; Fachkräfte / Arbeit / Qualifizierung; Wirtschaft / Mittelstand / Standort; Wissenschaft / Bildung / Hochschule | H38: KI; Digitalisierung; digital; Daten; IT; Technologie; Automatisierung; Industrie 4.0; Verwaltung; Transfer; Wissen; Fachkräfte; Qualifizierung; Arbeitsmarkt; Produktivität; Wirtschaft; Mittelstand; Industrie; Hochschule | I38: 19 | J38: Arbeitsmarkt, Fachkräfte und Qualifizierung (4) | K38: Static profile activates 5 keyword family/families: KI / Digital, Innovation / Transfer, Fachkräfte / Arbeit / Qualifizierung, Wirtschaft / Mittelstand / Standort, Wissenschaft / Bildung / Hochschule. | L38: Use as evidence, research or transfer partner for digitalization / data / technology opportunity anchor. | M38: https://www.zirp.de/die-zirp/mitglieder/ | N38: Keyword search over existing static ZIRP member fields in this workbook, designed to mirror/search official ZIRP profile info boxes.
A39: 38 | B39: Hochschule Koblenz | C39: https://www.hs-koblenz.de | D39: academic_support | E39: university_applied_sciences | F39: Hochschule Koblenz | academic_support | technologie, wirtschaft, wissen | Arbeitsmarkt, Fachkräfte und Qualifizierung (4); Hochschule-Wirtschaft-Transfer (4); Weiterbildung und lebenslanges Lernen (4); KI, Daten und Verwaltungs-/Wirtschaftsanwendungen (3); Mittelstand, Digitalisierung und Produktivität (3) | G39: KI / Digital; Innovation / Transfer; Fachkräfte / Arbeit / Qualifizierung; Wirtschaft / Mittelstand / Standort; Wissenschaft / Bildung / Hochschule | H39: KI; Digitalisierung; digital; Daten; IT; Technologie; Verwaltung; Transfer; Wissen; Fachkräfte; Qualifizierung; Weiterbildung; Arbeitsmarkt; Produktivität; lebenslanges Lernen; Wirtschaft; Mittelstand; Hochschule; Bildung | I39: 19 | J39: Arbeitsmarkt, Fachkräfte und Qualifizierung (4) | K39: Static profile activates 5 keyword family/families: KI / Digital, Innovation / Transfer, Fachkräfte / Arbeit / Qualifizierung, Wirtschaft / Mittelstand / Standort, Wissenschaft / Bildung / Hochschule. | L39: Use as evidence, research or transfer partner for digitalization / data / technology opportunity anchor. | M39: https://www.zirp.de/die-zirp/mitglieder/ | N39: Keyword search over existing static ZIRP member fields in this workbook, designed to mirror/search official ZIRP profile info boxes.
A40: 39 | B40: Hochschule Mainz | C40: https://www.hs-mainz.de | D40: academic_support | E40: university_applied_sciences | F40: Hochschule Mainz | academic_support | kultur, technologie, wirtschaft, wissen | Digitale Bau-, Planungs- und Genehmigungsprozesse (5); Kreativwirtschaft, Medien und digitale Öffentlichkeit (5); Arbeitsmarkt, Fachkräfte und Qualifizierung (4); Hochschule-Wirtschaft-Transfer (4); KI, Daten und Verwaltungs-/Wirtschaftsanwendungen (4) | G40: KI / Digital; Innovation / Transfer; Fachkräfte / Arbeit / Qualifizierung; Bau / Raum / Infrastruktur; Wirtschaft / Mittelstand / Standort; Wissenschaft / Bildung / Hochschule; Kultur / Medien / Öffentlichkeit | H40: KI; digital; Daten; IT; Technologie; Verwaltung; Transfer; Wissen; Fachkräfte; Qualifizierung; Arbeitsmarkt; Bau; Planung; Genehmigung; Wirtschaft; Hochschule; Kultur; Medien; Öffentlichkeit; Kreativwirtschaft | I40: 20 | J40: Digitale Bau-, Planungs- und Genehmigungsprozesse (5) | K40: Static profile activates 7 keyword family/families: KI / Digital, Innovation / Transfer, Fachkräfte / Arbeit / Qualifizierung, Bau / Raum / Infrastruktur, Wirtschaft / Mittelstand / Standort, Wissenschaft / Bildung / Hochschule, Kultur / Medien / Öffentlichkeit. | L40: Use as evidence, research or transfer partner for digitalization / data / technology opportunity anchor. | M40: https://www.zirp.de/die-zirp/mitglieder/ | N40: Keyword search over existing static ZIRP member fields in this workbook, designed to mirror/search official ZIRP profile info boxes.
A41: 40 | B41: Hochschule Trier | C41: https://www.hochschule-trier.de | D41: academic_support | E41: university_applied_sciences | F41: Hochschule Trier | academic_support | nachhaltigkeit, technologie, wirtschaft, wissen | Arbeitsmarkt, Fachkräfte und Qualifizierung (4); Hochschule-Wirtschaft-Transfer (4); Wasser, Umwelttechnik und kommunale Resilienz (4); Weiterbildung und lebenslanges Lernen (4); Industrie 4.0, Automatisierung und Produktion (3) | G41: KI / Digital; Innovation / Transfer; Nachhaltigkeit / Klima / Energie; Fachkräfte / Arbeit / Qualifizierung; Wirtschaft / Mittelstand / Standort; Wissenschaft / Bildung / Hochschule | H41: IT; Technologie; Automatisierung; Industrie 4.0; Transfer; Wissen; Nachhaltigkeit; nachhaltig; Umwelt; Fachkräfte; Qualifizierung; Weiterbildung; Arbeitsmarkt; lebenslanges Lernen; Wirtschaft; Industrie; Hochschule; Bildung | I41: 18 | J41: Arbeitsmarkt, Fachkräfte und Qualifizierung (4) | K41: Static profile activates 6 keyword family/families: KI / Digital, Innovation / Transfer, Nachhaltigkeit / Klima / Energie, Fachkräfte / Arbeit / Qualifizierung, Wirtschaft / Mittelstand / Standort, Wissenschaft / Bildung / Hochschule. | L41: Use as evidence, research or transfer partner for digitalization / data / technology opportunity anchor. | M41: https://www.zirp.de/die-zirp/mitglieder/ | N41: Keyword search over existing static ZIRP member fields in this workbook, designed to mirror/search official ZIRP profile info boxes.
A42: 41 | B42: Hochschule Worms | C42: https://www.hs-worms.de | D42: academic_support | E42: university_applied_sciences | F42: Hochschule Worms | academic_support | wirtschaft, wissen | Arbeitsmarkt, Fachkräfte und Qualifizierung (4); Hochschule-Wirtschaft-Transfer (4); Weiterbildung und lebenslanges Lernen (4) | G42: KI / Digital; Innovation / Transfer; Fachkräfte / Arbeit / Qualifizierung; Wirtschaft / Mittelstand / Standort; Wissenschaft / Bildung / Hochschule | H42: IT; Transfer; Wissen; Fachkräfte; Qualifizierung; Weiterbildung; Arbeitsmarkt; lebenslanges Lernen; Wirtschaft; Hochschule; Bildung | I42: 11 | J42: Arbeitsmarkt, Fachkräfte und Qualifizierung (4) | K42: Static profile activates 5 keyword family/families: KI / Digital, Innovation / Transfer, Fachkräfte / Arbeit / Qualifizierung, Wirtschaft / Mittelstand / Standort, Wissenschaft / Bildung / Hochschule. | L42: Use as evidence, research or transfer partner for digitalization / data / technology opportunity anchor. | M42: https://www.zirp.de/die-zirp/mitglieder/ | N42: Keyword search over existing static ZIRP member fields in this workbook, designed to mirror/search official ZIRP profile info boxes.
A43: 42 | B43: IKK Südwest | C43: https://www.ikk-suedwest.de | D43: context_actor | E43: health_social_anchor | F43: IKK Südwest | context_actor | gesellschaft | Gesundheitsversorgung und Prävention (5); Pflege, Fachkräfte und Sozialwirtschaft (4); Sport, Region und gesellschaftliche Identifikation (4) | G43: KI / Digital; Gesundheit / Pflege / Sozialwirtschaft; Fachkräfte / Arbeit / Qualifizierung; Wirtschaft / Mittelstand / Standort; Dialog / Netzwerk / Verantwortung; Kultur / Medien / Öffentlichkeit | H43: IT; Gesundheit; Gesundheitsversorgung; Pflege; Sozialwirtschaft; Prävention; Versorgung; Fachkräfte; Wirtschaft; gesellschaftlich; Region; gesellschaftliche Identifikation | I43: 12 | J43: Gesundheitsversorgung und Prävention (5) | K43: Static profile activates 6 keyword family/families: KI / Digital, Gesundheit / Pflege / Sozialwirtschaft, Fachkräfte / Arbeit / Qualifizierung, Wirtschaft / Mittelstand / Standort, Dialog / Netzwerk / Verantwortung, Kultur / Medien / Öffentlichkeit. | L43: Use as convening/context partner for health/social-sector opportunity anchor. | M43: https://www.zirp.de/die-zirp/mitglieder/ | N43: Keyword search over existing static ZIRP member fields in this workbook, designed to mirror/search official ZIRP profile info boxes.
... A59: 58 | B59: KÜBLER GmbH | C59: https://www.kuebler-hallenheizungen.de | D59: profit_anchor | E59: energy_infrastructure_anchor | F59: KÜBLER GmbH | profit_anchor | nachhaltigkeit, technologie, wirtschaft | Energie, Netze und Versorgungssicherheit (4); Industrie 4.0, Automatisierung und Produktion (3); Mittelstand, Digitalisierung und Produktivität (3) | G59: KI / Digital; Nachhaltigkeit / Klima / Energie; Gesundheit / Pflege / Sozialwirtschaft; Fachkräfte / Arbeit / Qualifizierung; Wirtschaft / Mittelstand / Standort | H59: Digitalisierung; digital; IT; Technologie; Automatisierung; Industrie 4.0; Nachhaltigkeit; nachhaltig; Energie; Netze; Versorgungssicherheit; Versorgung; Produktivität; Wirtschaft; Mittelstand; Industrie | I59: 16 | J59: Energie, Netze und Versorgungssicherheit (4) | K59: Static profile activates 5 keyword family/families: KI / Digital, Nachhaltigkeit / Klima / Energie, Gesundheit / Pflege / Sozialwirtschaft, Fachkräfte / Arbeit / Qualifizierung, Wirtschaft / Mittelstand / Standort. | L59: Use as implementation/commercial partner for health/social-sector opportunity anchor. | M59: https://www.zirp.de/die-zirp/mitglieder/ | N59: Keyword search over existing static ZIRP member fields in this workbook, designed to mirror/search official ZIRP profile info boxes.
A60: 59 | B60: L Q M Marktforschung GmbH | D60: profit_anchor | E60: professional_services_anchor | F60: L Q M Marktforschung GmbH | profit_anchor | | | G60: KI / Digital; Innovation / Transfer | H60: IT; Forschung | I60: 2 | K60: Static profile activates 2 keyword family/families: KI / Digital, Innovation / Transfer. | L60: Use as implementation/commercial partner for digitalization / data / technology opportunity anchor. | M60: https://www.zirp.de/die-zirp/mitglieder/ | N60: Keyword search over existing static ZIRP member fields in this workbook, designed to mirror/search official ZIRP profile info boxes.
A61: 60 | B61: Landesbank Baden-Württemberg (LBBW) | C61: https://www.lbbw.de | D61: profit_anchor | E61: bank_finance_anchor | F61: Landesbank Baden-Württemberg (LBBW) | profit_anchor | nachhaltigkeit, technologie, wirtschaft | Finanzierung und Förderung von Transformation (5); Standort, Investition und industrielle Transformation (5); Cyberresilienz und kritische Infrastruktur (4); Energie, Netze und Versorgungssicherheit (3) | G61: KI / Digital; Nachhaltigkeit / Klima / Energie; Gesundheit / Pflege / Sozialwirtschaft; Bau / Raum / Infrastruktur; Wirtschaft / Mittelstand / Standort | H61: IT; Technologie; Cyber; Nachhaltigkeit; nachhaltig; Energie; Netze; Versorgungssicherheit; Land; Versorgung; Infrastruktur; Wirtschaft; Standort; Industrie; Investition; Transformation; Förderung; Finanzierung | I61: 18 | J61: Finanzierung und Förderung von Transformation (5) | K61: Static profile activates 5 keyword family/families: KI / Digital, Nachhaltigkeit / Klima / Energie, Gesundheit / Pflege / Sozialwirtschaft, Bau / Raum / Infrastruktur, Wirtschaft / Mittelstand / Standort. | L61: Use as implementation/commercial partner for health/social-sector opportunity anchor. | M61: https://www.zirp.de/die-zirp/mitglieder/ | N61: Keyword search over existing static ZIRP member fields in this workbook, designed to mirror/search official ZIRP profile info boxes.
A62: 61 | B62: LandesPsychotherapeutenKammer Rheinland-Pfalz | C62: https://www.lpk-rlp.de | D62: implementation_anchor | E62: health_social_anchor | F62: LandesPsychotherapeutenKammer Rheinland-Pfalz | implementation_anchor | gesellschaft | Gesundheitsversorgung und Prävention (4); Pflege, Fachkräfte und Sozialwirtschaft (4) | G62: KI / Digital; Nachhaltigkeit / Klima / Energie; Gesundheit / Pflege / Sozialwirtschaft; Fachkräfte / Arbeit / Qualifizierung; Wirtschaft / Mittelstand / Standort | H62: IT; Land; Gesundheit; Gesundheitsversorgung; Pflege; Sozialwirtschaft; Prävention; Versorgung; Fachkräfte; Wirtschaft | I62: 10 | J62: Gesundheitsversorgung und Prävention (4) | K62: Static profile activates 5 keyword family/families: KI / Digital, Nachhaltigkeit / Klima / Energie, Gesundheit / Pflege / Sozialwirtschaft, Fachkräfte / Arbeit / Qualifizierung, Wirtschaft / Mittelstand / Standort. | L62: Use as institutional implementation partner for health/social-sector opportunity anchor. | M62: https://www.zirp.de/die-zirp/mitglieder/ | N62: Keyword search over existing static ZIRP member fields in this workbook, designed to mirror/search official ZIRP profile info boxes.
A63: 62 | B63: Landesärztekammer Rheinland-Pfalz | C63: https://www.laek-rlp.de | D63: implementation_anchor | E63: health_social_anchor | F63: Landesärztekammer Rheinland-Pfalz | implementation_anchor | gesellschaft | Gesundheitsversorgung und Prävention (5); Pflege, Fachkräfte und Sozialwirtschaft (4) | G63: KI / Digital; Nachhaltigkeit / Klima / Energie; Gesundheit / Pflege / Sozialwirtschaft; Fachkräfte / Arbeit / Qualifizierung; Wirtschaft / Mittelstand / Standort | H63: IT; Land; Gesundheit; Gesundheitsversorgung; Pflege; Sozialwirtschaft; Prävention; Versorgung; Fachkräfte; Wirtschaft | I63: 10 | J63: Gesundheitsversorgung und Prävention (5) | K63: Static profile activates 5 keyword family/families: KI / Digital, Nachhaltigkeit / Klima / Energie, Gesundheit / Pflege / Sozialwirtschaft, Fachkräfte / Arbeit / Qualifizierung, Wirtschaft / Mittelstand / Standort. | L63: Use as institutional implementation partner for health/social-sector opportunity anchor. | M63: https://www.zirp.de/die-zirp/mitglieder/ | N63: Keyword search over existing static ZIRP member fields in this workbook, designed to mirror/search official ZIRP profile info boxes.
A64: 63 | B64: Landkreistag Rheinland-Pfalz | C64: https://www.landkreistag.rlp.de | D64: context_actor | E64: public_policy_anchor | F64: Landkreistag Rheinland-Pfalz | context_actor | nachhaltigkeit, technologie, wissen | Digitale Bau-, Planungs- und Genehmigungsprozesse (5); Klimaanpassung in Stadt und Land (5); Kreislaufwirtschaft, Bau und Ersatzbaustoffverordnung (5); Verwaltungswissen und digitale Umsetzung (5); Cyberresilienz und kritische Infrastruktur (4) | G64: KI / Digital; Innovation / Transfer; Nachhaltigkeit / Klima / Energie; Bau / Raum / Infrastruktur; Wirtschaft / Mittelstand / Standort; Wissenschaft / Bildung / Hochschule | H64: digital; IT; Technologie; Cyber; Verwaltung; Wissen; Nachhaltigkeit; nachhaltig; Klima; Klimaanpassung; Kreislauf; Ersatzbaustoff; Land; Stadt; Bau; Infrastruktur; Planung; Genehmigung; Wirtschaft | I64: 19 | J64: Digitale Bau-, Planungs- und Genehmigungsprozesse (5) | K64: Static profile activates 6 keyword family/families: KI / Digital, Innovation / Transfer, Nachhaltigkeit / Klima / Energie, Bau / Raum / Infrastruktur, Wirtschaft / Mittelstand / Standort, Wissenschaft / Bildung / Hochschule. | L64: Use as convening/context partner for digitalization / data / technology opportunity anchor. | M64: https://www.zirp.de/die-zirp/mitglieder/ | N64: Keyword search over existing static ZIRP member fields in this workbook, designed to mirror/search official ZIRP profile info boxes.
A65: 64 | B65: Leonardo PersonalKonzept GmbH | C65: https://www.leonardo-personal.de | D65: profit_anchor | E65: professional_services_anchor | F65: Leonardo PersonalKonzept GmbH | profit_anchor | gesellschaft, wirtschaft, wissen | Arbeitsmarkt, Fachkräfte und Qualifizierung (4); Teilhabe, Inklusion und Arbeitsmarkt (4); Pflege, Fachkräfte und Sozialwirtschaft (3); Weiterbildung und lebenslanges Lernen (3) | G65: KI / Digital; Innovation / Transfer; Gesundheit / Pflege / Sozialwirtschaft; Fachkräfte / Arbeit / Qualifizierung; Wirtschaft / Mittelstand / Standort; Wissenschaft / Bildung / Hochschule | H65: IT; Wissen; Pflege; Sozialwirtschaft; Teilhabe; Fachkräfte; Qualifizierung; Weiterbildung; Arbeitsmarkt; Personal; lebenslanges Lernen; Wirtschaft; Bildung | I65: 13 | J65: Arbeitsmarkt, Fachkräfte und Qualifizierung (4) | K65: Static profile activates 6 keyword family/families: KI / Digital, Innovation / Transfer, Gesundheit / Pflege / Sozialwirtschaft, Fachkräfte / Arbeit / Qualifizierung, Wirtschaft / Mittelstand / Standort, Wissenschaft / Bildung / Hochschule. | L65: Use as implementation/commercial partner for health/social-sector opportunity anchor. | M65: https://www.zirp.de/die-zirp/mitglieder/ | N65: Keyword search over existing static ZIRP member fields in this workbook, designed to mirror/search official ZIRP profile info boxes.
A66: 65 | B66: Licharz GmbH | C66: https://www.licharz.com | D66: profit_anchor | E66: industry_anchor | F66: Licharz GmbH | profit_anchor | technologie, wirtschaft | Industrie 4.0, Automatisierung und Produktion (3); Mittelstand, Digitalisierung und Produktivität (3) | G66: KI / Digital; Fachkräfte / Arbeit / Qualifizierung; Wirtschaft / Mittelstand / Standort | H66: Digitalisierung; digital; IT; Technologie; Automatisierung; Industrie 4.0; Produktivität; Wirtschaft; Mittelstand; Industrie | I66: 10 | J66: Industrie 4.0, Automatisierung und Produktion (3) | K66: Static profile activates 3 keyword family/families: KI / Digital, Fachkräfte / Arbeit / Qualifizierung, Wirtschaft / Mittelstand / Standort. | L66: Use as implementation/commercial partner for digitalization / data / technology opportunity anchor. | M66: https://www.zirp.de/die-zirp/mitglieder/ | N66: Keyword search over existing static ZIRP member fields in this workbook, designed to mirror/search official ZIRP profile info boxes.
A67: 66 | B67: LOTTO Rheinland-Pfalz GmbH | C67: https://www.lotto-rlp.de | D67: profit_anchor | E67: culture_foundation_anchor | F67: LOTTO Rheinland-Pfalz GmbH | profit_anchor | gesellschaft, kultur | Sport, Region und gesellschaftliche Identifikation (4); Kultur, Standortidentität und regionale Attraktivität (3); Talentförderung, Musik und Nachwuchs (3) | G67: KI / Digital; Nachhaltigkeit / Klima / Energie; Wirtschaft / Mittelstand / Standort; Dialog / Netzwerk / Verantwortung; Kultur / Medien / Öffentlichkeit | H67: IT; Land; Standort; Förderung; gesellschaftlich; Kultur; Musik; Standortidentität; Region; gesellschaftliche Identifikation | I67: 10 | J67: Sport, Region und gesellschaftliche Identifikation (4) | K67: Static profile activates 5 keyword family/families: KI / Digital, Nachhaltigkeit / Klima / Energie, Wirtschaft / Mittelstand / Standort, Dialog / Netzwerk / Verantwortung, Kultur / Medien / Öffentlichkeit. | L67: Use as implementation/commercial partner for digitalization / data / technology opportunity anchor. | M67: https://www.zirp.de/die-zirp/mitglieder/ | N67: Keyword search over existing static ZIRP member fields in this workbook, designed to mirror/search official ZIRP profile info boxes.
A68: 67 | B68: LÖWEN ENTERTAINMENT GmbH | C68: https://www.loewen.de | D68: profit_anchor | E68: technology_digital_anchor | F68: LÖWEN ENTERTAINMENT GmbH | profit_anchor | | | G68: KI / Digital | H68: IT | I68: 1 | K68: Static profile activates 1 keyword family/families: KI / Digital. | L68: Use as implementation/commercial partner for digitalization / data / technology opportunity anchor. | M68: https://www.zirp.de/die-zirp/mitglieder/ | N68: Keyword search over existing static ZIRP member fields in this workbook, designed to mirror/search official ZIRP profile info boxes.
A69: 68 | B69: Mainzer Stadtwerke AG | C69: https://www.mainzer-stadtwerke.de | D69: profit_anchor | E69: energy_infrastructure_anchor | F69: Mainzer Stadtwerke AG | profit_anchor | nachhaltigkeit, technologie | Cyberresilienz und kritische Infrastruktur (5); Energie, Netze und Versorgungssicherheit (5); Klimaanpassung in Stadt und Land (4); Wasser, Umwelttechnik und kommunale Resilienz (4) | G69: KI / Digital; Nachhaltigkeit / Klima / Energie; Gesundheit / Pflege / Sozialwirtschaft; Bau / Raum / Infrastruktur | H69: IT; Technologie; Cyber; Nachhaltigkeit; nachhaltig; Klima; Klimaanpassung; Umwelt; Energie; Netze; Versorgungssicherheit; Land; Stadt; Versorgung; Infrastruktur | I69: 15 | J69: Cyberresilienz und kritische Infrastruktur (5) | K69: Static profile activates 4 keyword family/families: KI / Digital, Nachhaltigkeit / Klima / Energie, Gesundheit / Pflege / Sozialwirtschaft, Bau / Raum / Infrastruktur. | L69: Use as implementation/commercial partner for health/social-sector opportunity anchor. | M69: https://www.zirp.de/die-zirp/mitglieder/ | N69: Keyword search over existing static ZIRP member fields in this workbook, designed to mirror/search official ZIRP profile info boxes.
A70: 69 | B70: Michelin Reifenwerke AG & Co. KGaA | C70: https://www.michelin.de | D70: profit_anchor | E70: industry_anchor | F70: Michelin Reifenwerke AG & Co. KGaA | profit_anchor | nachhaltigkeit, technologie, wirtschaft | Industrie 4.0, Automatisierung und Produktion (4); Standort, Investition und industrielle Transformation (4); Energie, Netze und Versorgungssicherheit (3) | G70: KI / Digital; Nachhaltigkeit / Klima / Energie; Gesundheit / Pflege / Sozialwirtschaft; Wirtschaft / Mittelstand / Standort | H70: IT; Technologie; Automatisierung; Industrie 4.0; Nachhaltigkeit; nachhaltig; Energie; Netze; Versorgungssicherheit; Versorgung; Wirtschaft; Standort; Industrie; Investition; Transformation | I70: 15 | J70: Industrie 4.0, Automatisierung und Produktion (4) | K70: Static profile activates 4 keyword family/families: KI / Digital, Nachhaltigkeit / Klima / Energie, Gesundheit / Pflege / Sozialwirtschaft, Wirtschaft / Mittelstand / Standort. | L70: Use as implementation/commercial partner for health/social-sector opportunity anchor. | M70: https://www.zirp.de/die-zirp/mitglieder/ | N70: Keyword search over existing static ZIRP member fields in this workbook, designed to mirror/search official ZIRP profile info boxes.
A71: 70 | B71: Ministerium für Wirtschaft, Verkehr, Landwirtschaft und Weinbau | C71: https://mwvlw.rlp.de | D71: profit_anchor | E71: public_policy_anchor | F71: Ministerium für Wirtschaft, Verkehr, Landwirtschaft und Weinbau | profit_anchor | technologie, wirtschaft, wissen | Finanzierung und Förderung von Transformation (5); Standort, Investition und industrielle Transformation (5); Verwaltungswissen und digitale Umsetzung (5); Arbeitsmarkt, Fachkräfte und Qualifizierung (4); Digitale Bau-, Planungs- und Genehmigungsprozesse (4) | G71: KI / Digital; Innovation / Transfer; Nachhaltigkeit / Klima / Energie; Fachkräfte / Arbeit / Qualifizierung; Bau / Raum / Infrastruktur; Wirtschaft / Mittelstand / Standort; Wissenschaft / Bildung / Hochschule | H71: digital; IT; Technologie; Verwaltung; Wissen; Land; Fachkräfte; Qualifizierung; Arbeitsmarkt; Bau; Planung; Genehmigung; Verkehr; Wirtschaft; Standort; Industrie; Investition; Transformation; Förderung; Finanzierung | I71: 20 | J71: Finanzierung und Förderung von Transformation (5) | K71: Static profile activates 7 keyword family/families: KI / Digital, Innovation / Transfer, Nachhaltigkeit / Klima / Energie, Fachkräfte / Arbeit / Qualifizierung, Bau / Raum / Infrastruktur, Wirtschaft / Mittelstand / Standort, Wissenschaft / Bildung / Hochschule. | L71: Use as implementation/commercial partner for digitalization / data / technology opportunity anchor. | M71: https://www.zirp.de/die-zirp/mitglieder/ | N71: Keyword search over existing static ZIRP member fields in this workbook, designed to mirror/search official ZIRP profile info boxes.
A72: 71 | B72: PFAFF Industriesysteme und Maschinen GmbH | C72: https://www.pfaff-industrial.com | D72: profit_anchor | E72: industry_anchor | F72: PFAFF Industriesysteme und Maschinen GmbH | profit_anchor | technologie, wirtschaft | Industrie 4.0, Automatisierung und Produktion (5); Mittelstand, Digitalisierung und Produktivität (4) | G72: KI / Digital; Fachkräfte / Arbeit / Qualifizierung; Wirtschaft / Mittelstand / Standort | H72: Digitalisierung; digital; IT; Technologie; Automatisierung; Industrie 4.0; Produktivität; Wirtschaft; Mittelstand; Industrie | I72: 10 | J72: Industrie 4.0, Automatisierung und Produktion (5) | K72: Static profile activates 3 keyword family/families: KI / Digital, Fachkräfte / Arbeit / Qualifizierung, Wirtschaft / Mittelstand / Standort. | L72: Use as implementation/commercial partner for digitalization / data / technology opportunity anchor. | M72: https://www.zirp.de/die-zirp/mitglieder/ | N72: Keyword search over existing static ZIRP member fields in this workbook, designed to mirror/search official ZIRP profile info boxes.
A73: 72 | B73: Pfalzwerke AG | C73: https://www.pfalzwerke.de | D73: profit_anchor | E73: energy_infrastructure_anchor | F73: Pfalzwerke AG | profit_anchor | nachhaltigkeit, technologie, wirtschaft | Cyberresilienz und kritische Infrastruktur (5); Energie, Netze und Versorgungssicherheit (5); Finanzierung und Förderung von Transformation (3); Klimaanpassung in Stadt und Land (3); Wasser, Umwelttechnik und kommunale Resilienz (3) | G73: KI / Digital; Nachhaltigkeit / Klima / Energie; Gesundheit / Pflege / Sozialwirtschaft; Bau / Raum / Infrastruktur; Wirtschaft / Mittelstand / Standort | H73: IT; Technologie; Cyber; Nachhaltigkeit; nachhaltig; Klima; Klimaanpassung; Umwelt; Energie; Netze; Versorgungssicherheit; Land; Stadt; Versorgung; Infrastruktur; Wirtschaft; Transformation; Förderung; Finanzierung | I73: 19 | J73: Cyberresilienz und kritische Infrastruktur (5) | K73: Static profile activates 5 keyword family/families: KI / Digital, Nachhaltigkeit / Klima / Energie, Gesundheit / Pflege / Sozialwirtschaft, Bau / Raum / Infrastruktur, Wirtschaft / Mittelstand / Standort. | L73: Use as implementation/commercial partner for health/social-sector opportunity anchor. | M73: https://www.zirp.de/die-zirp/mitglieder/ | N73: Keyword search over existing static ZIRP member fields in this workbook, designed to mirror/search official ZIRP profile info boxes.
A74: 73 | B74: Provinzial Versicherung AG | C74: http://www.provinzial.de | D74: profit_anchor | E74: bank_finance_anchor | F74: Provinzial Versicherung AG | profit_anchor | technologie, wirtschaft | Cyberresilienz und kritische Infrastruktur (4); Finanzierung und Förderung von Transformation (4) | G74: KI / Digital; Bau / Raum / Infrastruktur; Wirtschaft / Mittelstand / Standort | H74: IT; Technologie; Cyber; Infrastruktur; Wirtschaft; Transformation; Förderung; Finanzierung | I74: 8 | J74: Cyberresilienz und kritische Infrastruktur (4) | K74: Static profile activates 3 keyword family/families: KI / Digital, Bau / Raum / Infrastruktur, Wirtschaft / Mittelstand / Standort. | L74: Use as implementation/commercial partner for digitalization / data / technology opportunity anchor. | M74: https://www.zirp.de/die-zirp/mitglieder/ | N74: Keyword search over existing static ZIRP member fields in this workbook, designed to mirror/search official ZIRP profile info boxes.
A75: 74 | B75: Rheinland-Pfälzische Technische Universität Kaiserslautern-Landau (RPTU) | C75: https://regionalentwicklung-raumordnung.de | D75: academic_support | E75: university_research | F75: Rheinland-Pfälzische Technische Universität Kaiserslautern-Landau (RPTU) | academic_support | technologie, wirtschaft, wissen | Cyberresilienz und kritische Infrastruktur (5); Hochschule-Wirtschaft-Transfer (5); Industrie 4.0, Automatisierung und Produktion (5); KI, Daten und Verwaltungs-/Wirtschaftsanwendungen (5); Mittelstand, Digitalisierung und Produktivität (5) | G75: KI / Digital; Innovation / Transfer; Nachhaltigkeit / Klima / Energie; Fachkräfte / Arbeit / Qualifizierung; Bau / Raum / Infrastruktur; Wirtschaft / Mittelstand / Standort; Wissenschaft / Bildung / Hochschule | H75: KI; Digitalisierung; digital; Daten; IT; Technologie; Cyber; Automatisierung; Industrie 4.0; Verwaltung; Transfer; Wissen; Land; Produktivität; Infrastruktur; Wirtschaft; Mittelstand; Industrie; Hochschule; Universität | I75: 20 | J75: Cyberresilienz und kritische Infrastruktur (5) | K75: Static profile activates 7 keyword family/families: KI / Digital, Innovation / Transfer, Nachhaltigkeit / Klima / Energie, Fachkräfte / Arbeit / Qualifizierung, Bau / Raum / Infrastruktur, Wirtschaft / Mittelstand / Standort, Wissenschaft / Bildung / Hochschule. | L75: Use as evidence, research or transfer partner for digitalization / data / technology opportunity anchor. | M75: https://www.zirp.de/die-zirp/mitglieder/ | N75: Keyword search over existing static ZIRP member fields in this workbook, designed to mirror/search official ZIRP profile info boxes.
A76: 75 | B76: robotspaceship | C76: https://www.robotspaceship.ai | D76: context_actor | E76: technology_digital_anchor | F76: robotspaceship | context_actor | kultur, technologie, wirtschaft | KI, Daten und Verwaltungs-/Wirtschaftsanwendungen (5); Mittelstand, Digitalisierung und Produktivität (5); Kreativwirtschaft, Medien und digitale Öffentlichkeit (4) | G76: KI / Digital; Fachkräfte / Arbeit / Qualifizierung; Wirtschaft / Mittelstand / Standort; Kultur / Medien / Öffentlichkeit | H76: KI; Digitalisierung; digital; Daten; IT; Technologie; Verwaltung; Produktivität; Wirtschaft; Mittelstand; Kultur; Medien; Öffentlichkeit; Kreativwirtschaft | I76: 14 | J76: KI, Daten und Verwaltungs-/Wirtschaftsanwendungen (5) | K76: Static profile activates 4 keyword family/families: KI / Digital, Fachkräfte / Arbeit / Qualifizierung, Wirtschaft / Mittelstand / Standort, Kultur / Medien / Öffentlichkeit. | L76: Use as convening/context partner for digitalization / data / technology opportunity anchor. | M76: https://www.zirp.de/die-zirp/mitglieder/ | N76: Keyword search over existing static ZIRP member fields in this workbook, designed to mirror/search official ZIRP profile info boxes.
A77: 76 | B77: RPR1. | C77: https://www.rpr1.de | D77: context_actor | E77: media_publicity_anchor | F77: RPR1. | context_actor | gesellschaft, kultur, wissen | Demokratie, Medien und gesellschaftlicher Zusammenhalt (5); Kreativwirtschaft, Medien und digitale Öffentlichkeit (5); Kultur, Standortidentität und regionale Attraktivität (4); Sport, Region und gesellschaftliche Identifikation (4); Wissenschaft, Demokratie und gesellschaftlicher Zusammenhalt (4) | G77: KI / Digital; Innovation / Transfer; Wirtschaft / Mittelstand / Standort; Wissenschaft / Bildung / Hochschule; Dialog / Netzwerk / Verantwortung; Kultur / Medien / Öffentlichkeit | H77: digital; IT; Wissen; Wirtschaft; Standort; Wissenschaft; gesellschaftlich; Zusammenhalt; Kultur; Medien; Öffentlichkeit; Kreativwirtschaft; Standortidentität; Region; gesellschaftliche Identifikation; Demokratie | I77: 16 | J77: Demokratie, Medien und gesellschaftlicher Zusammenhalt (5) | K77: Static profile activates 6 keyword family/families: KI / Digital, Innovation / Transfer, Wirtschaft / Mittelstand / Standort, Wissenschaft / Bildung / Hochschule, Dialog / Netzwerk / Verantwortung, Kultur / Medien / Öffentlichkeit. | L77: Use as convening/context partner for digitalization / data / technology opportunity anchor. | M77: https://www.zirp.de/die-zirp/mitglieder/ | N77: Keyword search over existing static ZIRP member fields in this workbook, designed to mirror/search official ZIRP profile info boxes.
A78: 77 | B78: Schoenergie GmbH | C78: http://www.schoenergie.de | D78: profit_anchor | E78: energy_infrastructure_anchor | F78: Schoenergie GmbH | profit_anchor | nachhaltigkeit | Energie, Netze und Versorgungssicherheit (4) | G78: KI / Digital; Nachhaltigkeit / Klima / Energie; Gesundheit / Pflege / Sozialwirtschaft | H78: IT; Nachhaltigkeit; nachhaltig; Energie; Netze; Versorgungssicherheit; Versorgung | I78: 7 | J78: Energie, Netze und Versorgungssicherheit (4) | K78: Static profile activates 3 keyword family/families: KI / Digital, Nachhaltigkeit / Klima / Energie, Gesundheit / Pflege / Sozialwirtschaft. | L78: Use as implementation/commercial partner for health/social-sector opportunity anchor. | M78: https://www.zirp.de/die-zirp/mitglieder/ | N78: Keyword search over existing static ZIRP member fields in this workbook, designed to mirror/search official ZIRP profile info boxes.
A79: 78 | B79: SCHOTT AG | C79: https://www.schott.com | D79: profit_anchor | E79: industry_anchor | F79: SCHOTT AG | profit_anchor | nachhaltigkeit, technologie, wirtschaft, wissen | Standort, Investition und industrielle Transformation (5); Energie, Netze und Versorgungssicherheit (4); Hochschule-Wirtschaft-Transfer (4); Industrie 4.0, Automatisierung und Produktion (4); Finanzierung und Förderung von Transformation (3) | G79: KI / Digital; Innovation / Transfer; Nachhaltigkeit / Klima / Energie; Gesundheit / Pflege / Sozialwirtschaft; Wirtschaft / Mittelstand / Standort; Wissenschaft / Bildung / Hochschule | H79: IT; Technologie; Automatisierung; Industrie 4.0; Transfer; Wissen; Nachhaltigkeit; nachhaltig; Energie; Netze; Versorgungssicherheit; Versorgung; Wirtschaft; Standort; Industrie; Investition; Transformation; Förderung; Finanzierung; Hochschule | I79: 20 | J79: Standort, Investition und industrielle Transformation (5) | K79: Static profile activates 6 keyword family/families: KI / Digital, Innovation / Transfer, Nachhaltigkeit / Klima / Energie, Gesundheit / Pflege / Sozialwirtschaft, Wirtschaft / Mittelstand / Standort, Wissenschaft / Bildung / Hochschule. | L79: Use as implementation/commercial partner for health/social-sector opportunity anchor. | M79: https://www.zirp.de/die-zirp/mitglieder/ | N79: Keyword search over existing static ZIRP member fields in this workbook, designed to mirror/search official ZIRP profile info boxes.
A80: 79 | B80: Schuler Service GmbH & Co. KG | C80: https://www.schuler-service.com | D80: profit_anchor | E80: industry_anchor | F80: Schuler Service GmbH & Co. KG | profit_anchor | | | G80: KI / Digital | H80: IT | I80: 1 | K80: Static profile activates 1 keyword family/families: KI / Digital. | L80: Use as implementation/commercial partner for digitalization / data / technology opportunity anchor. | M80: https://www.zirp.de/die-zirp/mitglieder/ | N80: Keyword search over existing static ZIRP member fields in this workbook, designed to mirror/search official ZIRP profile info boxes.
A81: 80 | B81: SIMONA AG | C81: https://www.simona.de | D81: profit_anchor | E81: industry_anchor | F81: SIMONA AG | profit_anchor | nachhaltigkeit, technologie, wirtschaft | Standort, Investition und industrielle Transformation (4); Energie, Netze und Versorgungssicherheit (3); Industrie 4.0, Automatisierung und Produktion (3) | G81: KI / Digital; Nachhaltigkeit / Klima / Energie; Gesundheit / Pflege / Sozialwirtschaft; Wirtschaft / Mittelstand / Standort | H81: IT; Technologie; Automatisierung; Industrie 4.0; Nachhaltigkeit; nachhaltig; Energie; Netze; Versorgungssicherheit; Versorgung; Wirtschaft; Standort; Industrie; Investition; Transformation | I81: 15 | J81: Standort, Investition und industrielle Transformation (4) | K81: Static profile activates 4 keyword family/families: KI / Digital, Nachhaltigkeit / Klima / Energie, Gesundheit / Pflege / Sozialwirtschaft, Wirtschaft / Mittelstand / Standort. | L81: Use as implementation/commercial partner for health/social-sector opportunity anchor. | M81: https://www.zirp.de/die-zirp/mitglieder/ | N81: Keyword search over existing static ZIRP member fields in this workbook, designed to mirror/search official ZIRP profile info boxes.
A82: 81 | B82: SmartFactory KL e.V. | C82: https://smartfactory.de | D82: context_actor | E82: technology_digital_anchor | F82: SmartFactory KL e.V. | context_actor | technologie, wirtschaft, wissen | Hochschule-Wirtschaft-Transfer (5); Industrie 4.0, Automatisierung und Produktion (5); Mittelstand, Digitalisierung und Produktivität (5); KI, Daten und Verwaltungs-/Wirtschaftsanwendungen (4) | G82: KI / Digital; Innovation / Transfer; Fachkräfte / Arbeit / Qualifizierung; Wirtschaft / Mittelstand / Standort; Wissenschaft / Bildung / Hochschule | H82: KI; Digitalisierung; digital; Daten; IT; Technologie; Automatisierung; Industrie 4.0; Verwaltung; Transfer; Wissen; Produktivität; Wirtschaft; Mittelstand; Industrie; Hochschule | I82: 16 | J82: Hochschule-Wirtschaft-Transfer (5) | K82: Static profile activates 5 keyword family/families: KI / Digital, Innovation / Transfer, Fachkräfte / Arbeit / Qualifizierung, Wirtschaft / Mittelstand / Standort, Wissenschaft / Bildung / Hochschule. | L82: Use as convening/context partner for digitalization / data / technology opportunity anchor. | M82: https://www.zirp.de/die-zirp/mitglieder/ | N82: Keyword search over existing static ZIRP member fields in this workbook, designed to mirror/search official ZIRP profile info boxes.
A83: 82 | B83: Sparkassenverband Rheinland-Pfalz | C83: https://www.sv-rlp.de | D83: profit_anchor | E83: bank_finance_anchor | F83: Sparkassenverband Rheinland-Pfalz | profit_anchor | technologie, wirtschaft, wissen | Finanzierung und Förderung von Transformation (5); Cyberresilienz und kritische Infrastruktur (4); Standort, Investition und industrielle Transformation (4); Mittelstand, Digitalisierung und Produktivität (3); Verwaltungswissen und digitale Umsetzung (3) | G83: KI / Digital; Innovation / Transfer; Nachhaltigkeit / Klima / Energie; Fachkräfte / Arbeit / Qualifizierung; Bau / Raum / Infrastruktur; Wirtschaft / Mittelstand / Standort; Wissenschaft / Bildung / Hochschule | H83: Digitalisierung; digital; IT; Technologie; Cyber; Verwaltung; Wissen; Land; Produktivität; Infrastruktur; Wirtschaft; Standort; Mittelstand; Industrie; Investition; Transformation; Förderung; Finanzierung | I83: 18 | J83: Finanzierung und Förderung von Transformation (5) | K83: Static profile activates 7 keyword family/families: KI / Digital, Innovation / Transfer, Nachhaltigkeit / Klima / Energie, Fachkräfte / Arbeit / Qualifizierung, Bau / Raum / Infrastruktur, Wirtschaft / Mittelstand / Standort, Wissenschaft / Bildung / Hochschule. | L83: Use as implementation/commercial partner for digitalization / data / technology opportunity anchor. | M83: https://www.zirp.de/die-zirp/mitglieder/ | N83: Keyword search over existing static ZIRP member fields in this workbook, designed to mirror/search official ZIRP profile info boxes.
A84: 83 | B84: Staatskanzlei des Landes Rheinland-Pfalz | C84: https://www.rlp.de/regierung/staatskanzlei | D84: context_actor | E84: public_policy_anchor | F84: Staatskanzlei des Landes Rheinland-Pfalz | context_actor | gesellschaft, technologie, wissen | Cyberresilienz und kritische Infrastruktur (5); Demokratie, Medien und gesellschaftlicher Zusammenhalt (5); Verwaltungswissen und digitale Umsetzung (5); Wissenschaft, Demokratie und gesellschaftlicher Zusammenhalt (5); Digitale Bau-, Planungs- und Genehmigungsprozesse (4) | G84: KI / Digital; Innovation / Transfer; Nachhaltigkeit / Klima / Energie; Bau / Raum / Infrastruktur; Wissenschaft / Bildung / Hochschule; Dialog / Netzwerk / Verantwortung; Kultur / Medien / Öffentlichkeit | H84: digital; IT; Technologie; Cyber; Verwaltung; Wissen; Land; Bau; Infrastruktur; Planung; Genehmigung; Wissenschaft; gesellschaftlich; Zusammenhalt; Medien; Demokratie | I84: 16 | J84: Cyberresilienz und kritische Infrastruktur (5) | K84: Static profile activates 7 keyword family/families: KI / Digital, Innovation / Transfer, Nachhaltigkeit / Klima / Energie, Bau / Raum / Infrastruktur, Wissenschaft / Bildung / Hochschule, Dialog / Netzwerk / Verantwortung, Kultur / Medien / Öffentlichkeit. | L84: Use as convening/context partner for digitalization / data / technology opportunity anchor. | M84: https://www.zirp.de/die-zirp/mitglieder/ | N84: Keyword search over existing static ZIRP member fields in this workbook, designed to mirror/search official ZIRP profile info boxes.
A85: 84 | B85: Steuerberaterkammer Rheinland-Pfalz | C85: https://www.sbk-rlp.de | D85: implementation_anchor | E85: chamber_association_anchor | F85: Steuerberaterkammer Rheinland-Pfalz | implementation_anchor | | | G85: Nachhaltigkeit / Klima / Energie | H85: Land | I85: 1 | K85: Static profile activates 1 keyword family/families: Nachhaltigkeit / Klima / Energie. | L85: Use as institutional implementation partner for sustainability / climate / energy opportunity anchor. | M85: https://www.zirp.de/die-zirp/mitglieder/ | N85: Keyword search over existing static ZIRP member fields in this workbook, designed to mirror/search official ZIRP profile info boxes.
A86: 85 | B86: Städtetag Rheinland-Pfalz | C86: https://www.staedtetag-rlp.de | D86: context_actor | E86: public_policy_anchor | F86: Städtetag Rheinland-Pfalz | context_actor | kultur, nachhaltigkeit, technologie, wissen | Digitale Bau-, Planungs- und Genehmigungsprozesse (5); Klimaanpassung in Stadt und Land (5); Kreislaufwirtschaft, Bau und Ersatzbaustoffverordnung (5); Kultur, Standortidentität und regionale Attraktivität (5); Verwaltungswissen und digitale Umsetzung (5) | G86: KI / Digital; Innovation / Transfer; Nachhaltigkeit / Klima / Energie; Bau / Raum / Infrastruktur; Wirtschaft / Mittelstand / Standort; Wissenschaft / Bildung / Hochschule; Kultur / Medien / Öffentlichkeit | H86: digital; IT; Technologie; Verwaltung; Wissen; Nachhaltigkeit; nachhaltig; Klima; Klimaanpassung; Kreislauf; Ersatzbaustoff; Land; Stadt; Bau; Planung; Genehmigung; Wirtschaft; Standort; Kultur; Standortidentität; Region | I86: 21 | J86: Digitale Bau-, Planungs- und Genehmigungsprozesse (5) | K86: Static profile activates 7 keyword family/families: KI / Digital, Innovation / Transfer, Nachhaltigkeit / Klima / Energie, Bau / Raum / Infrastruktur, Wirtschaft / Mittelstand / Standort, Wissenschaft / Bildung / Hochschule, Kultur / Medien / Öffentlichkeit. | L86: Use as convening/context partner for digitalization / data / technology opportunity anchor. | M86: https://www.zirp.de/die-zirp/mitglieder/ | N86: Keyword search over existing static ZIRP member fields in this workbook, designed to mirror/search official ZIRP profile info boxes.
A87: 86 | B87: SWR – Südwestrundfunk | C87: https://www.swr.de | D87: context_actor | E87: media_publicity_anchor | F87: SWR – Südwestrundfunk | context_actor | gesellschaft, kultur, wissen | Demokratie, Medien und gesellschaftlicher Zusammenhalt (5); Kreativwirtschaft, Medien und digitale Öffentlichkeit (5); Kultur, Standortidentität und regionale Attraktivität (5); Wissenschaft, Demokratie und gesellschaftlicher Zusammenhalt (5); Talentförderung, Musik und Nachwuchs (4) | G87: KI / Digital; Innovation / Transfer; Wirtschaft / Mittelstand / Standort; Wissenschaft / Bildung / Hochschule; Dialog / Netzwerk / Verantwortung; Kultur / Medien / Öffentlichkeit | H87: digital; IT; Wissen; Wirtschaft; Standort; Förderung; Wissenschaft; gesellschaftlich; Zusammenhalt; Kultur; Medien; Öffentlichkeit; Kreativwirtschaft; Musik; Standortidentität; Region; Demokratie | I87: 17 | J87: Demokratie, Medien und gesellschaftlicher Zusammenhalt (5) | K87: Static profile activates 6 keyword family/families: KI / Digital, Innovation / Transfer, Wirtschaft / Mittelstand / Standort, Wissenschaft / Bildung / Hochschule, Dialog / Netzwerk / Verantwortung, Kultur / Medien / Öffentlichkeit. | L87: Use as convening/context partner for digitalization / data / technology opportunity anchor. | M87: https://www.zirp.de/die-zirp/mitglieder/ | N87: Keyword search over existing static ZIRP member fields in this workbook, designed to mirror/search official ZIRP profile info boxes.
A88: 87 | B88: Techniker Krankenkasse | C88: https://www.tk.de/rp | D88: context_actor | E88: health_social_anchor | F88: Techniker Krankenkasse | context_actor | gesellschaft | Gesundheitsversorgung und Prävention (5); Pflege, Fachkräfte und Sozialwirtschaft (4); Sport, Region und gesellschaftliche Identifikation (4) | G88: KI / Digital; Gesundheit / Pflege / Sozialwirtschaft; Fachkräfte / Arbeit / Qualifizierung; Wirtschaft / Mittelstand / Standort; Dialog / Netzwerk / Verantwortung; Kultur / Medien / Öffentlichkeit | H88: IT; Gesundheit; Gesundheitsversorgung; Pflege; Sozialwirtschaft; Prävention; Versorgung; Fachkräfte; Wirtschaft; gesellschaftlich; Region; gesellschaftliche Identifikation | I88: 12 | J88: Gesundheitsversorgung und Prävention (5) | K88: Static profile activates 6 keyword family/families: KI / Digital, Gesundheit / Pflege / Sozialwirtschaft, Fachkräfte / Arbeit / Qualifizierung, Wirtschaft / Mittelstand / Standort, Dialog / Netzwerk / Verantwortung, Kultur / Medien / Öffentlichkeit. | L88: Use as convening/context partner for health/social-sector opportunity anchor. | M88: https://www.zirp.de/die-zirp/mitglieder/ | N88: Keyword search over existing static ZIRP member fields in this workbook, designed to mirror/search official ZIRP profile info boxes.
A89: 88 | B89: Technische Hochschule Bingen | C89: https://www.th-bingen.de | D89: academic_support | E89: university_applied_sciences | F89: Technische Hochschule Bingen | academic_support | nachhaltigkeit, technologie, wirtschaft, wissen | Arbeitsmarkt, Fachkräfte und Qualifizierung (4); Digitale Bau-, Planungs- und Genehmigungsprozesse (4); Hochschule-Wirtschaft-Transfer (4); Industrie 4.0, Automatisierung und Produktion (4); Klimaanpassung in Stadt und Land (4) | G89: KI / Digital; Innovation / Transfer; Nachhaltigkeit / Klima / Energie; Fachkräfte / Arbeit / Qualifizierung; Bau / Raum / Infrastruktur; Wirtschaft / Mittelstand / Standort; Wissenschaft / Bildung / Hochschule | H89: digital; IT; Technologie; Automatisierung; Industrie 4.0; Transfer; Wissen; Nachhaltigkeit; nachhaltig; Klima; Klimaanpassung; Land; Stadt; Fachkräfte; Qualifizierung; Arbeitsmarkt; Bau; Planung; Genehmigung; Wirtschaft; Industrie; Hochschule | I89: 22 | J89: Arbeitsmarkt, Fachkräfte und Qualifizierung (4) | K89: Static profile activates 7 keyword family/families: KI / Digital, Innovation / Transfer, Nachhaltigkeit / Klima / Energie, Fachkräfte / Arbeit / Qualifizierung, Bau / Raum / Infrastruktur, Wirtschaft / Mittelstand / Standort, Wissenschaft / Bildung / Hochschule. | L89: Use as evidence, research or transfer partner for digitalization / data / technology opportunity anchor. | M89: https://www.zirp.de/die-zirp/mitglieder/ | N89: Keyword search over existing static ZIRP member fields in this workbook, designed to mirror/search official ZIRP profile info boxes.
A90: 89 | B90: thyssenkrupp Rasselstein GmbH | C90: https://www.thyssenkrupp-steel.com/de/unternehmen/business-units/packaging-steel/ | D90: profit_anchor | E90: industry_anchor | F90: thyssenkrupp Rasselstein GmbH | profit_anchor | nachhaltigkeit, technologie, wirtschaft | Standort, Investition und industrielle Transformation (5); Energie, Netze und Versorgungssicherheit (4); Industrie 4.0, Automatisierung und Produktion (4) | G90: KI / Digital; Nachhaltigkeit / Klima / Energie; Gesundheit / Pflege / Sozialwirtschaft; Wirtschaft / Mittelstand / Standort | H90: IT; Technologie; Automatisierung; Industrie 4.0; Nachhaltigkeit; nachhaltig; Energie; Netze; Versorgungssicherheit; Versorgung; Wirtschaft; Standort; Industrie; Investition; Transformation | I90: 15 | J90: Standort, Investition und industrielle Transformation (5) | K90: Static profile activates 4 keyword family/families: KI / Digital, Nachhaltigkeit / Klima / Energie, Gesundheit / Pflege / Sozialwirtschaft, Wirtschaft / Mittelstand / Standort. | L90: Use as implementation/commercial partner for health/social-sector opportunity anchor. | M90: https://www.zirp.de/die-zirp/mitglieder/ | N90: Keyword search over existing static ZIRP member fields in this workbook, designed to mirror/search official ZIRP profile info boxes.
A91: 90 | B91: Transdev GmbH | C91: https://www.transdev.de | D91: profit_anchor | E91: energy_infrastructure_anchor | F91: Transdev GmbH | profit_anchor | nachhaltigkeit | Klimaanpassung in Stadt und Land (3) | G91: KI / Digital; Nachhaltigkeit / Klima / Energie; Bau / Raum / Infrastruktur | H91: IT; Nachhaltigkeit; nachhaltig; Klima; Klimaanpassung; Land; Stadt | I91: 7 | J91: Klimaanpassung in Stadt und Land (3) | K91: Static profile activates 3 keyword family/families: KI / Digital, Nachhaltigkeit / Klima / Energie, Bau / Raum / Infrastruktur. | L91: Use as implementation/commercial partner for digitalization / data / technology opportunity anchor. | M91: https://www.zirp.de/die-zirp/mitglieder/ | N91: Keyword search over existing static ZIRP member fields in this workbook, designed to mirror/search official ZIRP profile info boxes.
A92: 91 | B92: TÜV Rheinland Berlin Brandenburg Pfalz e.V. | C92: https://www.tuv.com/germany/de/ | D92: context_actor | E92: chamber_association_anchor | F92: TÜV Rheinland Berlin Brandenburg Pfalz e.V. | context_actor | nachhaltigkeit, technologie | Cyberresilienz und kritische Infrastruktur (5); Digitale Bau-, Planungs- und Genehmigungsprozesse (4); Industrie 4.0, Automatisierung und Produktion (4); KI, Daten und Verwaltungs-/Wirtschaftsanwendungen (4); Kreislaufwirtschaft, Bau und Ersatzbaustoffverordnung (4) | G92: KI / Digital; Nachhaltigkeit / Klima / Energie; Bau / Raum / Infrastruktur; Wirtschaft / Mittelstand / Standort | H92: KI; digital; Daten; IT; Technologie; Cyber; Automatisierung; Industrie 4.0; Verwaltung; Nachhaltigkeit; nachhaltig; Kreislauf; Ersatzbaustoff; Land; Bau; Infrastruktur; Planung; Genehmigung; Wirtschaft; Industrie | I92: 20 | J92: Cyberresilienz und kritische Infrastruktur (5) | K92: Static profile activates 4 keyword family/families: KI / Digital, Nachhaltigkeit / Klima / Energie, Bau / Raum / Infrastruktur, Wirtschaft / Mittelstand / Standort. | L92: Use as convening/context partner for digitalization / data / technology opportunity anchor. | M92: https://www.zirp.de/die-zirp/mitglieder/ | N92: Keyword search over existing static ZIRP member fields in this workbook, designed to mirror/search official ZIRP profile info boxes.
A93: 92 | B93: Universität Koblenz | C93: http://www.uni-koblenz.de | D93: academic_support | E93: university_research | F93: Universität Koblenz | academic_support | gesellschaft, technologie, wissen | Demokratie, Medien und gesellschaftlicher Zusammenhalt (4); Hochschule-Wirtschaft-Transfer (4); KI, Daten und Verwaltungs-/Wirtschaftsanwendungen (4); Verwaltungswissen und digitale Umsetzung (4); Wissenschaft, Demokratie und gesellschaftlicher Zusammenhalt (4) | G93: KI / Digital; Innovation / Transfer; Wirtschaft / Mittelstand / Standort; Wissenschaft / Bildung / Hochschule; Dialog / Netzwerk / Verantwortung; Kultur / Medien / Öffentlichkeit | H93: KI; digital; Daten; IT; Technologie; Verwaltung; Transfer; Wissen; Wirtschaft; Wissenschaft; Hochschule; Universität; gesellschaftlich; Zusammenhalt; Medien; Demokratie | I93: 16 | J93: Demokratie, Medien und gesellschaftlicher Zusammenhalt (4) | K93: Static profile activates 6 keyword family/families: KI / Digital, Innovation / Transfer, Wirtschaft / Mittelstand / Standort, Wissenschaft / Bildung / Hochschule, Dialog / Netzwerk / Verantwortung, Kultur / Medien / Öffentlichkeit. | L93: Use as evidence, research or transfer partner for digitalization / data / technology opportunity anchor. | M93: https://www.zirp.de/die-zirp/mitglieder/ | N93: Keyword search over existing static ZIRP member fields in this workbook, designed to mirror/search official ZIRP profile info boxes.
A94: 93 | B94: Universität Trier | C94: https://www.uni-trier.de | D94: academic_support | E94: university_research | F94: Universität Trier | academic_support | gesellschaft, technologie, wissen | Wissenschaft, Demokratie und gesellschaftlicher Zusammenhalt (5); Cyberresilienz und kritische Infrastruktur (4); Demokratie, Medien und gesellschaftlicher Zusammenhalt (4); Hochschule-Wirtschaft-Transfer (4); KI, Daten und Verwaltungs-/Wirtschaftsanwendungen (4) | G94: KI / Digital; Innovation / Transfer; Bau / Raum / Infrastruktur; Wirtschaft / Mittelstand / Standort; Wissenschaft / Bildung / Hochschule; Dialog / Netzwerk / Verantwortung; Kultur / Medien / Öffentlichkeit | H94: KI; Daten; IT; Technologie; Cyber; Verwaltung; Transfer; Wissen; Infrastruktur; Wirtschaft; Wissenschaft; Hochschule; Universität; gesellschaftlich; Zusammenhalt; Medien; Demokratie | I94: 17 | J94: Wissenschaft, Demokratie und gesellschaftlicher Zusammenhalt (5) | K94: Static profile activates 7 keyword family/families: KI / Digital, Innovation / Transfer, Bau / Raum / Infrastruktur, Wirtschaft / Mittelstand / Standort, Wissenschaft / Bildung / Hochschule, Dialog / Netzwerk / Verantwortung, Kultur / Medien / Öffentlichkeit. | L94: Use as evidence, research or transfer partner for digitalization / data / technology opportunity anchor. | M94: https://www.zirp.de/die-zirp/mitglieder/ | N94: Keyword search over existing static ZIRP member fields in this workbook, designed to mirror/search official ZIRP profile info boxes.
A95: 94 | B95: Vereinigte VR Bank Kur- und Rheinpfalz eG | C95: https://www.vvrbank-krp.de | D95: profit_anchor | E95: bank_finance_anchor | F95: Vereinigte VR Bank Kur- und Rheinpfalz eG | profit_anchor | wirtschaft | Finanzierung und Förderung von Transformation (4); Standort, Investition und industrielle Transformation (3) | G95: KI / Digital; Wirtschaft / Mittelstand / Standort | H95: IT; Wirtschaft; Standort; Industrie; Investition; Transformation; Förderung; Finanzierung | I95: 8 | J95: Finanzierung und Förderung von Transformation (4) | K95: Static profile activates 2 keyword family/families: KI / Digital, Wirtschaft / Mittelstand / Standort. | L95: Use as implementation/commercial partner for digitalization / data / technology opportunity anchor. | M95: https://www.zirp.de/die-zirp/mitglieder/ | N95: Keyword search over existing static ZIRP member fields in this workbook, designed to mirror/search official ZIRP profile info boxes.
A96: 95 | B96: vero – Verband der Bau- und Rohstoffindustrie | C96: http://www.vero-baustoffe.de | D96: profit_anchor | E96: construction_planning_anchor | F96: vero – Verband der Bau- und Rohstoffindustrie | profit_anchor | nachhaltigkeit, technologie | Digitale Bau-, Planungs- und Genehmigungsprozesse (5); Kreislaufwirtschaft, Bau und Ersatzbaustoffverordnung (5) | G96: KI / Digital; Nachhaltigkeit / Klima / Energie; Bau / Raum / Infrastruktur; Wirtschaft / Mittelstand / Standort | H96: digital; IT; Technologie; Nachhaltigkeit; nachhaltig; Kreislauf; Ersatzbaustoff; Bau; Planung; Genehmigung; Wirtschaft; Industrie | I96: 12 | J96: Digitale Bau-, Planungs- und Genehmigungsprozesse (5) | K96: Static profile activates 4 keyword family/families: KI / Digital, Nachhaltigkeit / Klima / Energie, Bau / Raum / Infrastruktur, Wirtschaft / Mittelstand / Standort. | L96: Use as implementation/commercial partner for digitalization / data / technology opportunity anchor. | M96: https://www.zirp.de/die-zirp/mitglieder/ | N96: Keyword search over existing static ZIRP member fields in this workbook, designed to mirror/search official ZIRP profile info boxes.
A97: 96 | B97: Villa Musica Rheinland-Pfalz | C97: https://www.villamusica.de | D97: context_actor | E97: culture_foundation_anchor | F97: Villa Musica Rheinland-Pfalz | context_actor | gesellschaft, kultur, wissen | Kultur, Standortidentität und regionale Attraktivität (5); Talentförderung, Musik und Nachwuchs (5); Kreativwirtschaft, Medien und digitale Öffentlichkeit (4); Demokratie, Medien und gesellschaftlicher Zusammenhalt (3); Wissenschaft, Demokratie und gesellschaftlicher Zusammenhalt (3) | G97: KI / Digital; Innovation / Transfer; Nachhaltigkeit / Klima / Energie; Wirtschaft / Mittelstand / Standort; Wissenschaft / Bildung / Hochschule; Dialog / Netzwerk / Verantwortung; Kultur / Medien / Öffentlichkeit | H97: digital; IT; Wissen; Land; Wirtschaft; Standort; Förderung; Wissenschaft; gesellschaftlich; Zusammenhalt; Kultur; Medien; Öffentlichkeit; Kreativwirtschaft; Musik; Standortidentität; Region; Demokratie | I97: 18 | J97: Kultur, Standortidentität und regionale Attraktivität (5) | K97: Static profile activates 7 keyword family/families: KI / Digital, Innovation / Transfer, Nachhaltigkeit / Klima / Energie, Wirtschaft / Mittelstand / Standort, Wissenschaft / Bildung / Hochschule, Dialog / Netzwerk / Verantwortung, Kultur / Medien / Öffentlichkeit. | L97: Use as convening/context partner for digitalization / data / technology opportunity anchor. | M97: https://www.zirp.de/die-zirp/mitglieder/ | N97: Keyword search over existing static ZIRP member fields in this workbook, designed to mirror/search official ZIRP profile info boxes.
... A104: 103 | B104: Alexianer GmbH | C104: https://www.alexianer.de/ | D104: context_actor | E104: health_social_anchor | F104: Alexianer GmbH | context_actor | gesellschaft, wirtschaft, wissen | Gesundheitsversorgung und Prävention (5); Pflege, Fachkräfte und Sozialwirtschaft (5); Teilhabe, Inklusion und Arbeitsmarkt (4); Dialog, Vernetzung und gesellschaftliche Verantwortung (4) | Die Alexianer Gruppe ist eines der größten konfessionellen Gesundheits- und Sozialwirtschafts-Unternehmen mit Krankenhäusern, medizinischen Versorgungszentren sowie Senioren-, Eingliederungs- und Jugendhilfe. ZIRP als Plattform für Dialog und Vernetzung über Themen der Gesundheits- und Sozialwirtschaft. | G104: KI / Digital; Innovation / Transfer; Gesundheit / Pflege / Sozialwirtschaft; Fachkräfte / Arbeit / Qualifizierung; Wirtschaft / Mittelstand / Standort; Wissenschaft / Bildung / Hochschule; Dialog / Netzwerk / Verantwortung | H104: IT; Plattform; Wissen; Gesundheit; Gesundheitsversorgung; Medizin; Pflege; Sozialwirtschaft; Krankenhäuser; Prävention; Versorgung; Teilhabe; Senioren; Fachkräfte; Arbeitsmarkt; Wirtschaft; Unternehmen; Dialog; Vernetzung; Verantwortung; gesellschaftlich | I104: 21 | J104: Gesundheitsversorgung und Prävention (5) | K104: Static profile activates 7 keyword family/families: KI / Digital, Innovation / Transfer, Gesundheit / Pflege / Sozialwirtschaft, Fachkräfte / Arbeit / Qualifizierung, Wirtschaft / Mittelstand / Standort, Wissenschaft / Bildung / Hochschule, Dialog / Netzwerk / Verantwortung. | L104: Use as convening/context partner for health/social-sector opportunity anchor. | M104: https://www.zirp.de/die-zirp/mitglieder/ | N104: Keyword search over official/static member profile layer; Alexianer added from live ZIRP member profile.

Sheet Keyword_Summary
A1: keyword_family | B1: member_count | C1: example_members | D1: all_members
A2: KI / Digital | B2: 102 | C2: 1. FSV Mainz 05 e.V.; AOK Rheinland-Pfalz/Saarland; Architektenkammer Rheinland-Pfalz; Aturas GmbH; Barmherzige Brüder Trier gGmbH; BASF SE; Bauern- und Winzerverband Rheinland-Pfalz Süd e.V.; Bauwirtschaft Rheinland-Pfalz e.V. | D2: 1. FSV Mainz 05 e.V.; AOK Rheinland-Pfalz/Saarland; Architektenkammer Rheinland-Pfalz; Aturas GmbH; Barmherzige Brüder Trier gGmbH; BASF SE; Bauern- und Winzerverband Rheinland-Pfalz Süd e.V.; Bauwirtschaft Rheinland-Pfalz e.V.; Bernd Hummel Holding GmbH; Bitburger Braugruppe GmbH; Boehringer Ingelheim Pharma GmbH & Co. KG; BRICKMAKERS AG; Bundesagentur für Arbeit, Regionaldirektion Rheinland-Pfalz-Saarland; Caritasverband für die Diözese Speyer e.V.; Continental Automotive Technologies GmbH, Safety and Motion (SAM), Standort Rheinböllen; Debeka Versicherungsgruppe; Deutsche Bundesbank, Hauptverwaltung in Rheinland-Pfalz und dem Saarland; Deutsche Telekom AG; Deutsche Universität für Verwaltungswissenschaften Speyer; Deutscher Gewerkschaftsbund (DGB) Rheinland-Pfalz/Saarland; Duale Hochschule Rheinland-Pfalz; Eckes-Granini Deutschland GmbH; Empolis Information Management GmbH; ENTEGA Plus GmbH; Entwicklungsagentur Rheinland-Pfalz e.V.; Ernst & Young GmbH; Erster FC Kaiserslautern GmbH & Co. KGaA; Evangelische Kirche der Pfalz; Fachingen Heil- und Mineralbrunnen GmbH; Gerolsteiner Brunnen GmbH & Co. KG; GLOBUS Markthallen Holding GmbH & Co. KG; Handwerkskammern Rheinland-Pfalz; Heberger Gruppe; Hochschule für Gesellschaftsgestaltung (HfGG); Hochschule für Musik Mainz; Hochschule für Wirtschaft und Gesellschaft Ludwigshafen; Hochschule Kaiserslautern; Hochschule Koblenz; Hochschule Mainz; Hochschule Trier; Hochschule Worms; IKK Südwest; in.betrieb gGmbH; Ingenieurkammer Rheinland-Pfalz; Investitions- und Strukturbank Rheinland-Pfalz (ISB); IQIB - Institut für qualifizierende Innovationsforschung und -beratung GmbH; ITK Engineering GmbH; JOBS FOR MOMS UG; Johannes Gutenberg-Universität Mainz; Joseph Vögele AG; JUWI GmbH; Karl Gemünden GmbH & Co. KG; Kassenzahnärztliche Vereinigung Rheinland-Pfalz; Kassenärztliche Vereinigung Rheinland-Pfalz; Katholische Hochschule Mainz; KPMG AG Wirtschaftsprüfungsgesellschaft; KSB AG; KÜBLER GmbH; L Q M Marktforschung GmbH; Landesbank Baden-Württemberg (LBBW); LandesPsychotherapeutenKammer Rheinland-Pfalz; Landesärztekammer Rheinland-Pfalz; Landkreistag Rheinland-Pfalz; Leonardo PersonalKonzept GmbH; Licharz GmbH; LOTTO Rheinland-Pfalz GmbH; LÖWEN ENTERTAINMENT GmbH; Mainzer Stadtwerke AG; Michelin Reifenwerke AG & Co. KGaA; Ministerium für Wirtschaft, Verkehr, Landwirtschaft und Weinbau; PFAFF Industriesysteme und Maschinen GmbH; Pfalzwerke AG; Provinzial Versicherung AG; Rheinland-Pfälzische Technische Universität Kaiserslautern-Landau (RPTU); robotspaceship; RPR1.; Schoenergie GmbH; SCHOTT AG; Schuler Service GmbH & Co. KG; SIMONA AG; SmartFactory KL e.V.; Sparkassenverband Rheinland-Pfalz; Staatskanzlei des Landes Rheinland-Pfalz; Städtetag Rheinland-Pfalz; SWR – Südwestrundfunk; Techniker Krankenkasse; Technische Hochschule Bingen; thyssenkrupp Rasselstein GmbH; Transdev GmbH; TÜV Rheinland Berlin Brandenburg Pfalz e.V.; Universität Koblenz; Universität Trier; Vereinigte VR Bank Kur- und Rheinpfalz eG; vero – Verband der Bau- und Rohstoffindustrie; Villa Musica Rheinland-Pfalz; Vinzenz Pallotti University gGmbH; Westenergie AG; WHU – Otto Beisheim School of Management; Wilhelm Faber GmbH; Zahnen Technik GmbH; ZDF – Zweites Deutsches Fernsehen; Alexianer GmbH
A3: Innovation / Transfer | B3: 48 | C3: Aturas GmbH; Barmherzige Brüder Trier gGmbH; BASF SE; Boehringer Ingelheim Pharma GmbH & Co. KG; BRICKMAKERS AG; Bundesagentur für Arbeit, Regionaldirektion Rheinland-Pfalz-Saarland; Deutsche Universität für Verwaltungswissenschaften Speyer; Deutscher Gewerkschaftsbund (DGB) Rheinland-Pfalz/Saarland | D3: Aturas GmbH; Barmherzige Brüder Trier gGmbH; BASF SE; Boehringer Ingelheim Pharma GmbH & Co. KG; BRICKMAKERS AG; Bundesagentur für Arbeit, Regionaldirektion Rheinland-Pfalz-Saarland; Deutsche Universität für Verwaltungswissenschaften Speyer; Deutscher Gewerkschaftsbund (DGB) Rheinland-Pfalz/Saarland; Duale Hochschule Rheinland-Pfalz; Empolis Information Management GmbH; Entwicklungsagentur Rheinland-Pfalz e.V.; Evangelische Kirche der Pfalz; GLOBUS Markthallen Holding GmbH & Co. KG; Handwerkskammern Rheinland-Pfalz; Hochschule für Gesellschaftsgestaltung (HfGG); Hochschule für Musik Mainz; Hochschule für Wirtschaft und Gesellschaft Ludwigshafen; Hochschule Kaiserslautern; Hochschule Koblenz; Hochschule Mainz; Hochschule Trier; Hochschule Worms; Investitions- und Strukturbank Rheinland-Pfalz (ISB); IQIB - Institut für qualifizierende Innovationsforschung und -beratung GmbH; ITK Engineering GmbH; JOBS FOR MOMS UG; Johannes Gutenberg-Universität Mainz; Katholische Hochschule Mainz; L Q M Marktforschung GmbH; Landkreistag Rheinland-Pfalz; Leonardo PersonalKonzept GmbH; Ministerium für Wirtschaft, Verkehr, Landwirtschaft und Weinbau; Rheinland-Pfälzische Technische Universität Kaiserslautern-Landau (RPTU); RPR1.; SCHOTT AG; SmartFactory KL e.V.; Sparkassenverband Rheinland-Pfalz; Staatskanzlei des Landes Rheinland-Pfalz; Städtetag Rheinland-Pfalz; SWR – Südwestrundfunk; Technische Hochschule Bingen; Universität Koblenz; Universität Trier; Villa Musica Rheinland-Pfalz; Vinzenz Pallotti University gGmbH; WHU – Otto Beisheim School of Management; ZDF – Zweites Deutsches Fernsehen; Alexianer GmbH
A4: Nachhaltigkeit / Klima / Energie | B4: 50 | C4: AOK Rheinland-Pfalz/Saarland; Architektenkammer Rheinland-Pfalz; BASF SE; Bauern- und Winzerverband Rheinland-Pfalz Süd e.V.; Bauwirtschaft Rheinland-Pfalz e.V.; Bundesagentur für Arbeit, Regionaldirektion Rheinland-Pfalz-Saarland; Deutsche Bundesbank, Hauptverwaltung in Rheinland-Pfalz und dem Saarland; Deutscher Gewerkschaftsbund (DGB) Rheinland-Pfalz/Saarland | D4: AOK Rheinland-Pfalz/Saarland; Architektenkammer Rheinland-Pfalz; BASF SE; Bauern- und Winzerverband Rheinland-Pfalz Süd e.V.; Bauwirtschaft Rheinland-Pfalz e.V.; Bundesagentur für Arbeit, Regionaldirektion Rheinland-Pfalz-Saarland; Deutsche Bundesbank, Hauptverwaltung in Rheinland-Pfalz und dem Saarland; Deutscher Gewerkschaftsbund (DGB) Rheinland-Pfalz/Saarland; Duale Hochschule Rheinland-Pfalz; Eckes-Granini Deutschland GmbH; ENTEGA Plus GmbH; Entwicklungsagentur Rheinland-Pfalz e.V.; Handwerkskammern Rheinland-Pfalz; Heberger Gruppe; Hochschule für Gesellschaftsgestaltung (HfGG); Hochschule Trier; Ingenieurkammer Rheinland-Pfalz; Investitions- und Strukturbank Rheinland-Pfalz (ISB); JUWI GmbH; Karl Gemünden GmbH & Co. KG; Kassenzahnärztliche Vereinigung Rheinland-Pfalz; Kassenärztliche Vereinigung Rheinland-Pfalz; KSB AG; KÜBLER GmbH; Landesbank Baden-Württemberg (LBBW); LandesPsychotherapeutenKammer Rheinland-Pfalz; Landesärztekammer Rheinland-Pfalz; Landkreistag Rheinland-Pfalz; LOTTO Rheinland-Pfalz GmbH; Mainzer Stadtwerke AG; Michelin Reifenwerke AG & Co. KGaA; Ministerium für Wirtschaft, Verkehr, Landwirtschaft und Weinbau; Pfalzwerke AG; Rheinland-Pfälzische Technische Universität Kaiserslautern-Landau (RPTU); Schoenergie GmbH; SCHOTT AG; SIMONA AG; Sparkassenverband Rheinland-Pfalz; Staatskanzlei des Landes Rheinland-Pfalz; Steuerberaterkammer Rheinland-Pfalz; Städtetag Rheinland-Pfalz; Technische Hochschule Bingen; thyssenkrupp Rasselstein GmbH; Transdev GmbH; TÜV Rheinland Berlin Brandenburg Pfalz e.V.; vero – Verband der Bau- und Rohstoffindustrie; Villa Musica Rheinland-Pfalz; Westenergie AG; Wilhelm Faber GmbH; Zahnen Technik GmbH
A5: Gesundheit / Pflege / Sozialwirtschaft | B5: 37 | C5: AOK Rheinland-Pfalz/Saarland; Barmherzige Brüder Trier gGmbH; BASF SE; Boehringer Ingelheim Pharma GmbH & Co. KG; Bundesagentur für Arbeit, Regionaldirektion Rheinland-Pfalz-Saarland; Caritasverband für die Diözese Speyer e.V.; Deutscher Gewerkschaftsbund (DGB) Rheinland-Pfalz/Saarland; Duale Hochschule Rheinland-Pfalz | D5: AOK Rheinland-Pfalz/Saarland; Barmherzige Brüder Trier gGmbH; BASF SE; Boehringer Ingelheim Pharma GmbH & Co. KG; Bundesagentur für Arbeit, Regionaldirektion Rheinland-Pfalz-Saarland; Caritasverband für die Diözese Speyer e.V.; Deutscher Gewerkschaftsbund (DGB) Rheinland-Pfalz/Saarland; Duale Hochschule Rheinland-Pfalz; ENTEGA Plus GmbH; Evangelische Kirche der Pfalz; GLOBUS Markthallen Holding GmbH & Co. KG; Hochschule für Gesellschaftsgestaltung (HfGG); Hochschule für Wirtschaft und Gesellschaft Ludwigshafen; IKK Südwest; in.betrieb gGmbH; Investitions- und Strukturbank Rheinland-Pfalz (ISB); JOBS FOR MOMS UG; JUWI GmbH; Kassenzahnärztliche Vereinigung Rheinland-Pfalz; Kassenärztliche Vereinigung Rheinland-Pfalz; Katholische Hochschule Mainz; KÜBLER GmbH; Landesbank Baden-Württemberg (LBBW); LandesPsychotherapeutenKammer Rheinland-Pfalz; Landesärztekammer Rheinland-Pfalz; Leonardo PersonalKonzept GmbH; Mainzer Stadtwerke AG; Michelin Reifenwerke AG & Co. KGaA; Pfalzwerke AG; Schoenergie GmbH; SCHOTT AG; SIMONA AG; Techniker Krankenkasse; thyssenkrupp Rasselstein GmbH; Vinzenz Pallotti University gGmbH; Westenergie AG; Alexianer GmbH
A6: Fachkräfte / Arbeit / Qualifizierung | B6: 47 | C6: AOK Rheinland-Pfalz/Saarland; Aturas GmbH; Barmherzige Brüder Trier gGmbH; BASF SE; Boehringer Ingelheim Pharma GmbH & Co. KG; BRICKMAKERS AG; Bundesagentur für Arbeit, Regionaldirektion Rheinland-Pfalz-Saarland; Caritasverband für die Diözese Speyer e.V. | D6: AOK Rheinland-Pfalz/Saarland; Aturas GmbH; Barmherzige Brüder Trier gGmbH; BASF SE; Boehringer Ingelheim Pharma GmbH & Co. KG; BRICKMAKERS AG; Bundesagentur für Arbeit, Regionaldirektion Rheinland-Pfalz-Saarland; Caritasverband für die Diözese Speyer e.V.; Deutsche Telekom AG; Deutscher Gewerkschaftsbund (DGB) Rheinland-Pfalz/Saarland; Duale Hochschule Rheinland-Pfalz; Empolis Information Management GmbH; Evangelische Kirche der Pfalz; GLOBUS Markthallen Holding GmbH & Co. KG; Handwerkskammern Rheinland-Pfalz; Hochschule für Gesellschaftsgestaltung (HfGG); Hochschule für Musik Mainz; Hochschule für Wirtschaft und Gesellschaft Ludwigshafen; Hochschule Kaiserslautern; Hochschule Koblenz; Hochschule Mainz; Hochschule Trier; Hochschule Worms; IKK Südwest; in.betrieb gGmbH; IQIB - Institut für qualifizierende Innovationsforschung und -beratung GmbH; ITK Engineering GmbH; JOBS FOR MOMS UG; Joseph Vögele AG; Kassenärztliche Vereinigung Rheinland-Pfalz; Katholische Hochschule Mainz; KÜBLER GmbH; LandesPsychotherapeutenKammer Rheinland-Pfalz; Landesärztekammer Rheinland-Pfalz; Leonardo PersonalKonzept GmbH; Licharz GmbH; Ministerium für Wirtschaft, Verkehr, Landwirtschaft und Weinbau; PFAFF Industriesysteme und Maschinen GmbH; Rheinland-Pfälzische Technische Universität Kaiserslautern-Landau (RPTU); robotspaceship; SmartFactory KL e.V.; Sparkassenverband Rheinland-Pfalz; Techniker Krankenkasse; Technische Hochschule Bingen; Vinzenz Pallotti University gGmbH; WHU – Otto Beisheim School of Management; Alexianer GmbH
A7: Bau / Raum / Infrastruktur | B7: 38 | C7: Architektenkammer Rheinland-Pfalz; Aturas GmbH; Bauern- und Winzerverband Rheinland-Pfalz Süd e.V.; Bauwirtschaft Rheinland-Pfalz e.V.; BRICKMAKERS AG; Debeka Versicherungsgruppe; Deutsche Bundesbank, Hauptverwaltung in Rheinland-Pfalz und dem Saarland; Deutsche Telekom AG | D7: Architektenkammer Rheinland-Pfalz; Aturas GmbH; Bauern- und Winzerverband Rheinland-Pfalz Süd e.V.; Bauwirtschaft Rheinland-Pfalz e.V.; BRICKMAKERS AG; Debeka Versicherungsgruppe; Deutsche Bundesbank, Hauptverwaltung in Rheinland-Pfalz und dem Saarland; Deutsche Telekom AG; Deutsche Universität für Verwaltungswissenschaften Speyer; Empolis Information Management GmbH; ENTEGA Plus GmbH; Entwicklungsagentur Rheinland-Pfalz e.V.; Heberger Gruppe; Hochschule für Gesellschaftsgestaltung (HfGG); Hochschule Mainz; Ingenieurkammer Rheinland-Pfalz; Investitions- und Strukturbank Rheinland-Pfalz (ISB); JUWI GmbH; Karl Gemünden GmbH & Co. KG; KSB AG; Landesbank Baden-Württemberg (LBBW); Landkreistag Rheinland-Pfalz; Mainzer Stadtwerke AG; Ministerium für Wirtschaft, Verkehr, Landwirtschaft und Weinbau; Pfalzwerke AG; Provinzial Versicherung AG; Rheinland-Pfälzische Technische Universität Kaiserslautern-Landau (RPTU); Sparkassenverband Rheinland-Pfalz; Staatskanzlei des Landes Rheinland-Pfalz; Städtetag Rheinland-Pfalz; Technische Hochschule Bingen; Transdev GmbH; TÜV Rheinland Berlin Brandenburg Pfalz e.V.; Universität Trier; vero – Verband der Bau- und Rohstoffindustrie; Westenergie AG; Wilhelm Faber GmbH; Zahnen Technik GmbH
A8: Wirtschaft / Mittelstand / Standort | B8: 87 | C8: 1. FSV Mainz 05 e.V.; AOK Rheinland-Pfalz/Saarland; Architektenkammer Rheinland-Pfalz; Aturas GmbH; Barmherzige Brüder Trier gGmbH; BASF SE; Bauwirtschaft Rheinland-Pfalz e.V.; Bitburger Braugruppe GmbH | D8: 1. FSV Mainz 05 e.V.; AOK Rheinland-Pfalz/Saarland; Architektenkammer Rheinland-Pfalz; Aturas GmbH; Barmherzige Brüder Trier gGmbH; BASF SE; Bauwirtschaft Rheinland-Pfalz e.V.; Bitburger Braugruppe GmbH; Boehringer Ingelheim Pharma GmbH & Co. KG; BRICKMAKERS AG; Bundesagentur für Arbeit, Regionaldirektion Rheinland-Pfalz-Saarland; Caritasverband für die Diözese Speyer e.V.; Continental Automotive Technologies GmbH, Safety and Motion (SAM), Standort Rheinböllen; Debeka Versicherungsgruppe; Deutsche Telekom AG; Deutsche Universität für Verwaltungswissenschaften Speyer; Deutscher Gewerkschaftsbund (DGB) Rheinland-Pfalz/Saarland; Duale Hochschule Rheinland-Pfalz; Eckes-Granini Deutschland GmbH; Empolis Information Management GmbH; Entwicklungsagentur Rheinland-Pfalz e.V.; Ernst & Young GmbH; Erster FC Kaiserslautern GmbH & Co. KGaA; Evangelische Kirche der Pfalz; GLOBUS Markthallen Holding GmbH & Co. KG; Handwerkskammern Rheinland-Pfalz; Heberger Gruppe; Hochschule für Gesellschaftsgestaltung (HfGG); Hochschule für Musik Mainz; Hochschule für Wirtschaft und Gesellschaft Ludwigshafen; Hochschule Kaiserslautern; Hochschule Koblenz; Hochschule Mainz; Hochschule Trier; Hochschule Worms; IKK Südwest; in.betrieb gGmbH; Ingenieurkammer Rheinland-Pfalz; Investitions- und Strukturbank Rheinland-Pfalz (ISB); IQIB - Institut für qualifizierende Innovationsforschung und -beratung GmbH; ITK Engineering GmbH; JOBS FOR MOMS UG; Johannes Gutenberg-Universität Mainz; Joseph Vögele AG; JUWI GmbH; Karl Gemünden GmbH & Co. KG; Kassenärztliche Vereinigung Rheinland-Pfalz; Katholische Hochschule Mainz; KPMG AG Wirtschaftsprüfungsgesellschaft; KSB AG; KÜBLER GmbH; Landesbank Baden-Württemberg (LBBW); LandesPsychotherapeutenKammer Rheinland-Pfalz; Landesärztekammer Rheinland-Pfalz; Landkreistag Rheinland-Pfalz; Leonardo PersonalKonzept GmbH; Licharz GmbH; LOTTO Rheinland-Pfalz GmbH; Michelin Reifenwerke AG & Co. KGaA; Ministerium für Wirtschaft, Verkehr, Landwirtschaft und Weinbau; PFAFF Industriesysteme und Maschinen GmbH; Pfalzwerke AG; Provinzial Versicherung AG; Rheinland-Pfälzische Technische Universität Kaiserslautern-Landau (RPTU); robotspaceship; RPR1.; SCHOTT AG; SIMONA AG; SmartFactory KL e.V.; Sparkassenverband Rheinland-Pfalz; Städtetag Rheinland-Pfalz; SWR – Südwestrundfunk; Techniker Krankenkasse; Technische Hochschule Bingen; thyssenkrupp Rasselstein GmbH; TÜV Rheinland Berlin Brandenburg Pfalz e.V.; Universität Koblenz; Universität Trier; Vereinigte VR Bank Kur- und Rheinpfalz eG; vero – Verband der Bau- und Rohstoffindustrie; Villa Musica Rheinland-Pfalz; Vinzenz Pallotti University gGmbH; Westenergie AG; WHU – Otto Beisheim School of Management; Wilhelm Faber GmbH; ZDF – Zweites Deutsches Fernsehen; Alexianer GmbH
A9: Wissenschaft / Bildung / Hochschule | B9: 47 | C9: Aturas GmbH; Barmherzige Brüder Trier gGmbH; BASF SE; Boehringer Ingelheim Pharma GmbH & Co. KG; BRICKMAKERS AG; Bundesagentur für Arbeit, Regionaldirektion Rheinland-Pfalz-Saarland; Caritasverband für die Diözese Speyer e.V.; Deutsche Universität für Verwaltungswissenschaften Speyer | D9: Aturas GmbH; Barmherzige Brüder Trier gGmbH; BASF SE; Boehringer Ingelheim Pharma GmbH & Co. KG; BRICKMAKERS AG; Bundesagentur für Arbeit, Regionaldirektion Rheinland-Pfalz-Saarland; Caritasverband für die Diözese Speyer e.V.; Deutsche Universität für Verwaltungswissenschaften Speyer; Deutscher Gewerkschaftsbund (DGB) Rheinland-Pfalz/Saarland; Duale Hochschule Rheinland-Pfalz; Empolis Information Management GmbH; Evangelische Kirche der Pfalz; GLOBUS Markthallen Holding GmbH & Co. KG; Handwerkskammern Rheinland-Pfalz; Hochschule für Gesellschaftsgestaltung (HfGG); Hochschule für Musik Mainz; Hochschule für Wirtschaft und Gesellschaft Ludwigshafen; Hochschule Kaiserslautern; Hochschule Koblenz; Hochschule Mainz; Hochschule Trier; Hochschule Worms; in.betrieb gGmbH; Investitions- und Strukturbank Rheinland-Pfalz (ISB); ITK Engineering GmbH; JOBS FOR MOMS UG; Johannes Gutenberg-Universität Mainz; Katholische Hochschule Mainz; Landkreistag Rheinland-Pfalz; Leonardo PersonalKonzept GmbH; Ministerium für Wirtschaft, Verkehr, Landwirtschaft und Weinbau; Rheinland-Pfälzische Technische Universität Kaiserslautern-Landau (RPTU); RPR1.; SCHOTT AG; SmartFactory KL e.V.; Sparkassenverband Rheinland-Pfalz; Staatskanzlei des Landes Rheinland-Pfalz; Städtetag Rheinland-Pfalz; SWR – Südwestrundfunk; Technische Hochschule Bingen; Universität Koblenz; Universität Trier; Villa Musica Rheinland-Pfalz; Vinzenz Pallotti University gGmbH; WHU – Otto Beisheim School of Management; ZDF – Zweites Deutsches Fernsehen; Alexianer GmbH
A10: Dialog / Netzwerk / Verantwortung | B10: 24 | C10: 1. FSV Mainz 05 e.V.; AOK Rheinland-Pfalz/Saarland; Caritasverband für die Diözese Speyer e.V.; Deutsche Universität für Verwaltungswissenschaften Speyer; Entwicklungsagentur Rheinland-Pfalz e.V.; Erster FC Kaiserslautern GmbH & Co. KGaA; Evangelische Kirche der Pfalz; GLOBUS Markthallen Holding GmbH & Co. KG | D10: 1. FSV Mainz 05 e.V.; AOK Rheinland-Pfalz/Saarland; Caritasverband für die Diözese Speyer e.V.; Deutsche Universität für Verwaltungswissenschaften Speyer; Entwicklungsagentur Rheinland-Pfalz e.V.; Erster FC Kaiserslautern GmbH & Co. KGaA; Evangelische Kirche der Pfalz; GLOBUS Markthallen Holding GmbH & Co. KG; Hochschule für Gesellschaftsgestaltung (HfGG); Hochschule für Musik Mainz; IKK Südwest; Johannes Gutenberg-Universität Mainz; Katholische Hochschule Mainz; LOTTO Rheinland-Pfalz GmbH; RPR1.; Staatskanzlei des Landes Rheinland-Pfalz; SWR – Südwestrundfunk; Techniker Krankenkasse; Universität Koblenz; Universität Trier; Villa Musica Rheinland-Pfalz; Vinzenz Pallotti University gGmbH; ZDF – Zweites Deutsches Fernsehen; Alexianer GmbH
A11: Kultur / Medien / Öffentlichkeit | B11: 28 | C11: 1. FSV Mainz 05 e.V.; AOK Rheinland-Pfalz/Saarland; Bundesagentur für Arbeit, Regionaldirektion Rheinland-Pfalz-Saarland; Caritasverband für die Diözese Speyer e.V.; Deutsche Telekom AG; Deutsche Universität für Verwaltungswissenschaften Speyer; Entwicklungsagentur Rheinland-Pfalz e.V.; Erster FC Kaiserslautern GmbH & Co. KGaA | D11: 1. FSV Mainz 05 e.V.; AOK Rheinland-Pfalz/Saarland; Bundesagentur für Arbeit, Regionaldirektion Rheinland-Pfalz-Saarland; Caritasverband für die Diözese Speyer e.V.; Deutsche Telekom AG; Deutsche Universität für Verwaltungswissenschaften Speyer; Entwicklungsagentur Rheinland-Pfalz e.V.; Erster FC Kaiserslautern GmbH & Co. KGaA; Evangelische Kirche der Pfalz; GLOBUS Markthallen Holding GmbH & Co. KG; Hochschule für Gesellschaftsgestaltung (HfGG); Hochschule für Musik Mainz; Hochschule Mainz; IKK Südwest; Johannes Gutenberg-Universität Mainz; Katholische Hochschule Mainz; LOTTO Rheinland-Pfalz GmbH; robotspaceship; RPR1.; Staatskanzlei des Landes Rheinland-Pfalz; Städtetag Rheinland-Pfalz; SWR – Südwestrundfunk; Techniker Krankenkasse; Universität Koblenz; Universität Trier; Villa Musica Rheinland-Pfalz; Vinzenz Pallotti University gGmbH; ZDF – Zweites Deutsches Fernsehen

Sheet Keyword_Dictionary
A1: keyword_family | B1: keywords
A2: KI / Digital | B2: KI; Künstliche Intelligenz; Artificial Intelligence; Digitalisierung; digital; Daten; Data; Software; IT; Technologie; Plattform; Cyber; Automatisierung; Industrie 4.0; Verwaltung
A3: Innovation / Transfer | B3: Innovation; innovativ; Forschung; Entwicklung; Transfer; Zukunft; Pilot; Geschäftsmodell; Start-up; Startup; Expertise; Fortschritt; Fortschritte; Wissen
A4: Nachhaltigkeit / Klima / Energie | B4: Nachhaltigkeit; nachhaltig; Klima; Klimaanpassung; Umwelt; Energie; Netze; Versorgungssicherheit; Greentech; Kreislauf; Ressourcenschonung; Ersatzbaustoff; Land; Stadt
A5: Gesundheit / Pflege / Sozialwirtschaft | B5: Gesundheit; Gesundheitsversorgung; Medizin; Pflege; Sozialwirtschaft; Krankenhaus; Krankenhäuser; Prävention; Versorgung; Betreuung; Teilhabe; Patienten; Humanmedizin; Tiergesundheit; Senioren
A6: Fachkräfte / Arbeit / Qualifizierung | B6: Fachkräfte; Qualifizierung; Ausbildung; Weiterbildung; Arbeitsmarkt; Beschäftigung; Personal; Mitarbeiter; Mitarbeitende; Arbeitgeber; Produktivität; lebenslanges Lernen
A7: Bau / Raum / Infrastruktur | B7: Bau; Bauen; Architektur; Wohnraum; Stadt; Raum; Infrastruktur; Immobilien; Baukultur; Planung; Genehmigung; Ersatzbaustoff; Verkehr
A8: Wirtschaft / Mittelstand / Standort | B8: Wirtschaft; Standort; Unternehmen; Mittelstand; Industrie; Wettbewerbsfähigkeit; Investition; Kapital; Wachstum; Produktivität; Transformation; Förderung; Finanzierung
A9: Wissenschaft / Bildung / Hochschule | B9: Wissenschaft; Hochschule; Forschungseinrichtungen; Bildung; Studium; Universität; Weiterbildung; Wissen; Transfer; Qualifizierung
A10: Dialog / Netzwerk / Verantwortung | B10: Dialog; Vernetzung; Austausch; Plattform; Kooperation; Zusammenarbeit; Verantwortung; Netzwerk; Meinungsaustausch; gesellschaftlich; Zusammenhalt
A11: Kultur / Medien / Öffentlichkeit | B11: Kultur; Medien; Öffentlichkeit; Kreativwirtschaft; Musik; Standortidentität; Region; gesellschaftliche Identifikation; Demokratie; Zusammenhalt

Sheet SCIP_Role_Constraint_Readme
A1: Section | B1: Content
A2: Goal | B2: Reduce university/academic dominance by giving each actor role one normalized total mass. If a role has n members, each member contributes 1/n. Therefore SUM(role member weights)=1 for every role.
A3: Primary formula | B3: member_role_weight(r) = 1 / count_members_in_role(r)
A4: Candidate formula | B4: candidate_pair_mass = 1/count(role_a) + 1/count(role_b)
A5: Weighted objective option | B5: balanced_score = base_support_score * AVERAGE(role_multiplier(role_a), role_multiplier(role_b)), where role_multiplier = average_role_count / role_count. This downweights overrepresented roles and boosts underrepresented roles.
A6: SCIP exposure constraint option | B6: For each role r: SUM(selected_x_c * (1[role_a=r] + 1[role_b=r]) / count_members_in_role(r)) <= role_mass_budget. Default budget in Role_Weights is 1.0; tighten academic_support if needed.
A7: Practical recommendation | B7: Use role_balanced_score in the objective AND add an academic/support share cap. The weighted score reduces generic university pull; the exposure constraint makes the portfolio auditable.
A8: Code mapping | B8: Candidate_Role_Balance columns K/O can be used directly: K = pair_role_mass, M = role_balanced_score, O = selected_x * pair_role_mass.
A9: Important warning | B9: If the solver treats lower coefficients as cheaper in a <= constraint, inverse weights alone can make large roles easier to select. Use inverse weights for score balancing/reporting; use explicit role caps for hard limits.

Sheet Actor_Source_Profiles
A1: Member | B1: Source URL | C1: Source Type | D1: Crawl Priority | E1: Crawler Difficulty | F1: Why it matters for SOR | G1: Current crawler risk | H1: Recommended crawl strategy | I1: Follow patterns | J1: Extract sections / signals | K1: Keyword families | L1: Status | M1: Source notes
A2: Continental AG | B2: https://www.continental.com/de/presse/?tabs%5B80284%5D=80285 | C2: Corporate press portal / tabbed press overview | D2: Very high | E2: Medium | F2: Strong implementation actor; press portal links to press releases, events, studies, videos, mobility studies, technology/product topics. | G2: Naive crawler may read only the top navigation or miss tabbed/nested sections; useful content starts much lower on the page. | H2: Normalize away tab anchor/query when needed, then explicitly follow press-release, event, studies/publications, stories, sustainability, product/technology links. Depth 2. | I2: pressemitteilungen; konzernthemen; produkte-technologien; messen-events; studien-publikationen; stories; nachhaltigkeit; mobilitaetsstudien | J2: Pressemeldungen; Aktuelle Meldungen; Messen & Events; Continental-Mobilitätsstudien; Bilder & Videos; Pressekontakte | K2: Mobility; logistics; smart tires; sustainability; industry; digital; innovation; materials; events | L2: Added | M2: User supplied URL; visible page contains press portal structure and current press/event/study sections.
A3: Boehringer Ingelheim | B3: https://www.boehringer-ingelheim.com/de/presse | C3: Pharma press portal / German press hub | D3: Very high | E3: High | F3: Major RLP pharma/research actor; relevant for health, life sciences, R&D, animal health, innovation, Standortpolitik. | G3: Direct parsing may fail or return almost no text because of JS/bot protection; search engine snippets still show dated press releases. | H3: Use sitemap/search-index discovery, RSS if available, cached snippets only as fallback, and allow headless/browser rendering if compliant. Follow known press-release path. | I3: de/presse/pressemitteilungen; de/presse/pressematerial; pressemitteilungen; innovation; pharmastrategie; jugend-forscht; standort | J3: Pressemitteilungen; Pressematerial; German local/standort news; research/innovation policy signals | K3: Health; pharma; R&D; innovation; education; Standort; animal health; patients; clinical pipeline | L3: Added | M3: Page is search-visible but hard for basic crawlers; should not be dropped just because HTML extraction is poor.
A4: Boehringer Ingelheim | B4: https://www.boehringer-ingelheim.com/media-stories | C4: Global media & stories hub | D4: High | E4: High | F4: Captures international narratives, press releases, stories, newsbits and downloadable press material; useful for broader strategic framing. | G4: Simple crawler may see blank/near-empty content or bot-protection incident; important links may be rendered dynamically. | H4: Use discovery paths for /media-stories/press-releases, /media-stories/stories, /media-stories/newsbits, /media-stories/press-material. Use title/date extraction. | I4: media-stories; press-releases; stories; newsbits; press-material; animal-health; prescription-medicine; partnering | J4: Press releases; Stories; Newsbits; Press Material; corporate news; partner signals | K4: Health; animal health; pharma; patients; partnering; research; integrated care; innovation | L4: Added | M4: User supplied URL; search results describe it as a hub for latest press releases, news, background stories and press material.
A5: Bauern- und Winzerverband Rheinland-Pfalz Süd e.V. | B5: https://www.bwv-rlp.de/ | C5: Association homepage / press + current affairs | D5: High | E5: Low to medium | F5: Strong sector/context actor for agriculture, wine, rural economy, regulation, subsidies, climate/soil, labor and seasonal workers. | G5: Homepage is easy HTML, but useful signals are distributed across press archive, Aktuelles, Fachabteilungen, Termine, downloads and member information. | H5: Crawl homepage plus menu categories. Follow Presse, Archiv, Aktuelles, Termine, Fachabteilungen, Download, Infodienst. Depth 2. | I5: presse; archiv; aktuelles; termine; fachabteilungen; lav; download; rundschreiben; infodienst; stellenangebote | J5: Aktuelles; Presse posts; Termine; Fachabteilungen; subsidies; minimum wage; animal welfare; soil management; alternative drives | K5: Agriculture; wine; rural space; labor; regulation; climate; soil; animal welfare; funding; energy/alternative drives | L5: Added | M5: Visible HTML includes current items and press/category structure.
A6: JOBS FOR MOMS | B6: https://jobsformoms.de/de-de/blog-posts | C6: Blog / thought-leadership feed | D6: Medium to high | E6: High | F6: Useful for Fachkräfte, female talent, Vereinbarkeit, New Work and family-friendly labor-market innovation. | G6: Direct extraction may return zero lines; likely dynamic rendering or non-standard blog feed. A simple crawler may falsely mark it empty. | H6: Use rendered/headless extraction or sitemap discovery. Follow article links from blog feed; capture title, date, tags and full body when available. | I6: blog-posts; blog; news; artikel; jobs; moms; vereinbarkeit; neue-arbeit; fachkraefte; muetter; familienfreundlich | J6: Blog titles; labor-market opinions; employer practice; Vereinbarkeit; Delete Work/new work narratives | K6: Fachkräfte; labor market; women; mothers; work design; New Work; inclusion; employer branding | L6: Added | M6: User supplied URL; search index shows blog content even though direct HTML extraction is empty.
A7: Bauern- und Winzerverband Rheinland-Pfalz Süd e.V. | B7: https://www.bwv-rlp.de/category/mitglieder/infodienst/ | C7: Association member infodienst / category archive | D7: Very high | E7: Low | F7: Very strong live sector feed for agriculture and wine: regulations, animal welfare, organic market, EU wine policy, subsidies, liquidity, packaging law and farm operations. | G7: Crawler may stay on homepage or press archive and miss this member-only category archive; page has lots of navigation but the article list is clean and dated. | H7: Seed this category directly. Parse title, date, category and teaser; follow each article link; also follow older-post pagination and category tags such as Vieh und Fleisch, Öko, Weinbau, Aktuelle Agrarpolitik. | I7: category/mitglieder/infodienst; /category/; /page/; vieh-und-fleisch; oeko; weinbau; aktuelle-agrarpolitik; weiterlesen | J7: Infodienst posts; Rundschreiben; title/date/category/excerpt; full article pages; older-post pagination | K7: Agriculture; wine; regulation; subsidies; animal welfare; organic market; energy costs; EU policy; packaging; liquidity; rural economy | L7: Added | M7: User supplied URL; visible page contains dated Infodienst posts such as THKG, ASP zones, ITW, Bio-Markt, Rentenbank liquidity, Widerrufsbutton, EU wine package, PPWR and Ökoregelungen.
A8: Investitions- und Strukturbank Rheinland-Pfalz (ISB) | B8: https://isb.rlp.de/aktuelles/news.html | C8: Public development bank / news + funding + venture capital feed | D8: Very high | E8: Medium | F8: Key financing and transformation anchor for RLP: venture capital, startup success stories, housing funding, reconstruction aid, mobility financing, infrastructure and innovation transfer. | G8: The page is very long and archive-heavy; naive crawlers may truncate, overread old entries or fail to isolate the current News card list. | H8: Start at the News section, keep the newest 12-18 months, parse each card headline/date/category/teaser, follow detail links, and weight categories such as Venture Capital, Success Story, Fördernews, Presse and Unwetterhilfen. | I8: aktuelles/news; venture-capital; success-story; foerdernews; presse; unwetterhilfen; gruenden; darlehen; beteiligung | J8: News cards; dates; categories; success stories; funding announcements; VC participations; housing/infrastructure projects; event/dialog formats | K8: Financing; venture capital; startups; innovation; KI; logistics; social housing; mobility; reconstruction; sustainability; infrastructure; Mittelstand | L8: Added | M8: User supplied URL; visible page lists current 2026 items such as KfW Award Gründen, ISB Beteiligung an Loady, LigniLabs, Wiederaufbau, Crateflow KI supply-chain planning and social housing.
A9: ITK Engineering GmbH | B9: https://www.itk-engineering.de/unternehmen/events/ | C9: Engineering / technology events feed | D9: High | E9: Low to medium | F9: Strong technology and implementation actor for mobility, medtech, robotics, software-defined vehicles, cyber security, data engineering, AI and industry events; useful for detecting where ITK is actively convening or presenting expertise. | G9: A crawler may read the navigation and miss the structured event cards, or stop after the first visible results; event pages may require following detail links and pagination / "Mehr anzeigen". | H9: Seed the events page directly. Parse event date range, event type, location, title and teaser; follow each event detail link; keep upcoming/current events and map them to technology domains. | I9: unternehmen/events; events; fachmesse; fachevent; vortrag; webinar; recruitingevent; medizintechnik; medical-robotics; innotrans; landtechnik; ivt-expo | J9: Events; Fachmesse; Fachevent; Vortrag; Webinar; date ranges; locations; industry domains; detail event pages; contact/event owner | K9: AI; data engineering; cyber security; digital twin; robotics; software-defined vehicle; medtech; digital health; mobility; industry; logistics; recruiting; events | L9: Added | M9: User supplied URL; visible page contains dated 2026 event cards including European Medical Device Summit, iVT Expo, Science for Lunch, Hamlyn Symposium Medical Robotics, FinnMETKO, InnoTrans, Innovation Forum Medizintechnik and VDI Land.Technik AgEng.
A10: Handwerkskammer der Pfalz | B10: https://www.hwk-pfalz.de/artikel/aktuelle-pressemitteilungen-51,1383,5113.html | C10: Chamber press archive / current press releases | D10: Very high | E10: Low | F10: Very strong regional craft-sector signal feed for training, apprenticeships, Weiterbildungsprogramme, Konjunktur, innovation awards, Landtagswahl policy demands and Mittelstand competitiveness. | G10: Crawler may overread navigation, miss the article list region, or fail to follow "mehr lesen" links into full press releases; archive link and older entries need freshness filtering. | H10: Seed this press list directly. Extract date, headline, teaser and article URL; follow "mehr lesen" links; also crawl archive and events/newsletter only as secondary sources. Apply a 12-18 month freshness window. | I10: aktuelle-pressemitteilungen; pressemitteilungen; presse-medien; archiv-pressemitteilungen; mehr-lesen; ausbildung; weiterbildung; konjunktur; landtagswahl; innovation | J10: Aktuelle Pressemitteilungen; dates; teasers; full press releases; archive; Ausbildung; Weiterbildung; Konjunktur; policy demands; innovation awards | K10: Handwerk; Mittelstand; Ausbildung; Fachkräfte; Weiterbildung; Digitalisierung; Technik; Innovation; Konjunktur; Politik; Wettbewerbsfähigkeit; PV; Nachhaltigkeit | L10: Added | M10: User supplied URL; visible page contains 2026 press items on Ferienwerkstätten, Frühjahrsumfrage Konjunktur, Landtagswahl, SOLARco.shoe innovation award, Weiterbildung, Betriebswirt and Ausbildung.
A11: 1. FSV Mainz 05 e.V. | B11: https://www.mainz05.de/nachhaltigkeit | C11: Discovered source page | D11: Medium | E11: Medium | F11: Auto-discovered source-quality score 32; contains dated strategic/source-page signals. | G11: Auto-discovered; review after the next crawl. | H11: Crawl as ranked source first, follow dated article cards, publications and event links, then apply normal signal gates. | L11: Discovered
A12: 1. FSV Mainz 05 e.V. | B12: https://www.mainz05.de/EVENTS-IN-DER-MEWA-ARENA | C12: Discovered source page | D12: Medium | E12: Medium | F12: Auto-discovered source-quality score 34; contains dated strategic/source-page signals. | G12: Auto-discovered; review after the next crawl. | H12: Crawl as ranked source first, follow dated article cards, publications and event links, then apply normal signal gates. | L12: Discovered
A13: 1. FSV Mainz 05 e.V. | B13: https://www.mainz05.de/KLIMAFREUNDLICHE-EVENTS | C13: Discovered source page | D13: High | E13: Medium | F13: Auto-discovered source-quality score 44; contains dated strategic/source-page signals. | G13: Auto-discovered; review after the next crawl. | H13: Crawl as ranked source first, follow dated article cards, publications and event links, then apply normal signal gates. | L13: Discovered
A14: Architektenkammer Rheinland-Pfalz | B14: https://www.diearchitekten.org/presse | C14: Discovered source page | D14: High | E14: Medium | F14: Auto-discovered source-quality score 48; contains dated strategic/source-page signals. | G14: Auto-discovered; review after the next crawl. | H14: Crawl as ranked source first, follow dated article cards, publications and event links, then apply normal signal gates. | L14: Discovered
A15: Architektenkammer Rheinland-Pfalz | B15: https://www.diearchitekten.org/energie | C15: Discovered source page | D15: Medium | E15: Medium | F15: Auto-discovered source-quality score 26; contains dated strategic/source-page signals. | G15: Auto-discovered; review after the next crawl. | H15: Crawl as ranked source first, follow dated article cards, publications and event links, then apply normal signal gates. | L15: Discovered
A16: Architektenkammer Rheinland-Pfalz | B16: https://www.diearchitekten.org | C16: Discovered source page | D16: High | E16: Medium | F16: Auto-discovered source-quality score 48; contains dated strategic/source-page signals. | G16: Auto-discovered; review after the next crawl. | H16: Crawl as ranked source first, follow dated article cards, publications and event links, then apply normal signal gates. | L16: Discovered
A17: Barmherzige Brüder Trier gGmbH | B17: https://www.bbtgruppe.de/aktuelles | C17: Discovered source page | D17: High | E17: Medium | F17: Auto-discovered source-quality score 56; contains dated strategic/source-page signals. | G17: Auto-discovered; review after the next crawl. | H17: Crawl as ranked source first, follow dated article cards, publications and event links, then apply normal signal gates. | L17: Discovered
A18: Barmherzige Brüder Trier gGmbH | B18: https://www.bbtgruppe.de/news | C18: Discovered source page | D18: High | E18: Medium | F18: Auto-discovered source-quality score 56; contains dated strategic/source-page signals. | G18: Auto-discovered; review after the next crawl. | H18: Crawl as ranked source first, follow dated article cards, publications and event links, then apply normal signal gates. | L18: Discovered
A19: Barmherzige Brüder Trier gGmbH | B19: https://www.bbtgruppe.de/presse | C19: Discovered source page | D19: High | E19: Medium | F19: Auto-discovered source-quality score 56; contains dated strategic/source-page signals. | G19: Auto-discovered; review after the next crawl. | H19: Crawl as ranked source first, follow dated article cards, publications and event links, then apply normal signal gates. | L19: Discovered
A20: Barmherzige Brüder Trier gGmbH | B20: https://www.bbtgruppe.de/termine | C20: Discovered source page | D20: High | E20: Medium | F20: Auto-discovered source-quality score 56; contains dated strategic/source-page signals. | G20: Auto-discovered; review after the next crawl. | H20: Crawl as ranked source first, follow dated article cards, publications and event links, then apply normal signal gates. | L20: Discovered
